Workbook

Sheet Portada
C9: TRABAJO FINAL DE INGENIERÍA
C21: Alumno: Gómez Avellaneda, Javier
C22: Legajo: B00074234-T1
C23: Docentes: Scali, Jorge — Vilaboa, Pablo
C24: Comisión: 5° A - Turno Noche
C25: Localización: Ciudad Autónoma de Buenos Aires
C26: Email: javieralejandro.gomezavellaneda@alumnos.uai.edu.ar

Sheet Indice
D2: Índice
D4: Hipótesis
D5: Proyección de ventas
D6: Anexo de capacidad operativa
D7: Modelo de ingresos
D8: Estructura de costos fijos
D9: Estructura de costos variables
D10: Estructura de costos de RRHH
D11: Modelo de egresos
D12: Modelo de inversión
D13: Amortizaciones
D14: Presupuesto financiero
... D19: Plan de contingencia

Sheet Hipótesis
E1: Hipótesis
B3: 1 - Descripción del negocio
B4: ShopMetrics es una Empresa de Base Tecnológica (EBT) que desarrolla y explota software propio bajo modalidad SaaS para el comercio minorista. El negocio no consiste en la venta de dispositivos de conteo, sino en la provisión de un ecosistema de medición del embudo comercial del local: cuántas personas pasan por delante, cuántas se detienen frente a la vidriera, cuántas entran y cuántas compran. Los datos se capturan con infraestructura propia instalada en el local (sensores de vidriera y contadores de puerta que publican únicamente cantidades, nunca imágenes) y se integran de forma automática con el sistema de punto de venta que el comercio ya utiliza; sobre esa base, modelos propios de Machine Learning convierten la medición en decisiones de exhibición, dotación de personal y horario de atención. El servicio se contrata con un abono mensual y un cargo de alta e instalación por única vez, y los equipos se entregan en comodato, de modo que el comercio no afronta inversión inicial. Todos los importes de este presupuesto están expresados en dólares.
B7: 2 - Mercado meta
B8: Comercios minoristas de indumentaria, textiles y calzado, de entre uno y cinco locales y hasta nueve ocupados, con local a la calle y vidriera a la vereda, ubicados en los ejes comerciales de mayor densidad del AMBA, con cabecera en el eje Avellaneda.
B11: Comercios | C11: Gasto promedio anual (USD) | D11: Total mercado (USD)
B12: 3400 | C12: 480 | D12: =B12*C12 -> 1632000
B15: 3 - Participación del mercado
B16: Participación del 15% del segmento objetivo al cierre del tercer año, con una progresión de 3% el primer año, 8% el segundo y 15% el tercero. La progresión es moderada porque se trata de un emprendimiento que recién arranca y porque el segmento ya está acotado por la segmentación: son 3.400 comercios de un solo rubro en los ejes relevados de la Ciudad de Buenos Aires. El salto del segundo al tercer año duplica la cartera, por lo que requiere un esfuerzo adicional de promoción que se refleja en el modelo de egresos.
A22: Evolución de la participación en el mercado
A23: Año | B23: Cantidad | C23: Porcentaje | D23: Total (USD)
A24: 2026 | B24: 102 comercios | C24: 0.03 | D24: =C24*$D$12 -> 48960
A25: 2027 | B25: 272 comercios | C25: 0.08 | D25: =C25*$D$12 -> 130560
A26: 2028 | B26: 510 comercios | C26: 0.15 | D26: =C26*$D$12 -> 244800
B31: Detalle: el gasto promedio anual de USD 480 por comercio corresponde a lo que un comercio minorista chico destina hoy a software de gestión y analítica. Se toma como referencia la lista de precios pública de Fudo, uno de los siete sistemas de punto de venta con los que la plataforma se integra, cuyo plan de entrada se ubica en el orden de los USD 40 mensuales por sucursal. La cantidad de 3.400 comercios surge de aplicar la participación del rubro Indumentaria, textiles y calzado (24,3%) sobre los 14.083 locales ocupados que releva el Instituto de Estadística y Censos de la Ciudad de Buenos Aires en sus ejes comerciales.
B33: 4 - Otros datos
B35: Líneas de servicios
C36: VERSIONES DEL SERVICIO
C39: Alta e instalación | D39: Abono mensual
B40: PROFUNDIDAD DE LAS LÍNEAS DE SERVICIOS | C40: Plan Básico | D40: Plan Básico
C43: Plan Vidriera | D43: Plan Vidriera
C46: Plan Cadena | D46: Plan Cadena
B56: Lista de precios (USD)
B57: Servicio | C57: Precio | D57: Detalle | E57: Modalidad de cobro
B58: Alta e instalación Plan Básico | C58: 25 | D58: Por única vez. Alta remota: conexión con el sistema de punto de venta y verificación de datos. No requiere visita al local. | E58: Cobro por única vez
B59: Alta e instalación Plan Vidriera | C59: 60 | D59: Por única vez. Visita al local: montaje del sensor de vidriera y del contador de puerta, conexión del punto de venta y prueba del embudo. | E59: Cobro por única vez
B60: Alta e instalación Plan Cadena | C60: 250 | D60: Por única vez. Instalación en hasta cinco locales de una misma cadena. | E60: Cobro por única vez
B61: Abono Plan Básico | C61: 15 | D61: Analítica de ventas por hora, ticket promedio y rotación, a partir del punto de venta. Sin dispositivos de conteo. Es la puerta de entrada comercial. | E61: Cobro mensual
B62: Abono Plan Vidriera | C62: 29 | D62: Embudo completo del local: pasan, se detienen, entran y compran, más comparación anónima contra el rubro y alertas automáticas. Es el plan principal. | E62: Cobro mensual
B63: Abono Plan Cadena | C63: 79 | D63: Hasta cinco locales: embudo por local, comparación entre sucursales y consolidado de toda la red. | E63: Cobro mensual

Sheet Proy. ventas
B1: Proyección de ventas
B5: Evolución de la participación | G5: Justificación ingresos
B6: 2026 | C6: 2027 | D6: 2028 | G6: Los ingresos no se distribuyen de manera uniforme en el año. El abono es mensual y las suscripciones se acumulan: el comercio que se da de alta en marzo sigue pagando en abril, de modo que el ingreso recurrente crece mes a mes aunque la cantidad de altas se mantenga constante. Los cargos de alta e instalación, en cambio, se cobran por única vez en el mes en que ingresa el comercio. El primer trimestre de 2026 tiene pocas altas porque se destina a poner a punto el proceso de instalación sobre los primeros comercios del eje Avellaneda; a partir de allí la captación crece de manera sostenida.
B7: =Hipótesis!C24 -> 0.03 | C7: =Hipótesis!C25 -> 0.08 | D7: =Hipótesis!C26 -> 0.15
B8: =Hipótesis!D24 -> 48960 | C8: =Hipótesis!D25 -> 130560 | D8: =Hipótesis!D26 -> 244800
A10: .
A15: Proyección de ventas 2026
A16: Producto | B16: Precio | C16: Anual | E16: Enero | G16: Febrero | I16: Marzo | K16: Abril | M16: Mayo | O16: Junio | Q16: Julio | S16: Agosto | U16: Septiembre | W16: Octubre | Y16: Noviembre | AA16: Diciembre
C17: Cantidad | D17: Ingresos | E17: =F32/$D$32 -> 0 | G17: =H32/$D$32 -> 0.0061831951 | I17: =J32/$D$32 -> 0.016824043 | K17: =L32/$D$32 -> 0.027896276 | M17: =N32/$D$32 -> 0.05492978 | O17: =P32/$D$32 -> 0.069021713 | Q17: =R32/$D$32 -> 0.086181278 | S17: =T32/$D$32 -> 0.10473086 | U17: =V32/$D$32 -> 0.12232181 | W17: =X32/$D$32 -> 0.1429804 | Y17: =Z32/$D$32 -> 0.16076307 | AA17: =AB32/$D$32 -> 0.20816757
E18: Cantidad | F18: Ingresos | G18: Cantidad | H18: Ingresos | I18: Cantidad | J18: Ingresos | K18: Cantidad | L18: Ingresos | M18: Cantidad | N18: Ingresos | O18: Cantidad | P18: Ingresos | Q18: Cantidad | R18: Ingresos | S18: Cantidad | T18: Ingresos | U18: Cantidad | V18: Ingresos | W18: Cantidad | X18: Ingresos | Y18: Cantidad | Z18: Ingresos | AA18: Cantidad | AB18: Ingresos
A19: =Hipótesis!$B$58 -> Alta e instalación Plan Básico | B19: =Hipótesis!C58 -> 25 | C19: =E19+G19+I19+K19+M19+O19+Q19+S19+U19+W19+Y19+AA19 -> 30 | D19: =B19*C19 -> 750 | E19: 0 | F19: =E19*$B$19 -> 0 | G19: 1 | H19: =G19*$B$19 -> 25 | I19: 1 | J19: =I19*$B$19 -> 25 | K19: 2 | L19: =K19*$B$19 -> 50 | M19: 2 | N19: =M19*$B$19 -> 50 | O19: 3 | P19: =O19*$B$19 -> 75 | Q19: 3 | R19: =Q19*$B$19 -> 75 | S19: 3 | T19: =S19*$B$19 -> 75 | U19: 4 | V19: =U19*$B$19 -> 100 | W19: 4 | X19: =W19*$B$19 -> 100 | Y19: 4 | Z19: =Y19*$B$19 -> 100 | AA19: 3 | AB19: =AA19*$B$19 -> 75
A20: =Hipótesis!$B$59 -> Alta e instalación Plan Vidriera | B20: =Hipótesis!C59 -> 60 | C20: =E20+G20+I20+K20+M20+O20+Q20+S20+U20+W20+Y20+AA20 -> 62 | D20: =B20*C20 -> 3720 | E20: 0 | F20: =E20*$B$20 -> 0 | G20: 1 | H20: =G20*$B$20 -> 60 | I20: 3 | J20: =I20*$B$20 -> 180 | K20: 4 | L20: =K20*$B$20 -> 240 | M20: 5 | N20: =M20*$B$20 -> 300 | O20: 5 | P20: =O20*$B$20 -> 300 | Q20: 6 | R20: =Q20*$B$20 -> 360 | S20: 7 | T20: =S20*$B$20 -> 420 | U20: 7 | V20: =U20*$B$20 -> 420 | W20: 8 | X20: =W20*$B$20 -> 480 | Y20: 8 | Z20: =Y20*$B$20 -> 480 | AA20: 8 | AB20: =AA20*$B$20 -> 480
A21: =Hipótesis!$B$60 -> Alta e instalación Plan Cadena | B21: =Hipótesis!C60 -> 250 | C21: =E21+G21+I21+K21+M21+O21+Q21+S21+U21+W21+Y21+AA21 -> 10 | D21: =B21*C21 -> 2500 | E21: 0 | F21: =E21*$B$21 -> 0 | G21: 0 | H21: =G21*$B$21 -> 0 | I21: 0 | J21: =I21*$B$21 -> 0 | K21: 0 | L21: =K21*$B$21 -> 0 | M21: 1 | N21: =M21*$B$21 -> 250 | O21: 1 | P21: =O21*$B$21 -> 250 | Q21: 1 | R21: =Q21*$B$21 -> 250 | S21: 1 | T21: =S21*$B$21 -> 250 | U21: 1 | V21: =U21*$B$21 -> 250 | W21: 1 | X21: =W21*$B$21 -> 250 | Y21: 1 | Z21: =Y21*$B$21 -> 250 | AA21: 3 | AB21: =AA21*$B$21 -> 750
A22: =Hipótesis!$B$61 -> Abono Plan Básico | B22: =Hipótesis!C61 -> 15 | C22: =E22+G22+I22+K22+M22+O22+Q22+S22+U22+W22+Y22+AA22 -> 148 | D22: =B22*C22 -> 2220 | E22: =E19 -> 0 | F22: =E22*$B$22 -> 0 | G22: =E22+G19 -> 1 | H22: =G22*$B$22 -> 15 | I22: =G22+I19 -> 2 | J22: =I22*$B$22 -> 30 | K22: =I22+K19 -> 4 | L22: =K22*$B$22 -> 60 | M22: =K22+M19 -> 6 | N22: =M22*$B$22 -> 90 | O22: =M22+O19 -> 9 | P22: =O22*$B$22 -> 135 | Q22: =O22+Q19 -> 12 | R22: =Q22*$B$22 -> 180 | S22: =Q22+S19 -> 15 | T22: =S22*$B$22 -> 225 | U22: =S22+U19 -> 19 | V22: =U22*$B$22 -> 285 | W22: =U22+W19 -> 23 | X22: =W22*$B$22 -> 345 | Y22: =W22+Y19 -> 27 | Z22: =Y22*$B$22 -> 405 | AA22: =Y22+AA19 -> 30 | AB22: =AA22*$B$22 -> 450
A23: =Hipótesis!$B$62 -> Abono Plan Vidriera | B23: =Hipótesis!C62 -> 29 | C23: =E23+G23+I23+K23+M23+O23+Q23+S23+U23+W23+Y23+AA23 -> 299 | D23: =B23*C23 -> 8671 | E23: =E20 -> 0 | F23: =E23*$B$23 -> 0 | G23: =E23+G20 -> 1 | H23: =G23*$B$23 -> 29 | I23: =G23+I20 -> 4 | J23: =I23*$B$23 -> 116 | K23: =I23+K20 -> 8 | L23: =K23*$B$23 -> 232 | M23: =K23+M20 -> 13 | N23: =M23*$B$23 -> 377 | O23: =M23+O20 -> 18 | P23: =O23*$B$23 -> 522 | Q23: =O23+Q20 -> 24 | R23: =Q23*$B$23 -> 696 | S23: =Q23+S20 -> 31 | T23: =S23*$B$23 -> 899 | U23: =S23+U20 -> 38 | V23: =U23*$B$23 -> 1102 | W23: =U23+W20 -> 46 | X23: =W23*$B$23 -> 1334 | Y23: =W23+Y20 -> 54 | Z23: =Y23*$B$23 -> 1566 | AA23: =Y23+AA20 -> 62 | AB23: =AA23*$B$23 -> 1798
A24: =Hipótesis!$B$63 -> Abono Plan Cadena | B24: =Hipótesis!C63 -> 79 | C24: =E24+G24+I24+K24+M24+O24+Q24+S24+U24+W24+Y24+AA24 -> 38 | D24: =B24*C24 -> 3002 | E24: =E21 -> 0 | F24: =E24*$B$24 -> 0 | G24: =E24+G21 -> 0 | H24: =G24*$B$24 -> 0 | I24: =G24+I21 -> 0 | J24: =I24*$B$24 -> 0 | K24: =I24+K21 -> 0 | L24: =K24*$B$24 -> 0 | M24: =K24+M21 -> 1 | N24: =M24*$B$24 -> 79 | O24: =M24+O21 -> 2 | P24: =O24*$B$24 -> 158 | Q24: =O24+Q21 -> 3 | R24: =Q24*$B$24 -> 237 | S24: =Q24+S21 -> 4 | T24: =S24*$B$24 -> 316 | U24: =S24+U21 -> 5 | V24: =U24*$B$24 -> 395 | W24: =U24+W21 -> 6 | X24: =W24*$B$24 -> 474 | Y24: =W24+Y21 -> 7 | Z24: =Y24*$B$24 -> 553 | AA24: =Y24+AA21 -> 10 | AB24: =AA24*$B$24 -> 790
A32: Ingreso Total | D32: =SUM(D19:D31) -> 20863 | F32: =SUM(F19:F31) -> 0 | H32: =SUM(H19:H31) -> 129 | J32: =SUM(J19:J31) -> 351 | L32: =SUM(L19:L31) -> 582 | N32: =SUM(N19:N31) -> 1146 | P32: =SUM(P19:P31) -> 1440 | R32: =SUM(R19:R31) -> 1798 | T32: =SUM(T19:T31) -> 2185 | V32: =SUM(V19:V31) -> 2552 | X32: =SUM(X19:X31) -> 2983 | Z32: =SUM(Z19:Z31) -> 3354 | AB32: =SUM(AB19:AB31) -> 4343
C33: =C19 -> 30 | E33: =E19 -> 0 | G33: =G19 -> 1 | I33: =I19 -> 1 | K33: =K19 -> 2 | M33: =M19 -> 2 | O33: =O19 -> 3 | Q33: =Q19 -> 3 | S33: =S19 -> 3 | U33: =U19 -> 4 | W33: =W19 -> 4 | Y33: =Y19 -> 4 | AA33: =AA19 -> 3
C34: =C20 -> 62 | E34: =E20 -> 0 | G34: =G20 -> 1 | I34: =I20 -> 3 | K34: =K20 -> 4 | M34: =M20 -> 5 | O34: =O20 -> 5 | Q34: =Q20 -> 6 | S34: =S20 -> 7 | U34: =U20 -> 7 | W34: =W20 -> 8 | Y34: =Y20 -> 8 | AA34: =AA20 -> 8
C35: =C21 -> 10 | E35: =E21 -> 0 | G35: =G21 -> 0 | I35: =I21 -> 0 | K35: =K21 -> 0 | M35: =M21 -> 1 | O35: =O21 -> 1 | Q35: =Q21 -> 1 | S35: =S21 -> 1 | U35: =U21 -> 1 | W35: =W21 -> 1 | Y35: =Y21 -> 1 | AA35: =AA21 -> 3
C36: =SUM(C22:C25) -> 485 | E36: =SUM(E22:E25) -> 0 | G36: =SUM(G22:G25) -> 2 | I36: =SUM(I22:I25) -> 6 | K36: =SUM(K22:K25) -> 12 | M36: =SUM(M22:M25) -> 20 | O36: =SUM(O22:O25) -> 29 | Q36: =SUM(Q22:Q25) -> 39 | S36: =SUM(S22:S25) -> 50 | U36: =SUM(U22:U25) -> 62 | W36: =SUM(W22:W25) -> 75 | Y36: =SUM(Y22:Y25) -> 88 | AA36: =SUM(AA22:AA25) -> 102
C37: =SUM(C26:C30) -> 0 | E37: =SUM(E26:E30) -> 0 | G37: =SUM(G26:G30) -> 0 | I37: =SUM(I26:I30) -> 0 | K37: =SUM(K26:K30) -> 0 | M37: =SUM(M26:M30) -> 0 | O37: =SUM(O26:O30) -> 0 | Q37: =SUM(Q26:Q30) -> 0 | S37: =SUM(S26:S30) -> 0 | U37: =SUM(U26:U30) -> 0 | W37: =SUM(W26:W30) -> 0 | Y37: =SUM(Y26:Y30) -> 0 | AA37: =SUM(AA26:AA30) -> 0
C38: =C31 -> 0 | E38: =E31 -> 0 | G38: =G31 -> 0 | I38: =I31 -> 0 | K38: =K31 -> 0 | M38: =M31 -> 0 | O38: =O31 -> 0 | Q38: =Q31 -> 0 | S38: =S31 -> 0 | U38: =U31 -> 0 | W38: =W31 -> 0 | Y38: =Y31 -> 0 | AA38: =AA31 -> 0
A40: Capacidad operativa Kick off - Año 2026
A41: Comentarios | B41: * Se arranca con el equipo fundador y un técnico. En julio se suma un segundo vendedor para sostener el ritmo de altas del segundo semestre.
A42: Concepto | C42: Año cero - Kick off | E42: Año 2026
C43: Cantidad | E43: Enero | G43: Febrero | I43: Marzo | K43: Abril | M43: Mayo | O43: Junio | Q43: Julio | S43: Agosto | U43: Septiembre | W43: Octubre | Y43: Noviembre | AA43: Diciembre
A44: RRHH | C44: Gerente general | E44: Sin cambios | G44: Sin cambios | I44: Sin cambios | K44: Sin cambios | M44: Sin cambios | O44: Sin cambios | Q44: Sin cambios | S44: Sin cambios | U44: Sin cambios | W44: Sin cambios | Y44: Sin cambios | AA44: Sin cambios
C45: Gerente de sistemas | E45: Sin cambios | G45: Sin cambios | I45: Sin cambios | K45: Sin cambios | M45: Sin cambios | O45: Sin cambios | Q45: Sin cambios | S45: Sin cambios | U45: Sin cambios | W45: Sin cambios | Y45: Sin cambios | AA45: Sin cambios
C46: Desarrollador | E46: Sin cambios | G46: Sin cambios | I46: Sin cambios | K46: Sin cambios | M46: Sin cambios | O46: Sin cambios | Q46: Sin cambios | S46: Sin cambios | U46: Sin cambios | W46: Sin cambios | Y46: Sin cambios | AA46: Sin cambios
C47: Técnico de instalación y soporte | E47: Sin cambios | G47: Sin cambios | I47: Sin cambios | K47: Sin cambios | M47: Sin cambios | O47: Sin cambios | Q47: Sin cambios | S47: Sin cambios | U47: Sin cambios | W47: Sin cambios | Y47: Sin cambios | AA47: Sin cambios
C48: Vendedor | E48: Sin cambios | G48: Sin cambios | I48: Sin cambios | K48: Sin cambios | M48: Sin cambios | O48: Sin cambios | Q48: Vendedor (+1) | S48: Sin cambios | U48: Sin cambios | W48: Sin cambios | Y48: Sin cambios | AA48: Sin cambios
A62: Infraestructura | C62: Oficina | E62: Oficina (+1 alquiler) | G62: Sin cambios | I62: Sin cambios | K62: Sin cambios | M62: Sin cambios | O62: Sin cambios | Q62: Sin cambios | S62: Sin cambios | U62: Sin cambios | W62: Sin cambios | Y62: Sin cambios | AA62: Sin cambios
C63: Notebooks | E63: Notebooks (+3) | G63: Sin cambios | I63: Sin cambios | K63: Sin cambios | M63: Sin cambios | O63: Sin cambios | Q63: Notebooks (+1) | S63: Sin cambios | U63: Sin cambios | W63: Sin cambios | Y63: Sin cambios | AA63: Sin cambios
C64: Escritorios | E64: Escritorios (+2) | G64: Sin cambios | I64: Sin cambios | K64: Sin cambios | M64: Sin cambios | O64: Sin cambios | Q64: Sin cambios | S64: Sin cambios | U64: Sin cambios | W64: Sin cambios | Y64: Sin cambios | AA64: Sin cambios
C65: Sillas de escritorio | E65: Sillas de escritorio (+4) | G65: Sin cambios | I65: Sin cambios | K65: Sin cambios | M65: Sin cambios | O65: Sin cambios | Q65: Sin cambios | S65: Sin cambios | U65: Sin cambios | W65: Sin cambios | Y65: Sin cambios | AA65: Sin cambios
C66: 0 | E66: Sin cambios | G66: Sin cambios | I66: Sin cambios | K66: Sin cambios | M66: Sin cambios | O66: Sin cambios | Q66: Sin cambios | S66: Sin cambios | U66: Sin cambios | W66: Sin cambios | Y66: Sin cambios | AA66: Sin cambios
C67: 0 | E67: Sin cambios | G67: Sin cambios | I67: Sin cambios | K67: Sin cambios | M67: Sin cambios | O67: Sin cambios | Q67: Sin cambios | S67: Sin cambios | U67: Sin cambios | W67: Sin cambios | Y67: Sin cambios | AA67: Sin cambios
C68: 0 | E68: Sin cambios | G68: Sin cambios | I68: Sin cambios | K68: Sin cambios | M68: Sin cambios | O68: Sin cambios | Q68: Sin cambios | S68: Sin cambios | U68: Sin cambios | W68: Sin cambios | Y68: Sin cambios | AA68: Sin cambios
A69: Capital de trabajo | C69: Sensores de vidriera | E69: Sensores de vidriera (+30) | G69: Sin cambios | I69: Sin cambios | K69: Sensores de vidriera (+30) | M69: Sin cambios | O69: Sin cambios | Q69: Sensores de vidriera (+30) | S69: Sin cambios | U69: Sin cambios | W69: Sensores de vidriera (+30) | Y69: Sin cambios | AA69: Sin cambios
C70: Contadores de puerta | E70: Contadores de puerta (+30) | G70: Sin cambios | I70: Sin cambios | K70: Contadores de puerta (+30) | M70: Sin cambios | O70: Sin cambios | Q70: Contadores de puerta (+30) | S70: Sin cambios | U70: Sin cambios | W70: Contadores de puerta (+30) | Y70: Sin cambios | AA70: Sin cambios
C71: Gateways de conexión | E71: Gateways de conexión (+30) | G71: Sin cambios | I71: Sin cambios | K71: Gateways de conexión (+30) | M71: Sin cambios | O71: Sin cambios | Q71: Gateways de conexión (+30) | S71: Sin cambios | U71: Sin cambios | W71: Gateways de conexión (+30) | Y71: Sin cambios | AA71: Sin cambios
C72: Kits de montaje | E72: Kits de montaje (+30) | G72: Sin cambios | I72: Sin cambios | K72: Kits de montaje (+30) | M72: Sin cambios | O72: Sin cambios | Q72: Kits de montaje (+30) | S72: Sin cambios | U72: Sin cambios | W72: Kits de montaje (+30) | Y72: Sin cambios | AA72: Sin cambios
A78: Proyección de ventas 2027
A79: Producto | B79: Precio | C79: Anual | E79: Enero | G79: Febrero | I79: Marzo | K79: Abril | M79: Mayo | O79: Junio | Q79: Julio | S79: Agosto | U79: Septiembre | W79: Octubre | Y79: Noviembre | AA79: Diciembre
C80: Cantidad | D80: Ingresos | E80: =F95/$D$95 -> 0.053570075 | G80: =H95/$D$95 -> 0.058258562 | I80: =J95/$D$95 -> 0.062947049 | K80: =L95/$D$95 -> 0.067635536 | M80: =N95/$D$95 -> 0.072324024 | O80: =P95/$D$95 -> 0.081170226 | Q80: =R95/$D$95 -> 0.083824087 | S80: =T95/$D$95 -> 0.093036775 | U80: =V95/$D$95 -> 0.09493239 | W80: =X95/$D$95 -> 0.10414508 | Y80: =Z95/$D$95 -> 0.1107039 | AA80: =AB95/$D$95 -> 0.11745229
E81: Cantidad | F81: Ingresos | G81: Cantidad | H81: Ingresos | I81: Cantidad | J81: Ingresos | K81: Cantidad | L81: Ingresos | M81: Cantidad | N81: Ingresos | O81: Cantidad | P81: Ingresos | Q81: Cantidad | R81: Ingresos | S81: Cantidad | T81: Ingresos | U81: Cantidad | V81: Ingresos | W81: Cantidad | X81: Ingresos | Y81: Cantidad | Z81: Ingresos | AA81: Cantidad | AB81: Ingresos
A82: =Hipótesis!$B$58 -> Alta e instalación Plan Básico | B82: =Hipótesis!C58 -> 25 | C82: =E82+G82+I82+K82+M82+O82+Q82+S82+U82+W82+Y82+AA82 -> 51 | D82: =B82*C82 -> 1275 | E82: 4 | F82: =E82*$B$82 -> 100 | G82: 4 | H82: =G82*$B$82 -> 100 | I82: 4 | J82: =I82*$B$82 -> 100 | K82: 4 | L82: =K82*$B$82 -> 100 | M82: 4 | N82: =M82*$B$82 -> 100 | O82: 4 | P82: =O82*$B$82 -> 100 | Q82: 4 | R82: =Q82*$B$82 -> 100 | S82: 4 | T82: =S82*$B$82 -> 100 | U82: 4 | V82: =U82*$B$82 -> 100 | W82: 4 | X82: =W82*$B$82 -> 100 | Y82: 5 | Z82: =Y82*$B$82 -> 125 | AA82: 6 | AB82: =AA82*$B$82 -> 150
A83: =Hipótesis!$B$59 -> Alta e instalación Plan Vidriera | B83: =Hipótesis!C59 -> 60 | C83: =E83+G83+I83+K83+M83+O83+Q83+S83+U83+W83+Y83+AA83 -> 102 | D83: =B83*C83 -> 6120 | E83: 8 | F83: =E83*$B$83 -> 480 | G83: 8 | H83: =G83*$B$83 -> 480 | I83: 8 | J83: =I83*$B$83 -> 480 | K83: 8 | L83: =K83*$B$83 -> 480 | M83: 8 | N83: =M83*$B$83 -> 480 | O83: 8 | P83: =O83*$B$83 -> 480 | Q83: 9 | R83: =Q83*$B$83 -> 540 | S83: 9 | T83: =S83*$B$83 -> 540 | U83: 9 | V83: =U83*$B$83 -> 540 | W83: 9 | X83: =W83*$B$83 -> 540 | Y83: 9 | Z83: =Y83*$B$83 -> 540 | AA83: 9 | AB83: =AA83*$B$83 -> 540
A84: =Hipótesis!$B$60 -> Alta e instalación Plan Cadena | B84: =Hipótesis!C60 -> 250 | C84: =E84+G84+I84+K84+M84+O84+Q84+S84+U84+W84+Y84+AA84 -> 17 | D84: =B84*C84 -> 4250 | E84: 1 | F84: =E84*$B$84 -> 250 | G84: 1 | H84: =G84*$B$84 -> 250 | I84: 1 | J84: =I84*$B$84 -> 250 | K84: 1 | L84: =K84*$B$84 -> 250 | M84: 1 | N84: =M84*$B$84 -> 250 | O84: 2 | P84: =O84*$B$84 -> 500 | Q84: 1 | R84: =Q84*$B$84 -> 250 | S84: 2 | T84: =S84*$B$84 -> 500 | U84: 1 | V84: =U84*$B$84 -> 250 | W84: 2 | X84: =W84*$B$84 -> 500 | Y84: 2 | Z84: =Y84*$B$84 -> 500 | AA84: 2 | AB84: =AA84*$B$84 -> 500
A85: =Hipótesis!$B$61 -> Abono Plan Básico | B85: =Hipótesis!C61 -> 15 | C85: =E85+G85+I85+K85+M85+O85+Q85+S85+U85+W85+Y85+AA85 -> 676 | D85: =B85*C85 -> 10140 | E85: =AA22+E82 -> 34 | F85: =E85*$B$85 -> 510 | G85: =E85+G82 -> 38 | H85: =G85*$B$85 -> 570 | I85: =G85+I82 -> 42 | J85: =I85*$B$85 -> 630 | K85: =I85+K82 -> 46 | L85: =K85*$B$85 -> 690 | M85: =K85+M82 -> 50 | N85: =M85*$B$85 -> 750 | O85: =M85+O82 -> 54 | P85: =O85*$B$85 -> 810 | Q85: =O85+Q82 -> 58 | R85: =Q85*$B$85 -> 870 | S85: =Q85+S82 -> 62 | T85: =S85*$B$85 -> 930 | U85: =S85+U82 -> 66 | V85: =U85*$B$85 -> 990 | W85: =U85+W82 -> 70 | X85: =W85*$B$85 -> 1050 | Y85: =W85+Y82 -> 75 | Z85: =Y85*$B$85 -> 1125 | AA85: =Y85+AA82 -> 81 | AB85: =AA85*$B$85 -> 1215
A86: =Hipótesis!$B$62 -> Abono Plan Vidriera | B86: =Hipótesis!C62 -> 29 | C86: =E86+G86+I86+K86+M86+O86+Q86+S86+U86+W86+Y86+AA86 -> 1389 | D86: =B86*C86 -> 40281 | E86: =AA23+E83 -> 70 | F86: =E86*$B$86 -> 2030 | G86: =E86+G83 -> 78 | H86: =G86*$B$86 -> 2262 | I86: =G86+I83 -> 86 | J86: =I86*$B$86 -> 2494 | K86: =I86+K83 -> 94 | L86: =K86*$B$86 -> 2726 | M86: =K86+M83 -> 102 | N86: =M86*$B$86 -> 2958 | O86: =M86+O83 -> 110 | P86: =O86*$B$86 -> 3190 | Q86: =O86+Q83 -> 119 | R86: =Q86*$B$86 -> 3451 | S86: =Q86+S83 -> 128 | T86: =S86*$B$86 -> 3712 | U86: =S86+U83 -> 137 | V86: =U86*$B$86 -> 3973 | W86: =U86+W83 -> 146 | X86: =W86*$B$86 -> 4234 | Y86: =W86+Y83 -> 155 | Z86: =Y86*$B$86 -> 4495 | AA86: =Y86+AA83 -> 164 | AB86: =AA86*$B$86 -> 4756
A87: =Hipótesis!$B$63 -> Abono Plan Cadena | B87: =Hipótesis!C63 -> 79 | C87: =E87+G87+I87+K87+M87+O87+Q87+S87+U87+W87+Y87+AA87 -> 216 | D87: =B87*C87 -> 17064 | E87: =AA24+E84 -> 11 | F87: =E87*$B$87 -> 869 | G87: =E87+G84 -> 12 | H87: =G87*$B$87 -> 948 | I87: =G87+I84 -> 13 | J87: =I87*$B$87 -> 1027 | K87: =I87+K84 -> 14 | L87: =K87*$B$87 -> 1106 | M87: =K87+M84 -> 15 | N87: =M87*$B$87 -> 1185 | O87: =M87+O84 -> 17 | P87: =O87*$B$87 -> 1343 | Q87: =O87+Q84 -> 18 | R87: =Q87*$B$87 -> 1422 | S87: =Q87+S84 -> 20 | T87: =S87*$B$87 -> 1580 | U87: =S87+U84 -> 21 | V87: =U87*$B$87 -> 1659 | W87: =U87+W84 -> 23 | X87: =W87*$B$87 -> 1817 | Y87: =W87+Y84 -> 25 | Z87: =Y87*$B$87 -> 1975 | AA87: =Y87+AA84 -> 27 | AB87: =AA87*$B$87 -> 2133
A95: Ingreso Total | D95: =SUM(D82:D94) -> 79130 | F95: =SUM(F82:F94) -> 4239 | H95: =SUM(H82:H94) -> 4610 | J95: =SUM(J82:J94) -> 4981 | L95: =SUM(L82:L94) -> 5352 | N95: =SUM(N82:N94) -> 5723 | P95: =SUM(P82:P94) -> 6423 | R95: =SUM(R82:R94) -> 6633 | T95: =SUM(T82:T94) -> 7362 | V95: =SUM(V82:V94) -> 7512 | X95: =SUM(X82:X94) -> 8241 | Z95: =SUM(Z82:Z94) -> 8760 | AB95: =SUM(AB82:AB94) -> 9294
C96: =C82 -> 51 | E96: =E82 -> 4 | G96: =G82 -> 4 | I96: =I82 -> 4 | K96: =K82 -> 4 | M96: =M82 -> 4 | O96: =O82 -> 4 | Q96: =Q82 -> 4 | S96: =S82 -> 4 | U96: =U82 -> 4 | W96: =W82 -> 4 | Y96: =Y82 -> 5 | AA96: =AA82 -> 6
C97: =C83 -> 102 | E97: =E83 -> 8 | G97: =G83 -> 8 | I97: =I83 -> 8 | K97: =K83 -> 8 | M97: =M83 -> 8 | O97: =O83 -> 8 | Q97: =Q83 -> 9 | S97: =S83 -> 9 | U97: =U83 -> 9 | W97: =W83 -> 9 | Y97: =Y83 -> 9 | AA97: =AA83 -> 9
C98: =C84 -> 17 | E98: =E84 -> 1 | G98: =G84 -> 1 | I98: =I84 -> 1 | K98: =K84 -> 1 | M98: =M84 -> 1 | O98: =O84 -> 2 | Q98: =Q84 -> 1 | S98: =S84 -> 2 | U98: =U84 -> 1 | W98: =W84 -> 2 | Y98: =Y84 -> 2 | AA98: =AA84 -> 2
C99: =SUM(C85:C88) -> 2281 | E99: =SUM(E85:E88) -> 115 | G99: =SUM(G85:G88) -> 128 | I99: =SUM(I85:I88) -> 141 | K99: =SUM(K85:K88) -> 154 | M99: =SUM(M85:M88) -> 167 | O99: =SUM(O85:O88) -> 181 | Q99: =SUM(Q85:Q88) -> 195 | S99: =SUM(S85:S88) -> 210 | U99: =SUM(U85:U88) -> 224 | W99: =SUM(W85:W88) -> 239 | Y99: =SUM(Y85:Y88) -> 255 | AA99: =SUM(AA85:AA88) -> 272
C100: =SUM(C89:C93) -> 0 | E100: =SUM(E89:E93) -> 0 | G100: =SUM(G89:G93) -> 0 | I100: =SUM(I89:I93) -> 0 | K100: =SUM(K89:K93) -> 0 | M100: =SUM(M89:M93) -> 0 | O100: =SUM(O89:O93) -> 0 | Q100: =SUM(Q89:Q93) -> 0 | S100: =SUM(S89:S93) -> 0 | U100: =SUM(U89:U93) -> 0 | W100: =SUM(W89:W93) -> 0 | Y100: =SUM(Y89:Y93) -> 0 | AA100: =SUM(AA89:AA93) -> 0
C101: =C94 -> 0 | E101: =E94 -> 0 | G101: =G94 -> 0 | I101: =I94 -> 0 | K101: =K94 -> 0 | M101: =M94 -> 0 | O101: =O94 -> 0 | Q101: =Q94 -> 0 | S101: =S94 -> 0 | U101: =U94 -> 0 | W101: =W94 -> 0 | Y101: =Y94 -> 0 | AA101: =AA94 -> 0
A103: Capacidad operativa - Año 2027
A104: Comentarios | B104: * En enero se contratará un auxiliar de soporte que trabajará con horarios rotativos en conjunto con el anterior empleado para cubrir una mayor franja horaria de soporte. * En marzo se contratará un auxiliar de ventas para poder cumplir con los objetivos del nuevo año. * Capital de trabajo: se seguira incrementando el stock de sensores para cubrir las instalaciones de los nuevos clientes y posibles fallos que puedan suceder de clientes ya existentes.
C105: Concepto | E105: Enero | G105: Febrero | I105: Marzo | K105: Abril | M105: Mayo | O105: Junio | Q105: Julio | S105: Agosto | U105: Septiembre | W105: Octubre | Y105: Noviembre | AA105: Diciembre
A106: RRHH | C106: Gerente general | E106: Sin cambios | G106: Sin cambios | I106: Sin cambios | K106: Sin cambios | M106: Sin cambios | O106: Sin cambios | Q106: Sin cambios | S106: Sin cambios | U106: Sin cambios | W106: Sin cambios | Y106: Sin cambios | AA106: Sin cambios
C107: Gerente de sistemas | E107: Sin cambios | G107: Sin cambios | I107: Sin cambios | K107: Sin cambios | M107: Sin cambios | O107: Sin cambios | Q107: Sin cambios | S107: Sin cambios | U107: Sin cambios | W107: Sin cambios | Y107: Sin cambios | AA107: Sin cambios
C108: Desarrollador | E108: Sin cambios | G108: Sin cambios | I108: Sin cambios | K108: Sin cambios | M108: Sin cambios | O108: Sin cambios | Q108: Sin cambios | S108: Sin cambios | U108: Sin cambios | W108: Sin cambios | Y108: Sin cambios | AA108: Sin cambios
C109: Técnico de instalación y soporte | E109: Sin cambios | G109: Sin cambios | I109: Sin cambios | K109: Sin cambios | M109: Sin cambios | O109: Sin cambios | Q109: Sin cambios | S109: Sin cambios | U109: Técnico de instalación y soporte (+1) | W109: Sin cambios | Y109: Sin cambios | AA109: Sin cambios
C110: Vendedor | E110: Vendedor (+1) | G110: Sin cambios | I110: Sin cambios | K110: Sin cambios | M110: Sin cambios | O110: Sin cambios | Q110: Sin cambios | S110: Sin cambios | U110: Sin cambios | W110: Sin cambios | Y110: Sin cambios | AA110: Sin cambios
A124: Infraestructura | C124: Oficina | E124: Sin cambios | G124: Sin cambios | I124: Sin cambios | K124: Sin cambios | M124: Sin cambios | O124: Sin cambios | Q124: Sin cambios | S124: Sin cambios | U124: Sin cambios | W124: Sin cambios | Y124: Sin cambios | AA124: Sin cambios
C125: Notebooks | E125: Notebooks (+1) | G125: Sin cambios | I125: Notebooks (+1) | K125: Sin cambios | M125: Sin cambios | O125: Sin cambios | Q125: Sin cambios | S125: Sin cambios | U125: Sin cambios | W125: Sin cambios | Y125: Sin cambios | AA125: Sin cambios
C126: Escritorios | E126: Escritorios (+1) | G126: Sin cambios | I126: Sin cambios | K126: Sin cambios | M126: Sin cambios | O126: Sin cambios | Q126: Sin cambios | S126: Sin cambios | U126: Sin cambios | W126: Sin cambios | Y126: Sin cambios | AA126: Sin cambios
C127: Sillas de escritorio | E127: Sillas de escritorio (+2) | G127: Sin cambios | I127: Sin cambios | K127: Sin cambios | M127: Sin cambios | O127: Sin cambios | Q127: Sin cambios | S127: Sin cambios | U127: Sin cambios | W127: Sin cambios | Y127: Sin cambios | AA127: Sin cambios
C128: 0 | E128: Sin cambios | G128: Sin cambios | I128: Sin cambios | K128: Sin cambios | M128: Sin cambios | O128: Sin cambios | Q128: Sin cambios | S128: Sin cambios | U128: Sin cambios | W128: Sin cambios | Y128: Sin cambios | AA128: Sin cambios
C129: 0 | E129: Sin cambios | G129: Sin cambios | I129: Sin cambios | K129: Sin cambios | M129: Sin cambios | O129: Sin cambios | Q129: Sin cambios | S129: Sin cambios | U129: Sin cambios | W129: Sin cambios | Y129: Sin cambios | AA129: Sin cambios
C130: 0 | E130: Sin cambios | G130: Sin cambios | I130: Sin cambios | K130: Sin cambios | M130: Sin cambios | O130: Sin cambios | Q130: Sin cambios | S130: Sin cambios | U130: Sin cambios | W130: Sin cambios | Y130: Sin cambios | AA130: Sin cambios
A131: Capital de trabajo | C131: Sensores de vidriera | E131: Sensores de vidriera (+50) | G131: Sin cambios | I131: Sensores de vidriera (+50) | K131: Sin cambios | M131: Sin cambios | O131: Sensores de vidriera (+50) | Q131: Sin cambios | S131: Sin cambios | U131: Sensores de vidriera (+50) | W131: Sin cambios | Y131: Sin cambios | AA131: Sin cambios
C132: Contadores de puerta | E132: Contadores de puerta (+50) | G132: Sin cambios | I132: Contadores de puerta (+50) | K132: Sin cambios | M132: Sin cambios | O132: Contadores de puerta (+50) | Q132: Sin cambios | S132: Sin cambios | U132: Contadores de puerta (+50) | W132: Sin cambios | Y132: Sin cambios | AA132: Sin cambios
C133: Gateways de conexión | E133: Gateways de conexión (+50) | G133: Sin cambios | I133: Gateways de conexión (+50) | K133: Sin cambios | M133: Sin cambios | O133: Gateways de conexión (+50) | Q133: Sin cambios | S133: Sin cambios | U133: Gateways de conexión (+50) | W133: Sin cambios | Y133: Sin cambios | AA133: Sin cambios
C134: Kits de montaje | E134: Kits de montaje (+50) | G134: Sin cambios | I134: Kits de montaje (+50) | K134: Sin cambios | M134: Sin cambios | O134: Kits de montaje (+50) | Q134: Sin cambios | S134: Sin cambios | U134: Kits de montaje (+50) | W134: Sin cambios | Y134: Sin cambios | AA134: Sin cambios
A140: Proyección de ventas 2028
A141: Producto | B141: Precio | C141: Anual | E141: Enero | G141: Febrero | I141: Marzo | K141: Abril | M141: Mayo | O141: Junio | Q141: Julio | S141: Agosto | U141: Septiembre | W141: Octubre | Y141: Noviembre | AA141: Diciembre
C142: Cantidad | D142: Ingresos | E142: =F157/$D$157 -> 0.062919018 | G142: =H157/$D$157 -> 0.066642924 | I142: =J157/$D$157 -> 0.07036683 | K142: =L157/$D$157 -> 0.074090736 | M142: =N157/$D$157 -> 0.077814642 | O142: =P157/$D$157 -> 0.081538548 | Q142: =R157/$D$157 -> 0.085262454 | S142: =T157/$D$157 -> 0.08898636 | U142: =V157/$D$157 -> 0.092710266 | W142: =X157/$D$157 -> 0.096434172 | Y142: =Z157/$D$157 -> 0.10015808 | AA142: =AB157/$D$157 -> 0.10307597
E143: Cantidad | F143: Ingresos | G143: Cantidad | H143: Ingresos | I143: Cantidad | J143: Ingresos | K143: Cantidad | L143: Ingresos | M143: Cantidad | N143: Ingresos | O143: Cantidad | P143: Ingresos | Q143: Cantidad | R143: Ingresos | S143: Cantidad | T143: Ingresos | U143: Cantidad | V143: Ingresos | W143: Cantidad | X143: Ingresos | Y143: Cantidad | Z143: Ingresos | AA143: Cantidad | AB143: Ingresos
A144: =Hipótesis!$B$58 -> Alta e instalación Plan Básico | B144: =Hipótesis!C58 -> 25 | C144: =E144+G144+I144+K144+M144+O144+Q144+S144+U144+W144+Y144+AA144 -> 71 | D144: =B144*C144 -> 1775 | E144: 6 | F144: =E144*$B$144 -> 150 | G144: 6 | H144: =G144*$B$144 -> 150 | I144: 6 | J144: =I144*$B$144 -> 150 | K144: 6 | L144: =K144*$B$144 -> 150 | M144: 6 | N144: =M144*$B$144 -> 150 | O144: 6 | P144: =O144*$B$144 -> 150 | Q144: 6 | R144: =Q144*$B$144 -> 150 | S144: 6 | T144: =S144*$B$144 -> 150 | U144: 6 | V144: =U144*$B$144 -> 150 | W144: 6 | X144: =W144*$B$144 -> 150 | Y144: 6 | Z144: =Y144*$B$144 -> 150 | AA144: 5 | AB144: =AA144*$B$144 -> 125
A145: =Hipótesis!$B$59 -> Alta e instalación Plan Vidriera | B145: =Hipótesis!C59 -> 60 | C145: =E145+G145+I145+K145+M145+O145+Q145+S145+U145+W145+Y145+AA145 -> 143 | D145: =B145*C145 -> 8580 | E145: 12 | F145: =E145*$B$145 -> 720 | G145: 12 | H145: =G145*$B$145 -> 720 | I145: 12 | J145: =I145*$B$145 -> 720 | K145: 12 | L145: =K145*$B$145 -> 720 | M145: 12 | N145: =M145*$B$145 -> 720 | O145: 12 | P145: =O145*$B$145 -> 720 | Q145: 12 | R145: =Q145*$B$145 -> 720 | S145: 12 | T145: =S145*$B$145 -> 720 | U145: 12 | V145: =U145*$B$145 -> 720 | W145: 12 | X145: =W145*$B$145 -> 720 | Y145: 12 | Z145: =Y145*$B$145 -> 720 | AA145: 11 | AB145: =AA145*$B$145 -> 660
A146: =Hipótesis!$B$60 -> Alta e instalación Plan Cadena | B146: =Hipótesis!C60 -> 250 | C146: =E146+G146+I146+K146+M146+O146+Q146+S146+U146+W146+Y146+AA146 -> 24 | D146: =B146*C146 -> 6000 | E146: 2 | F146: =E146*$B$146 -> 500 | G146: 2 | H146: =G146*$B$146 -> 500 | I146: 2 | J146: =I146*$B$146 -> 500 | K146: 2 | L146: =K146*$B$146 -> 500 | M146: 2 | N146: =M146*$B$146 -> 500 | O146: 2 | P146: =O146*$B$146 -> 500 | Q146: 2 | R146: =Q146*$B$146 -> 500 | S146: 2 | T146: =S146*$B$146 -> 500 | U146: 2 | V146: =U146*$B$146 -> 500 | W146: 2 | X146: =W146*$B$146 -> 500 | Y146: 2 | Z146: =Y146*$B$146 -> 500 | AA146: 2 | AB146: =AA146*$B$146 -> 500
A147: =Hipótesis!$B$61 -> Abono Plan Básico | B147: =Hipótesis!C61 -> 15 | C147: =E147+G147+I147+K147+M147+O147+Q147+S147+U147+W147+Y147+AA147 -> 1439 | D147: =B147*C147 -> 21585 | E147: =AA85+E144 -> 87 | F147: =E147*$B$147 -> 1305 | G147: =E147+G144 -> 93 | H147: =G147*$B$147 -> 1395 | I147: =G147+I144 -> 99 | J147: =I147*$B$147 -> 1485 | K147: =I147+K144 -> 105 | L147: =K147*$B$147 -> 1575 | M147: =K147+M144 -> 111 | N147: =M147*$B$147 -> 1665 | O147: =M147+O144 -> 117 | P147: =O147*$B$147 -> 1755 | Q147: =O147+Q144 -> 123 | R147: =Q147*$B$147 -> 1845 | S147: =Q147+S144 -> 129 | T147: =S147*$B$147 -> 1935 | U147: =S147+U144 -> 135 | V147: =U147*$B$147 -> 2025 | W147: =U147+W144 -> 141 | X147: =W147*$B$147 -> 2115 | Y147: =W147+Y144 -> 147 | Z147: =Y147*$B$147 -> 2205 | AA147: =Y147+AA144 -> 152 | AB147: =AA147*$B$147 -> 2280
A148: =Hipótesis!$B$62 -> Abono Plan Vidriera | B148: =Hipótesis!C62 -> 29 | C148: =E148+G148+I148+K148+M148+O148+Q148+S148+U148+W148+Y148+AA148 -> 2903 | D148: =B148*C148 -> 84187 | E148: =AA86+E145 -> 176 | F148: =E148*$B$148 -> 5104 | G148: =E148+G145 -> 188 | H148: =G148*$B$148 -> 5452 | I148: =G148+I145 -> 200 | J148: =I148*$B$148 -> 5800 | K148: =I148+K145 -> 212 | L148: =K148*$B$148 -> 6148 | M148: =K148+M145 -> 224 | N148: =M148*$B$148 -> 6496 | O148: =M148+O145 -> 236 | P148: =O148*$B$148 -> 6844 | Q148: =O148+Q145 -> 248 | R148: =Q148*$B$148 -> 7192 | S148: =Q148+S145 -> 260 | T148: =S148*$B$148 -> 7540 | U148: =S148+U145 -> 272 | V148: =U148*$B$148 -> 7888 | W148: =U148+W145 -> 284 | X148: =W148*$B$148 -> 8236 | Y148: =W148+Y145 -> 296 | Z148: =Y148*$B$148 -> 8584 | AA148: =Y148+AA145 -> 307 | AB148: =AA148*$B$148 -> 8903
A149: =Hipótesis!$B$63 -> Abono Plan Cadena | B149: =Hipótesis!C63 -> 79 | C149: =E149+G149+I149+K149+M149+O149+Q149+S149+U149+W149+Y149+AA149 -> 480 | D149: =B149*C149 -> 37920 | E149: =AA87+E146 -> 29 | F149: =E149*$B$149 -> 2291 | G149: =E149+G146 -> 31 | H149: =G149*$B$149 -> 2449 | I149: =G149+I146 -> 33 | J149: =I149*$B$149 -> 2607 | K149: =I149+K146 -> 35 | L149: =K149*$B$149 -> 2765 | M149: =K149+M146 -> 37 | N149: =M149*$B$149 -> 2923 | O149: =M149+O146 -> 39 | P149: =O149*$B$149 -> 3081 | Q149: =O149+Q146 -> 41 | R149: =Q149*$B$149 -> 3239 | S149: =Q149+S146 -> 43 | T149: =S149*$B$149 -> 3397 | U149: =S149+U146 -> 45 | V149: =U149*$B$149 -> 3555 | W149: =U149+W146 -> 47 | X149: =W149*$B$149 -> 3713 | Y149: =W149+Y146 -> 49 | Z149: =Y149*$B$149 -> 3871 | AA149: =Y149+AA146 -> 51 | AB149: =AA149*$B$149 -> 4029
A157: Ingreso Total | D157: =SUM(D144:D156) -> 160047 | F157: =SUM(F144:F156) -> 10070 | H157: =SUM(H144:H156) -> 10666 | J157: =SUM(J144:J156) -> 11262 | L157: =SUM(L144:L156) -> 11858 | N157: =SUM(N144:N156) -> 12454 | P157: =SUM(P144:P156) -> 13050 | R157: =SUM(R144:R156) -> 13646 | T157: =SUM(T144:T156) -> 14242 | V157: =SUM(V144:V156) -> 14838 | X157: =SUM(X144:X156) -> 15434 | Z157: =SUM(Z144:Z156) -> 16030 | AB157: =SUM(AB144:AB156) -> 16497
C158: =C144 -> 71 | E158: =E144 -> 6 | G158: =G144 -> 6 | I158: =I144 -> 6 | K158: =K144 -> 6 | M158: =M144 -> 6 | O158: =O144 -> 6 | Q158: =Q144 -> 6 | S158: =S144 -> 6 | U158: =U144 -> 6 | W158: =W144 -> 6 | Y158: =Y144 -> 6 | AA158: =AA144 -> 5
C159: =C145 -> 143 | E159: =E145 -> 12 | G159: =G145 -> 12 | I159: =I145 -> 12 | K159: =K145 -> 12 | M159: =M145 -> 12 | O159: =O145 -> 12 | Q159: =Q145 -> 12 | S159: =S145 -> 12 | U159: =U145 -> 12 | W159: =W145 -> 12 | Y159: =Y145 -> 12 | AA159: =AA145 -> 11
C160: =C146 -> 24 | E160: =E146 -> 2 | G160: =G146 -> 2 | I160: =I146 -> 2 | K160: =K146 -> 2 | M160: =M146 -> 2 | O160: =O146 -> 2 | Q160: =Q146 -> 2 | S160: =S146 -> 2 | U160: =U146 -> 2 | W160: =W146 -> 2 | Y160: =Y146 -> 2 | AA160: =AA146 -> 2
C161: =SUM(C147:C150) -> 4822 | E161: =SUM(E147:E150) -> 292 | G161: =SUM(G147:G150) -> 312 | I161: =SUM(I147:I150) -> 332 | K161: =SUM(K147:K150) -> 352 | M161: =SUM(M147:M150) -> 372 | O161: =SUM(O147:O150) -> 392 | Q161: =SUM(Q147:Q150) -> 412 | S161: =SUM(S147:S150) -> 432 | U161: =SUM(U147:U150) -> 452 | W161: =SUM(W147:W150) -> 472 | Y161: =SUM(Y147:Y150) -> 492 | AA161: =SUM(AA147:AA150) -> 510
C162: =SUM(C151:C155) -> 0 | E162: =SUM(E151:E155) -> 0 | G162: =SUM(G151:G155) -> 0 | I162: =SUM(I151:I155) -> 0 | K162: =SUM(K151:K155) -> 0 | M162: =SUM(M151:M155) -> 0 | O162: =SUM(O151:O155) -> 0 | Q162: =SUM(Q151:Q155) -> 0 | S162: =SUM(S151:S155) -> 0 | U162: =SUM(U151:U155) -> 0 | W162: =SUM(W151:W155) -> 0 | Y162: =SUM(Y151:Y155) -> 0 | AA162: =SUM(AA151:AA155) -> 0
C163: =C156 -> 0 | E163: =E156 -> 0 | G163: =G156 -> 0 | I163: =I156 -> 0 | K163: =K156 -> 0 | M163: =M156 -> 0 | O163: =O156 -> 0 | Q163: =Q156 -> 0 | S163: =S156 -> 0 | U163: =U156 -> 0 | W163: =W156 -> 0 | Y163: =Y156 -> 0 | AA163: =AA156 -> 0
A165: Capacidad operativa - Año 2028
A166: Comentarios | B166: * En febrero y junio se contratarán 3 auxiliares de soporte para cubrir la demanda de los nuevos clientes. * En enero se contratará un gerente comercial para poder cumplir con los objetivos del nuevo año. * Capital de trabajo: se seguira incrementando el stock de sensores para cubrir las instalaciones de los nuevos clientes y posibles fallos que puedan suceder de clientes ya existentes.
C167: Concepto | E167: Enero | G167: Febrero | I167: Marzo | K167: Abril | M167: Mayo | O167: Junio | Q167: Julio | S167: Agosto | U167: Septiembre | W167: Octubre | Y167: Noviembre | AA167: Diciembre
A168: RRHH | C168: Gerente general | E168: Sin cambios | G168: Sin cambios | I168: Sin cambios | K168: Sin cambios | M168: Sin cambios | O168: Sin cambios | Q168: Sin cambios | S168: Sin cambios | U168: Sin cambios | W168: Sin cambios | Y168: Sin cambios | AA168: Sin cambios
...

Sheet Anexo capacidad operativa
C1: Anexo capacidad operativa
A3: Instalación y alta de los planes ShopMetrics | H3: Soporte mensual por plan | O3: Sueldo tecnico por hora: | P3: 6 | S3: Coste del kit de instalación | Y3: Coste del soporte mensual
A6: Cálculo de horas laborables de un empleado por mes
A7: Semanas por año | B7: 52 | C7: semanas
A8: Semanas de licencias varias al año | B8: 2 | C8: semanas
A9: Días festivos | B9: 14 | C9: días
A10: Días laborales totales | B10: =(B7-B8)*5 -B9 -> 236 | C10: días
A11: Jornada laboral | B11: 8 | C11: horas | T11: Alta remota: conexión con el punto de venta
A12: Horas laborables anuales por empleado | B12: =B10*B11 -> 1888 | C12: horas | T12: Visita al local: sensor de vidriera + contador de puerta
A13: Consideraremos en promedio: | B13: 1800 | C13: Horas laborables anuales / empleado | T13: Instalación en hasta cinco locales de una cadena
B14: 150 | C14: Horas laborables mensuales / empleado [HsLaboralesXMes]
A18: Alta e instalación Plan Básico | H18: Soporte mensual Plan Básico | S18: Kit Plan Básico | Y18: Soporte mensual Plan Básico
A19: N° de tarea | B19: Descripción | C19: Base horaria [BH] | D19: Cantidad requerida [Cant] | E19: Horas por tarea Fórmula = Cant * BH | H19: N° de tarea | I19: Descripción | J19: Base horaria [BH] | K19: Cantidad requerida [Cant] | L19: Horas por tarea Fórmula = Cant * BH | S19: Componente | U19: Cantidad | V19: Precio unitario | W19: Subtotal | Y19: Componente | AA19: Cantidad | AB19: Precio unitario | AC19: Subtotal
A20: 1 | B20: Contacto y coordinación | C20: 0.08 | D20: 1 | E20: =D20*C20 -> 0.08 | H20: 1 | I20: Monitoreo de ingesta | J20: 0.05 | K20: 1 | L20: =K20*J20 -> 0.05 | S20: Instalación (mano de obra) | U20: =$E$32 -> 0.5 | V20: =$P$3 -> 6 | W20: =V20*U20 -> 3 | Y20: Servicio técnico | AA20: =$L$32 -> 0.15 | AB20: =$P$3 -> 6 | AC20: =AB20*AA20 -> 0.9
A21: 2 | B21: Alta en la plataforma | C21: 0.08 | D21: 1 | E21: =D21*C21 -> 0.08 | H21: 2 | I21: Atención de consultas | J21: 0.07 | K21: 1 | L21: =K21*J21 -> 0.07
A22: 3 | B22: Conexión con el punto de venta | C22: 0.17 | D22: 1 | E22: =D22*C22 -> 0.17 | H22: 3 | I22: Reporte mensual | J22: 0.03 | K22: 1 | L22: =K22*J22 -> 0.03 | AB22: =V3 -> 0
A23: 4 | B23: Verificación de los datos | C23: 0.12 | D23: 1 | E23: =D23*C23 -> 0.12 | H23: 4 | L23: =K23*J23 -> 0
A24: 5 | B24: Capacitación remota | C24: 0.05 | D24: 1 | E24: =D24*C24 -> 0.05 | H24: 5 | L24: =K24*J24 -> 0
A25: 6 | E25: =D25*C25 -> 0 | H25: 6
A26: 7 | E26: =D26*C26 -> 0 | H26: 7
A27: 8 | E27: =D27*C27 -> 0 | H27: 8
A28: 9 | E28: =D28*C28 -> 0 | H28: 9 | S28: Total | W28: =SUM(W20:W25) -> 3 | Y28: Total | AC28: =SUM(AC20:AC25) -> 0.9
A29: 10 | E29: =D29*C29 -> 0 | H29: 10
A30: 11 | E30: =D30*C30 -> 0 | H30: 11
A31: 12 | E31: =D31*C31 -> 0 | H31: 12
A32: Comentarios: el alta del Plan Básico es remota, no requiere visita. | D32: Horas totales por servicio [HsTotalesXServicio] Fórmula = Σ Horas por tarea del servicio | E32: =SUM(E20:E31) -> 0.5 | F32: Coste por instalación | H32: Comentarios: soporte enteramente remoto. | K32: Horas totales por servicio [HsTotalesXServicio] | L32: =SUM(L20:L31) -> 0.15
D33: Capacidad operativa mensual por proyecto Fórmula = HsTotalesXSer / HsLaboralesXMes | E33: =E32/$B$14 -> 0.0033333333 | F33: =$P$3*E32 -> 3 | K33: Capacidad operativa mensual por proyecto | L33: =L32/$B$14 -> 0.001
A37: Alta e instalación Plan Vidriera | H37: Soporte mensual Plan Vidriera | S37: Kit Plan Vidriera | Y37: Soporte mensual Plan Vidriera
A38: N° de tarea | B38: Descripción | C38: Base horaria [BH] | D38: Cantidad requerida [Cant] | E38: Horas por tarea Fórmula = Cant * BH | H38: N° de tarea | I38: Descripción | J38: Base horaria [BH] | K38: Cantidad requerida [Cant] | L38: Horas por tarea Fórmula = Cant * BH | S38: Componente | U38: Cantidad | V38: Precio unitario | W38: Subtotal | Y38: Componente | AA38: Cantidad | AB38: Precio unitario | AC38: Subtotal
A39: 1 | B39: Coordinación y armado del kit | C39: 0.25 | D39: 1 | E39: =D39*C39 -> 0.25 | H39: 1 | I39: Monitoreo de ingesta | J39: 0.05 | K39: 1 | L39: =K39*J39 -> 0.05 | S39: Sensor de vidriera | U39: 1 | V39: 14 | W39: =V39*U39 -> 14 | Y39: Servicio técnico | AA39: =$L$51 -> 0.25 | AB39: =$P$3 -> 6 | AC39: =AB39*AA39 -> 1.5
A40: 2 | B40: Traslado al local | C40: 0.5 | D40: 1 | E40: =D40*C40 -> 0.5 | H40: 2 | I40: Control del sensor | J40: 0.07 | K40: 1 | L40: =K40*J40 -> 0.07 | S40: Contador de puerta | U40: 1 | V40: 9 | W40: =V40*U40 -> 9
A41: 3 | B41: Montaje del sensor de vidriera | C41: 0.75 | D41: 1 | E41: =D41*C41 -> 0.75 | H41: 3 | I41: Atención de consultas | J41: 0.08 | K41: 1 | L41: =K41*J41 -> 0.08 | S41: Gateway de conexión | U41: 1 | V41: 7 | W41: =V41*U41 -> 7
A42: 4 | B42: Instalación contador de puerta | C42: 0.5 | D42: 1 | E42: =D42*C42 -> 0.5 | H42: 4 | I42: Reporte mensual | J42: 0.05 | K42: 1 | L42: =K42*J42 -> 0.05 | S42: Kit de montaje | U42: 1 | V42: 4 | W42: =V42*U42 -> 4
A43: 5 | B43: Conexión con el punto de venta | C43: 0.25 | D43: 1 | E43: =D43*C43 -> 0.25 | H43: 5 | L43: =K43*J43 -> 0 | S43: Instalación (mano de obra) | U43: =$E$51 -> 3 | V43: =$P$3 -> 6 | W43: =V43*U43 -> 18
A44: 6 | B44: Prueba del embudo | C44: 0.5 | D44: 1 | E44: =D44*C44 -> 0.5 | H44: 6 | L44: =K44*J44 -> 0
A45: 7 | B45: Capacitación y cierre | C45: 0.25 | D45: 1 | E45: =D45*C45 -> 0.25 | H45: 7 | L45: 0
A46: 8 | E46: =D46*C46 -> 0 | H46: 8 | L46: 0
A47: 9 | E47: =D47*C47 -> 0 | H47: 9 | L47: 0 | S47: Total | W47: =SUM(W39:W44) -> 52 | Y47: Total | AC47: =SUM(AC39:AC44) -> 1.5
A48: 10 | E48: =D48*C48 -> 0 | H48: 10 | L48: 0
A49: 11 | E49: =D49*C49 -> 0 | H49: 11 | L49: 0
A50: 12 | E50: =D50*C50 -> 0 | H50: 12 | L50: 0
A51: Comentarios: incluye traslado y montaje del equipamiento en vidriera. | D51: Horas totales por servicio [HsTotalesXServicio] Fórmula = Σ Horas por tarea del servicio | E51: =SUM(E39:E50) -> 3 | F51: Coste por instalación | H51: Comentarios: suma el control del sensor de vidriera. | K51: Horas totales por servicio [HsTotalesXServicio] | L51: =SUM(L39:L50) -> 0.25
D52: Capacidad operativa mensual por empleado Fórmula = HsTotalesXSer / HsLaboralesXMes | E52: =E51/$B$14 -> 0.02 | F52: =$P$3*E51 -> 18 | K52: Capacidad operativa mensual por proyecto | L52: =L51/$B$14 -> 0.0016666667
A56: Alta e instalación Plan Cadena | H56: Soporte mensual Plan Cadena | S56: Kit Plan Cadena | Y56: Soporte mensual Plan Cadena
A57: N° de tarea | B57: Descripción | C57: Base horaria [BH] | D57: Cantidad requerida [Cant] | E57: Horas por tarea Fórmula = Cant * BH | H57: N° de tarea | I57: Descripción | J57: Base horaria [BH] | K57: Cantidad requerida [Cant] | L57: Horas por tarea Fórmula = Cant * BH | S57: Componente | U57: Cantidad | V57: Precio unitario | W57: Subtotal | Y57: Componente | AA57: Cantidad | AB57: Precio unitario | AC57: Subtotal
A58: 1 | B58: Relevamiento de la cadena | C58: 1 | D58: 1 | E58: =D58*C58 -> 1 | H58: 1 | I58: Monitoreo por local | J58: 0.04 | K58: 5 | L58: =K58*J58 -> 0.2 | S58: Sensor de vidriera | U58: 5 | V58: 14 | W58: =V58*U58 -> 70 | Y58: Servicio técnico | AA58: =$L$70 -> 0.6 | AB58: =$P$3 -> 6 | AC58: =AB58*AA58 -> 3.6
A59: 2 | B59: Alta de cadena y sucursales | C59: 0.5 | D59: 1 | E59: =D59*C59 -> 0.5 | H59: 2 | I59: Control de sensores | J59: 0.03 | K59: 5 | L59: =K59*J59 -> 0.15 | S59: Contador de puerta | U59: 5 | V59: 9 | W59: =V59*U59 -> 45
A60: 3 | B60: Traslado entre locales | C60: 0.5 | D60: 5 | E60: =D60*C60 -> 2.5 | H60: 3 | I60: Consultas del titular | J60: 0.1 | K60: 1 | L60: =K60*J60 -> 0.1 | S60: Gateway de conexión | U60: 5 | V60: 7 | W60: =V60*U60 -> 35
A61: 4 | B61: Montaje sensor de vidriera | C61: 0.75 | D61: 5 | E61: =D61*C61 -> 3.75 | H61: 4 | I61: Reporte comparativo | J61: 0.15 | K61: 1 | L61: =K61*J61 -> 0.15 | S61: Kit de montaje | U61: 5 | V61: 4 | W61: =V61*U61 -> 20
A62: 5 | B62: Instalación contador de puerta | C62: 0.4 | D62: 5 | E62: =D62*C62 -> 2 | H62: 5 | L62: =K62*J62 -> 0 | S62: Instalación (mano de obra) | U62: =$E$70 -> 12 | V62: =$P$3 -> 6 | W62: =V62*U62 -> 72
A63: 6 | B63: Conexión del punto de venta | C63: 0.2 | D63: 5 | E63: =D63*C63 -> 1 | H63: 6 | L63: =K63*J63 -> 0
A64: 7 | B64: Prueba comparativa | C64: 0.75 | D64: 1 | E64: =D64*C64 -> 0.75 | H64: 7 | L64: =K64*J64 -> 0
A65: 8 | B65: Capacitación del responsable | C65: 0.5 | D65: 1 | E65: =D65*C65 -> 0.5 | H65: 8 | L65: =K65*J65 -> 0 | S65: Total | W65: =SUM(W58:W64) -> 242 | Y65: Total | AC65: =SUM(AC58:AC64) -> 3.6
A66: 9 | E66: =D66*C66 -> 0 | H66: 9 | L66: 0
A67: 10 | E67: =D67*C67 -> 0 | H67: 10 | L67: 0
A68: 11 | E68: =D68*C68 -> 0 | H68: 11 | L68: 0
A69: 12 | E69: =D69*C69 -> 0 | H69: 12 | L69: 0
A70: Comentarios: cubre hasta cinco locales de una misma cadena. | D70: Horas totales por servicio [HsTotalesXServicio] Fórmula = Σ Horas por tarea del servicio | E70: =SUM(E58:E69) -> 12 | F70: Coste por instalación | H70: Comentarios: el monitoreo se repite por local. | K70: Horas totales por servicio [HsTotalesXServicio] | L70: =SUM(L58:L69) -> 0.6
D71: Capacidad operativa mensual por empleado Fórmula = HsTotalesXSer / HsLaboralesXMes | E71: =E70/$B$14 -> 0.08 | F71: =$P$3*E70 -> 72 | K71: Capacidad operativa mensual por proyecto | L71: =L70/$B$14 -> 0.004
A76: Detalle: el soporte por plan es mensual y se sostiene mientras el comercio permanece abonado.
A77: ANALISIS CAPACIDAD OPERATIVA ANUAL POR SERVICIO EN HORAS HOMBRE
A78: CAPACIDAD OPERATIVA AÑO 2026 | C78: Enero | E78: Febrero | G78: Marzo | I78: Abril | K78: Mayo | M78: Junio | O78: Julio | Q78: Agosto | S78: Septiembre | U78: Octubre | W78: Noviembre | Y78: Diciembre
C79: Unidades requeridas | D79: Horas Hombre requeridas | E79: Unidades requeridas | F79: Horas Hombre requeridos | G79: Unidades requeridas | H79: Horas Hombre requeridas | I79: Unidades requeridas | J79: Horas Hombre requeridos | K79: Unidades requeridas | L79: Horas Hombre requeridas | M79: Unidades requeridas | N79: Horas Hombre requeridas | O79: Unidades requeridas | P79: Horas Hombre requeridas | Q79: Unidades requeridas | R79: Horas Hombre requeridas | S79: Unidades requeridas | T79: Horas Hombre requeridas | U79: Unidades requeridas | V79: Horas Hombre requeridas | W79: Unidades requeridas | X79: Horas Hombre requeridas | Y79: Unidades requeridas | Z79: Horas Hombre requeridas
A80: =Hipótesis!B$58 -> Alta e instalación Plan Básico | B80: =D80+F80+H80+J80+L80+N80+P80+R80+T80+V80+X80+Z80 -> 15 | C80: ='Proy. ventas'!E19 -> 0 | D80: =C80*$E$32 -> 0 | E80: ='Proy. ventas'!G33 -> 1 | F80: =E80*$E$32 -> 0.5 | G80: ='Proy. ventas'!I33 -> 1 | H80: =G80*$E$32 -> 0.5 | I80: ='Proy. ventas'!K33 -> 2 | J80: =I80*$E$32 -> 1 | K80: ='Proy. ventas'!M33 -> 2 | L80: =K80*$E$32 -> 1 | M80: ='Proy. ventas'!O33 -> 3 | N80: =M80*$E$32 -> 1.5 | O80: ='Proy. ventas'!Q33 -> 3 | P80: =O80*$E$32 -> 1.5 | Q80: ='Proy. ventas'!S33 -> 3 | R80: =Q80*$E$32 -> 1.5 | S80: ='Proy. ventas'!U33 -> 4 | T80: =S80*$E$32 -> 2 | U80: ='Proy. ventas'!W33 -> 4 | V80: =U80*$E$32 -> 2 | W80: ='Proy. ventas'!Y33 -> 4 | X80: =W80*$E$32 -> 2 | Y80: ='Proy. ventas'!AA33 -> 3 | Z80: =Y80*$E$32 -> 1.5
A81: =Hipótesis!B$59 -> Alta e instalación Plan Vidriera | B81: =D81+F81+H81+J81+L81+N81+P81+R81+T81+V81+X81+Z81 -> 186 | C81: ='Proy. ventas'!E20 -> 0 | D81: =C81*$E$51 -> 0 | E81: ='Proy. ventas'!G34 -> 1 | F81: =E81*$E$51 -> 3 | G81: ='Proy. ventas'!I34 -> 3 | H81: =G81*$E$51 -> 9 | I81: ='Proy. ventas'!K34 -> 4 | J81: =I81*$E$51 -> 12 | K81: ='Proy. ventas'!M34 -> 5 | L81: =K81*$E$51 -> 15 | M81: ='Proy. ventas'!O34 -> 5 | N81: =M81*$E$51 -> 15 | O81: ='Proy. ventas'!Q34 -> 6 | P81: =O81*$E$51 -> 18 | Q81: ='Proy. ventas'!S34 -> 7 | R81: =Q81*$E$51 -> 21 | S81: ='Proy. ventas'!U34 -> 7 | T81: =S81*$E$51 -> 21 | U81: ='Proy. ventas'!W34 -> 8 | V81: =U81*$E$51 -> 24 | W81: ='Proy. ventas'!Y34 -> 8 | X81: =W81*$E$51 -> 24 | Y81: ='Proy. ventas'!AA34 -> 8 | Z81: =Y81*$E$51 -> 24
A82: =Hipótesis!B$60 -> Alta e instalación Plan Cadena | B82: =D82+F82+H82+J82+L82+N82+P82+R82+T82+V82+X82+Z82 -> 120 | C82: ='Proy. ventas'!E21 -> 0 | D82: =C82*$E$70 -> 0 | E82: ='Proy. ventas'!G35 -> 0 | F82: =E82*$E$70 -> 0 | G82: ='Proy. ventas'!I35 -> 0 | H82: =G82*$E$70 -> 0 | I82: ='Proy. ventas'!K35 -> 0 | J82: =I82*$E$70 -> 0 | K82: ='Proy. ventas'!M35 -> 1 | L82: =K82*$E$70 -> 12 | M82: ='Proy. ventas'!O35 -> 1 | N82: =M82*$E$70 -> 12 | O82: ='Proy. ventas'!Q35 -> 1 | P82: =O82*$E$70 -> 12 | Q82: ='Proy. ventas'!S35 -> 1 | R82: =Q82*$E$70 -> 12 | S82: ='Proy. ventas'!U35 -> 1 | T82: =S82*$E$70 -> 12 | U82: ='Proy. ventas'!W35 -> 1 | V82: =U82*$E$70 -> 12 | W82: ='Proy. ventas'!Y35 -> 1 | X82: =W82*$E$70 -> 12 | Y82: ='Proy. ventas'!AA35 -> 3 | Z82: =Y82*$E$70 -> 36
A83: =Hipótesis!B$61 -> Abono Plan Básico | B83: =D83+F83+H83+J83+L83+N83+P83+R83+T83+V83+X83+Z83 -> 22.2 | C83: ='Proy. ventas'!E22 -> 0 | D83: =C83*$L$32 -> 0 | E83: ='Proy. ventas'!G22 -> 1 | F83: =E83*$L$32 -> 0.15 | G83: ='Proy. ventas'!I22 -> 2 | H83: =G83*$L$32 -> 0.3 | I83: ='Proy. ventas'!K22 -> 4 | J83: =I83*$L$32 -> 0.6 | K83: ='Proy. ventas'!M22 -> 6 | L83: =K83*$L$32 -> 0.9 | M83: ='Proy. ventas'!O22 -> 9 | N83: =M83*$L$32 -> 1.35 | O83: ='Proy. ventas'!Q22 -> 12 | P83: =O83*$L$32 -> 1.8 | Q83: ='Proy. ventas'!S22 -> 15 | R83: =Q83*$L$32 -> 2.25 | S83: ='Proy. ventas'!U22 -> 19 | T83: =S83*$L$32 -> 2.85 | U83: ='Proy. ventas'!W22 -> 23 | V83: =U83*$L$32 -> 3.45 | W83: ='Proy. ventas'!Y22 -> 27 | X83: =W83*$L$32 -> 4.05 | Y83: ='Proy. ventas'!AA22 -> 30 | Z83: =Y83*$L$32 -> 4.5
A84: =Hipótesis!B$62 -> Abono Plan Vidriera | B84: =D84+F84+H84+J84+L84+N84+P84+R84+T84+V84+X84+Z84 -> 74.75 | C84: ='Proy. ventas'!E23 -> 0 | D84: =C84*$L$51 -> 0 | E84: ='Proy. ventas'!G23 -> 1 | F84: =E84*$L$51 -> 0.25 | G84: ='Proy. ventas'!I23 -> 4 | H84: =G84*$L$51 -> 1 | I84: ='Proy. ventas'!K23 -> 8 | J84: =I84*$L$51 -> 2 | K84: ='Proy. ventas'!M23 -> 13 | L84: =K84*$L$51 -> 3.25 | M84: ='Proy. ventas'!O23 -> 18 | N84: =M84*$L$51 -> 4.5 | O84: ='Proy. ventas'!Q23 -> 24 | P84: =O84*$L$51 -> 6 | Q84: ='Proy. ventas'!S23 -> 31 | R84: =Q84*$L$51 -> 7.75 | S84: ='Proy. ventas'!U23 -> 38 | T84: =S84*$L$51 -> 9.5 | U84: ='Proy. ventas'!W23 -> 46 | V84: =U84*$L$51 -> 11.5 | W84: ='Proy. ventas'!Y23 -> 54 | X84: =W84*$L$51 -> 13.5 | Y84: ='Proy. ventas'!AA23 -> 62 | Z84: =Y84*$L$51 -> 15.5
A85: =Hipótesis!B$63 -> Abono Plan Cadena | B85: =D85+F85+H85+J85+L85+N85+P85+R85+T85+V85+X85+Z85 -> 22.8 | C85: ='Proy. ventas'!E24 -> 0 | D85: =C85*$L$70 -> 0 | E85: ='Proy. ventas'!G24 -> 0 | F85: =E85*$L$70 -> 0 | G85: ='Proy. ventas'!I24 -> 0 | H85: =G85*$L$70 -> 0 | I85: ='Proy. ventas'!K24 -> 0 | J85: =I85*$L$70 -> 0 | K85: ='Proy. ventas'!M24 -> 1 | L85: =K85*$L$70 -> 0.6 | M85: ='Proy. ventas'!O24 -> 2 | N85: =M85*$L$70 -> 1.2 | O85: ='Proy. ventas'!Q24 -> 3 | P85: =O85*$L$70 -> 1.8 | Q85: ='Proy. ventas'!S24 -> 4 | R85: =Q85*$L$70 -> 2.4 | S85: ='Proy. ventas'!U24 -> 5 | T85: =S85*$L$70 -> 3 | U85: ='Proy. ventas'!W24 -> 6 | V85: =U85*$L$70 -> 3.6 | W85: ='Proy. ventas'!Y24 -> 7 | X85: =W85*$L$70 -> 4.2 | Y85: ='Proy. ventas'!AA24 -> 10 | Z85: =Y85*$L$70 -> 6
A86: TOTALES | B86: =D86+F86+H86+J86+L86+N86+P86+R86+T86+V86+X86+Z86 -> 440.75 | C86: =SUM(C80:C85) -> 0 | D86: =SUM(D80:D85) -> 0 | E86: =SUM(E80:E85) -> 4 | F86: =SUM(F80:F85) -> 3.9 | G86: =SUM(G80:G85) -> 10 | H86: =SUM(H80:H85) -> 10.8 | I86: =SUM(I80:I85) -> 18 | J86: =SUM(J80:J85) -> 15.6 | ... Z86: =SUM(Z80:Z85) -> 87.5
A89: CAPACIDAD OPERATIVA AÑO 2027 | C89: Enero | E89: Febrero | G89: Marzo | I89: Abril | K89: Mayo | M89: Junio | O89: Julio | Q89: Agosto | S89: Septiembre | U89: Octubre | W89: Noviembre | Y89: Diciembre
C90: Unidades requeridas | D90: Horas Hombre requeridas | E90: Unidades requeridas | F90: Horas Hombre requeridos | G90: Unidades requeridas | H90: Horas Hombre requeridas | I90: Unidades requeridas | J90: Horas Hombre requeridos | K90: Unidades requeridas | L90: Horas Hombre requeridas | M90: Unidades requeridas | N90: Horas Hombre requeridas | O90: Unidades requeridas | P90: Horas Hombre requeridas | Q90: Unidades requeridas | R90: Horas Hombre requeridas | S90: Unidades requeridas | T90: Horas Hombre requeridas | U90: Unidades requeridas | V90: Horas Hombre requeridas | W90: Unidades requeridas | X90: Horas Hombre requeridas | Y90: Unidades requeridas | Z90: Horas Hombre requeridas
A91: =Hipótesis!B$58 -> Alta e instalación Plan Básico | B91: =D91+F91+H91+J91+L91+N91+P91+R91+T91+V91+X91+Z91 -> 25.5 | C91: ='Proy. ventas'!E82 -> 4 | D91: =C91*$E$32 -> 2 | E91: ='Proy. ventas'!G82 -> 4 | F91: =E91*$E$32 -> 2 | G91: ='Proy. ventas'!I82 -> 4 | H91: =G91*$E$32 -> 2 | I91: ='Proy. ventas'!K82 -> 4 | J91: =I91*$E$32 -> 2 | K91: ='Proy. ventas'!M82 -> 4 | L91: =K91*$E$32 -> 2 | M91: ='Proy. ventas'!O82 -> 4 | N91: =M91*$E$32 -> 2 | O91: ='Proy. ventas'!Q82 -> 4 | P91: =O91*$E$32 -> 2 | Q91: ='Proy. ventas'!S82 -> 4 | R91: =Q91*$E$32 -> 2 | S91: ='Proy. ventas'!U82 -> 4 | T91: =S91*$E$32 -> 2 | U91: ='Proy. ventas'!W82 -> 4 | V91: =U91*$E$32 -> 2 | W91: ='Proy. ventas'!Y82 -> 5 | X91: =W91*$E$32 -> 2.5 | Y91: ='Proy. ventas'!AA82 -> 6 | Z91: =Y91*$E$32 -> 3
A92: =Hipótesis!B$59 -> Alta e instalación Plan Vidriera | B92: =D92+F92+H92+J92+L92+N92+P92+R92+T92+V92+X92+Z92 -> 306 | C92: ='Proy. ventas'!E83 -> 8 | D92: =C92*$E$51 -> 24 | E92: ='Proy. ventas'!G83 -> 8 | F92: =E92*$E$51 -> 24 | G92: ='Proy. ventas'!I83 -> 8 | H92: =G92*$E$51 -> 24 | I92: ='Proy. ventas'!K83 -> 8 | J92: =I92*$E$51 -> 24 | K92: ='Proy. ventas'!M83 -> 8 | L92: =K92*$E$51 -> 24 | M92: ='Proy. ventas'!O83 -> 8 | N92: =M92*$E$51 -> 24 | O92: ='Proy. ventas'!Q83 -> 9 | P92: =O92*$E$51 -> 27 | Q92: ='Proy. ventas'!S83 -> 9 | R92: =Q92*$E$51 -> 27 | S92: ='Proy. ventas'!U83 -> 9 | T92: =S92*$E$51 -> 27 | U92: ='Proy. ventas'!W83 -> 9 | V92: =U92*$E$51 -> 27 | W92: ='Proy. ventas'!Y83 -> 9 | X92: =W92*$E$51 -> 27 | Y92: ='Proy. ventas'!AA83 -> 9 | Z92: =Y92*$E$51 -> 27
A93: =Hipótesis!B$60 -> Alta e instalación Plan Cadena | B93: =D93+F93+H93+J93+L93+N93+P93+R93+T93+V93+X93+Z93 -> 204 | C93: ='Proy. ventas'!E84 -> 1 | D93: =C93*$E$70 -> 12 | E93: ='Proy. ventas'!G84 -> 1 | F93: =E93*$E$70 -> 12 | G93: ='Proy. ventas'!I84 -> 1 | H93: =G93*$E$70 -> 12 | I93: ='Proy. ventas'!K84 -> 1 | J93: =I93*$E$70 -> 12 | K93: ='Proy. ventas'!M84 -> 1 | L93: =K93*$E$70 -> 12 | M93: ='Proy. ventas'!O84 -> 2 | N93: =M93*$E$70 -> 24 | O93: ='Proy. ventas'!Q84 -> 1 | P93: =O93*$E$70 -> 12 | Q93: ='Proy. ventas'!S84 -> 2 | R93: =Q93*$E$70 -> 24 | S93: ='Proy. ventas'!U84 -> 1 | T93: =S93*$E$70 -> 12 | U93: ='Proy. ventas'!W84 -> 2 | V93: =U93*$E$70 -> 24 | W93: ='Proy. ventas'!Y84 -> 2 | X93: =W93*$E$70 -> 24 | Y93: ='Proy. ventas'!AA84 -> 2 | Z93: =Y93*$E$70 -> 24
A94: =Hipótesis!B$61 -> Abono Plan Básico | B94: =D94+F94+H94+J94+L94+N94+P94+R94+T94+V94+X94+Z94 -> 101.4 | C94: ='Proy. ventas'!E85 -> 34 | D94: =C94*$L$32 -> 5.1 | E94: ='Proy. ventas'!G85 -> 38 | F94: =E94*$L$32 -> 5.7 | G94: ='Proy. ventas'!I85 -> 42 | H94: =G94*$L$32 -> 6.3 | I94: ='Proy. ventas'!K85 -> 46 | J94: =I94*$L$32 -> 6.9 | K94: ='Proy. ventas'!M85 -> 50 | L94: =K94*$L$32 -> 7.5 | M94: ='Proy. ventas'!O85 -> 54 | N94: =M94*$L$32 -> 8.1 | O94: ='Proy. ventas'!Q85 -> 58 | P94: =O94*$L$32 -> 8.7 | Q94: ='Proy. ventas'!S85 -> 62 | R94: =Q94*$L$32 -> 9.3 | S94: ='Proy. ventas'!U85 -> 66 | T94: =S94*$L$32 -> 9.9 | U94: ='Proy. ventas'!W85 -> 70 | V94: =U94*$L$32 -> 10.5 | W94: ='Proy. ventas'!Y85 -> 75 | X94: =W94*$L$32 -> 11.25 | Y94: ='Proy. ventas'!AA85 -> 81 | Z94: =Y94*$L$32 -> 12.15
A95: =Hipótesis!B$62 -> Abono Plan Vidriera | B95: =D95+F95+H95+J95+L95+N95+P95+R95+T95+V95+X95+Z95 -> 347.25 | C95: ='Proy. ventas'!E86 -> 70 | D95: =C95*$L$51 -> 17.5 | E95: ='Proy. ventas'!G86 -> 78 | F95: =E95*$L$51 -> 19.5 | G95: ='Proy. ventas'!I86 -> 86 | H95: =G95*$L$51 -> 21.5 | I95: ='Proy. ventas'!K86 -> 94 | J95: =I95*$L$51 -> 23.5 | K95: ='Proy. ventas'!M86 -> 102 | L95: =K95*$L$51 -> 25.5 | M95: ='Proy. ventas'!O86 -> 110 | N95: =M95*$L$51 -> 27.5 | O95: ='Proy. ventas'!Q86 -> 119 | P95: =O95*$L$51 -> 29.75 | Q95: ='Proy. ventas'!S86 -> 128 | R95: =Q95*$L$51 -> 32 | S95: ='Proy. ventas'!U86 -> 137 | T95: =S95*$L$51 -> 34.25 | U95: ='Proy. ventas'!W86 -> 146 | V95: =U95*$L$51 -> 36.5 | W95: ='Proy. ventas'!Y86 -> 155 | X95: =W95*$L$51 -> 38.75 | Y95: ='Proy. ventas'!AA86 -> 164 | Z95: =Y95*$L$51 -> 41
A96: =Hipótesis!B$63 -> Abono Plan Cadena | B96: =D96+F96+H96+J96+L96+N96+P96+R96+T96+V96+X96+Z96 -> 129.6 | C96: ='Proy. ventas'!E87 -> 11 | D96: =C96*$L$70 -> 6.6 | E96: ='Proy. ventas'!G87 -> 12 | F96: =E96*$L$70 -> 7.2 | G96: ='Proy. ventas'!I87 -> 13 | H96: =G96*$L$70 -> 7.8 | I96: ='Proy. ventas'!K87 -> 14 | J96: =I96*$L$70 -> 8.4 | K96: ='Proy. ventas'!M87 -> 15 | L96: =K96*$L$70 -> 9 | M96: ='Proy. ventas'!O87 -> 17 | N96: =M96*$L$70 -> 10.2 | O96: ='Proy. ventas'!Q87 -> 18 | P96: =O96*$L$70 -> 10.8 | Q96: ='Proy. ventas'!S87 -> 20 | R96: =Q96*$L$70 -> 12 | S96: ='Proy. ventas'!U87 -> 21 | T96: =S96*$L$70 -> 12.6 | U96: ='Proy. ventas'!W87 -> 23 | V96: =U96*$L$70 -> 13.8 | W96: ='Proy. ventas'!Y87 -> 25 | X96: =W96*$L$70 -> 15 | Y96: ='Proy. ventas'!AA87 -> 27 | Z96: =Y96*$L$70 -> 16.2
A97: TOTALES | B97: =D97+F97+H97+J97+L97+N97+P97+R97+T97+V97+X97+Z97 -> 1113.75 | C97: =SUM(C91:C96) -> 128 | D97: =SUM(D91:D96) -> 67.2 | E97: =SUM(E91:E96) -> 141 | F97: =SUM(F91:F96) -> 70.4 | G97: =SUM(G91:G96) -> 154 | H97: =SUM(H91:H96) -> 73.6 | I97: =SUM(I91:I96) -> 167 | J97: =SUM(J91:J96) -> 76.8 | ... Z97: =SUM(Z91:Z96) -> 123.35
A100: CAPACIDAD OPERATIVA AÑO 2028 | C100: Enero | E100: Febrero | G100: Marzo | I100: Abril | K100: Mayo | M100: Junio | O100: Julio | Q100: Agosto | S100: Septiembre | U100: Octubre | W100: Noviembre | Y100: Diciembre
C101: Unidades requeridas | D101: Horas Hombre requeridas | E101: Unidades requeridas | F101: Horas Hombre requeridos | G101: Unidades requeridas | H101: Horas Hombre requeridas | I101: Unidades requeridas | J101: Horas Hombre requeridos | K101: Unidades requeridas | L101: Horas Hombre requeridas | M101: Unidades requeridas | N101: Horas Hombre requeridas | O101: Unidades requeridas | P101: Horas Hombre requeridas | Q101: Unidades requeridas | R101: Horas Hombre requeridas | S101: Unidades requeridas | T101: Horas Hombre requeridas | U101: Unidades requeridas | V101: Horas Hombre requeridas | W101: Unidades requeridas | X101: Horas Hombre requeridas | Y101: Unidades requeridas | Z101: Horas Hombre requeridas
A102: =Hipótesis!B$58 -> Alta e instalación Plan Básico | B102: =D102+F102+H102+J102+L102+N102+P102+R102+T102+V102+X102+Z102 -> 35.5 | C102: ='Proy. ventas'!E144 -> 6 | D102: =C102*$E$32 -> 3 | E102: ='Proy. ventas'!G144 -> 6 | F102: =E102*$E$32 -> 3 | G102: ='Proy. ventas'!I144 -> 6 | H102: =G102*$E$32 -> 3 | I102: ='Proy. ventas'!K144 -> 6 | J102: =I102*$E$32 -> 3 | K102: ='Proy. ventas'!M144 -> 6 | L102: =K102*$E$32 -> 3 | M102: ='Proy. ventas'!O144 -> 6 | N102: =M102*$E$32 -> 3 | O102: ='Proy. ventas'!Q144 -> 6 | P102: =O102*$E$32 -> 3 | Q102: ='Proy. ventas'!S144 -> 6 | R102: =Q102*$E$32 -> 3 | S102: ='Proy. ventas'!U144 -> 6 | T102: =S102*$E$32 -> 3 | U102: ='Proy. ventas'!W144 -> 6 | V102: =U102*$E$32 -> 3 | W102: ='Proy. ventas'!Y144 -> 6 | X102: =W102*$E$32 -> 3 | Y102: ='Proy. ventas'!AA144 -> 5 | Z102: =Y102*$E$32 -> 2.5
A103: =Hipótesis!B$59 -> Alta e instalación Plan Vidriera | B103: =D103+F103+H103+J103+L103+N103+P103+R103+T103+V103+X103+Z103 -> 429 | C103: ='Proy. ventas'!E145 -> 12 | D103: =C103*$E$51 -> 36 | E103: ='Proy. ventas'!G145 -> 12 | F103: =E103*$E$51 -> 36 | G103: ='Proy. ventas'!I145 -> 12 | H103: =G103*$E$51 -> 36 | I103: ='Proy. ventas'!K145 -> 12 | J103: =I103*$E$51 -> 36 | K103: ='Proy. ventas'!M145 -> 12 | L103: =K103*$E$51 -> 36 | M103: ='Proy. ventas'!O145 -> 12 | N103: =M103*$E$51 -> 36 | O103: ='Proy. ventas'!Q145 -> 12 | P103: =O103*$E$51 -> 36 | Q103: ='Proy. ventas'!S145 -> 12 | R103: =Q103*$E$51 -> 36 | S103: ='Proy. ventas'!U145 -> 12 | T103: =S103*$E$51 -> 36 | U103: ='Proy. ventas'!W145 -> 12 | V103: =U103*$E$51 -> 36 | W103: ='Proy. ventas'!Y145 -> 12 | X103: =W103*$E$51 -> 36 | Y103: ='Proy. ventas'!AA145 -> 11 | Z103: =Y103*$E$51 -> 33
A104: =Hipótesis!B$60 -> Alta e instalación Plan Cadena | B104: =D104+F104+H104+J104+L104+N104+P104+R104+T104+V104+X104+Z104 -> 288 | C104: ='Proy. ventas'!E146 -> 2 | D104: =C104*$E$70 -> 24 | E104: ='Proy. ventas'!G146 -> 2 | F104: =E104*$E$70 -> 24 | G104: ='Proy. ventas'!I146 -> 2 | H104: =G104*$E$70 -> 24 | I104: ='Proy. ventas'!K146 -> 2 | J104: =I104*$E$70 -> 24 | K104: ='Proy. ventas'!M146 -> 2 | L104: =K104*$E$70 -> 24 | M104: ='Proy. ventas'!O146 -> 2 | N104: =M104*$E$70 -> 24 | O104: ='Proy. ventas'!Q146 -> 2 | P104: =O104*$E$70 -> 24 | Q104: ='Proy. ventas'!S146 -> 2 | R104: =Q104*$E$70 -> 24 | S104: ='Proy. ventas'!U146 -> 2 | T104: =S104*$E$70 -> 24 | U104: ='Proy. ventas'!W146 -> 2 | V104: =U104*$E$70 -> 24 | W104: ='Proy. ventas'!Y146 -> 2 | X104: =W104*$E$70 -> 24 | Y104: ='Proy. ventas'!AA146 -> 2 | Z104: =Y104*$E$70 -> 24
A105: =Hipótesis!B$61 -> Abono Plan Básico | B105: =D105+F105+H105+J105+L105+N105+P105+R105+T105+V105+X105+Z105 -> 215.85 | C105: ='Proy. ventas'!E147 -> 87 | D105: =C105*$L$32 -> 13.05 | E105: ='Proy. ventas'!G147 -> 93 | F105: =E105*$L$32 -> 13.95 | G105: ='Proy. ventas'!I147 -> 99 | H105: =G105*$L$32 -> 14.85 | I105: ='Proy. ventas'!K147 -> 105 | J105: =I105*$L$32 -> 15.75 | K105: ='Proy. ventas'!M147 -> 111 | L105: =K105*$L$32 -> 16.65 | M105: ='Proy. ventas'!O147 -> 117 | N105: =M105*$L$32 -> 17.55 | O105: ='Proy. ventas'!Q147 -> 123 | P105: =O105*$L$32 -> 18.45 | Q105: ='Proy. ventas'!S147 -> 129 | R105: =Q105*$L$32 -> 19.35 | S105: ='Proy. ventas'!U147 -> 135 | T105: =S105*$L$32 -> 20.25 | U105: ='Proy. ventas'!W147 -> 141 | V105: =U105*$L$32 -> 21.15 | W105: ='Proy. ventas'!Y147 -> 147 | X105: =W105*$L$32 -> 22.05 | Y105: ='Proy. ventas'!AA147 -> 152 | Z105: =Y105*$L$32 -> 22.8
A106: =Hipótesis!B$62 -> Abono Plan Vidriera | B106: =D106+F106+H106+J106+L106+N106+P106+R106+T106+V106+X106+Z106 -> 725.75 | C106: ='Proy. ventas'!E148 -> 176 | D106: =C106*$L$51 -> 44 | E106: ='Proy. ventas'!G148 -> 188 | F106: =E106*$L$51 -> 47 | G106: ='Proy. ventas'!I148 -> 200 | H106: =G106*$L$51 -> 50 | I106: ='Proy. ventas'!K148 -> 212 | J106: =I106*$L$51 -> 53 | K106: ='Proy. ventas'!M148 -> 224 | L106: =K106*$L$51 -> 56 | M106: ='Proy. ventas'!O148 -> 236 | N106: =M106*$L$51 -> 59 | O106: ='Proy. ventas'!Q148 -> 248 | P106: =O106*$L$51 -> 62 | Q106: ='Proy. ventas'!S148 -> 260 | R106: =Q106*$L$51 -> 65 | S106: ='Proy. ventas'!U148 -> 272 | T106: =S106*$L$51 -> 68 | U106: ='Proy. ventas'!W148 -> 284 | V106: =U106*$L$51 -> 71 | W106: ='Proy. ventas'!Y148 -> 296 | X106: =W106*$L$51 -> 74 | Y106: ='Proy. ventas'!AA148 -> 307 | Z106: =Y106*$L$51 -> 76.75
A107: =Hipótesis!B$63 -> Abono Plan Cadena | B107: =D107+F107+H107+J107+L107+N107+P107+R107+T107+V107+X107+Z107 -> 288 | C107: ='Proy. ventas'!E149 -> 29 | D107: =C107*$L$70 -> 17.4 | E107: ='Proy. ventas'!G149 -> 31 | F107: =E107*$L$70 -> 18.6 | G107: ='Proy. ventas'!I149 -> 33 | H107: =G107*$L$70 -> 19.8 | I107: ='Proy. ventas'!K149 -> 35 | J107: =I107*$L$70 -> 21 | K107: ='Proy. ventas'!M149 -> 37 | L107: =K107*$L$70 -> 22.2 | M107: ='Proy. ventas'!O149 -> 39 | N107: =M107*$L$70 -> 23.4 | O107: ='Proy. ventas'!Q149 -> 41 | P107: =O107*$L$70 -> 24.6 | Q107: ='Proy. ventas'!S149 -> 43 | R107: =Q107*$L$70 -> 25.8 | S107: ='Proy. ventas'!U149 -> 45 | T107: =S107*$L$70 -> 27 | U107: ='Proy. ventas'!W149 -> 47 | V107: =U107*$L$70 -> 28.2 | W107: ='Proy. ventas'!Y149 -> 49 | X107: =W107*$L$70 -> 29.4 | Y107: ='Proy. ventas'!AA149 -> 51 | Z107: =Y107*$L$70 -> 30.6
A108: TOTALES | B108: =D108+F108+H108+J108+L108+N108+P108+R108+T108+V108+X108+Z108 -> 1982.1 | C108: =SUM(C102:C107) -> 312 | D108: =SUM(D102:D107) -> 137.45 | E108: =SUM(E102:E107) -> 332 | F108: =SUM(F102:F107) -> 142.55 | G108: =SUM(G102:G107) -> 352 | H108: =SUM(H102:H107) -> 147.65 | I108: =SUM(I102:I107) -> 372 | J108: =SUM(J102:J107) -> 152.75 | ... Z108: =SUM(Z102:Z107) -> 189.65
A110: CONCLUSIÓN
A111: El anexo dimensiona la capacidad operativa desde la demanda. Cada plan tiene un consumo horario propio, obtenido de la suma de las tareas que requiere su alta, y un consumo mensual de soporte que se sostiene mientras el comercio permanece abonado: 0,50 h el Plan Básico, 3,00 h el Plan Vidriera y 12,00 h el Plan Cadena para el alta; 0,15 h, 0,25 h y 0,60 h al mes para el soporte. Multiplicando esas bases horarias por las unidades de la proyección de ventas se obtienen las horas hombre requeridas mes a mes. El total asciende a 440,75 horas en 2026, 1.113,75 en 2027 y 1.982,10 en 2028, con picos mensuales de 87,50, 123,35 y 189,65 horas respectivamente. Contra las 150 horas laborables mensuales de un empleado, la dotación técnica necesaria es de un técnico en 2026 y 2027, y de dos a partir de marzo de 2028. El mes en que ese cociente supera la unidad es el que marca la incorporación en la estructura de costos de recursos humanos: la contratación no se decide por criterio, se desprende del volumen proyectado. El costo de mano de obra por alta resulta de USD 3 en el Plan Básico, USD 18 en el Plan Vidriera y USD 72 en el Plan Cadena, contra precios de lista de USD 25, USD 60 y USD 250. Sumado el kit de equipamiento, el alta cubre el esfuerzo técnico comprometido en los tres planes.

Sheet Mod. ingresos
E1: Modelo de ingresos
B7: Evolución de la participación
B8: 2026 | C8: 2027 | D8: 2028
B9: =Hipótesis!C24 -> 0.03 | C9: =Hipótesis!C25 -> 0.08 | D9: =Hipótesis!C26 -> 0.15
B10: =Hipótesis!D24 -> 48960 | C10: =Hipótesis!D25 -> 130560 | D10: =Hipótesis!D26 -> 244800
B15: Ingresos por servicios
B16: Servicio | C16: Ingresos 2026 | D16: Ingresos 2027 | E16: Ingresos 2028
B17: =Hipótesis!$B$58 -> Alta e instalación Plan Básico | C17: ='Proy. ventas'!D19 -> 750 | D17: ='Proy. ventas'!D82 -> 1275 | E17: ='Proy. ventas'!D144 -> 1775
B18: =Hipótesis!$B$59 -> Alta e instalación Plan Vidriera | C18: ='Proy. ventas'!D20 -> 3720 | D18: ='Proy. ventas'!D83 -> 6120 | E18: ='Proy. ventas'!D145 -> 8580
B19: =Hipótesis!$B$60 -> Alta e instalación Plan Cadena | C19: ='Proy. ventas'!D21 -> 2500 | D19: ='Proy. ventas'!D84 -> 4250 | E19: ='Proy. ventas'!D146 -> 6000
B20: =Hipótesis!$B$61 -> Abono Plan Básico | C20: ='Proy. ventas'!D22 -> 2220 | D20: ='Proy. ventas'!D85 -> 10140 | E20: ='Proy. ventas'!D147 -> 21585
B21: =Hipótesis!$B$62 -> Abono Plan Vidriera | C21: ='Proy. ventas'!D23 -> 8671 | D21: ='Proy. ventas'!D86 -> 40281 | E21: ='Proy. ventas'!D148 -> 84187
B22: =Hipótesis!$B$63 -> Abono Plan Cadena | C22: ='Proy. ventas'!D24 -> 3002 | D22: ='Proy. ventas'!D87 -> 17064 | E22: ='Proy. ventas'!D149 -> 37920
B30: TOTALES | C30: =SUM(C17:C29) -> 20863 | D30: =SUM(D17:D29) -> 79130 | E30: =SUM(E17:E29) -> 160047

Sheet Costos fijos
F1: Estructura de costos fijos
C3: Evolución de la participación | G3: Costos fijos - Totales
C4: 2026 | D4: 2027 | E4: 2028 | G4: 2026 | H4: 2027 | I4: 2028
C5: =Hipótesis!C24 -> 0.03 | D5: =Hipótesis!C25 -> 0.08 | E5: =Hipótesis!C26 -> 0.15 | G5: =P25 -> 25440 | H5: =P42 -> 33300 | I5: =P60 -> 37260
C6: =Hipótesis!D24 -> 48960 | D6: =Hipótesis!D25 -> 130560 | E6: =Hipótesis!D26 -> 244800
G7: Costos fijos de promoción - Totales
G8: 2026 | H8: 2027 | I8: 2028
G9: =SUM(P23:P24) -> 2400 | H9: =SUM(P40:P41) -> 3240 | I9: =SUM(P58:P59) -> 4320
B11: Costos fijos - Año 2026
B12: Rubro | C12: Concepto | D12: Enero | E12: Febrero | F12: Marzo | G12: Abril | H12: Mayo | I12: Junio | J12: Julio | K12: Agosto | L12: Septiembre | M12: Octubre | N12: Noviembre | O12: Diciembre | P12: Total anual | Q12: Observaciones
B13: Servicios | C13: Luz | D13: 45 | E13: 45 | F13: 45 | G13: 45 | H13: 45 | I13: 45 | J13: 45 | K13: 45 | L13: 45 | M13: 45 | N13: 45 | O13: 45 | P13: =SUM(D13:O13) -> 540
C14: Agua | D14: 15 | E14: 15 | F14: 15 | G14: 15 | H14: 15 | I14: 15 | J14: 15 | K14: 15 | L14: 15 | M14: 15 | N14: 15 | O14: 15 | P14: =SUM(D14:O14) -> 180
C15: Internet y telefonía fija | D15: 60 | E15: 60 | F15: 60 | G15: 60 | H15: 60 | I15: 60 | J15: 60 | K15: 60 | L15: 60 | M15: 60 | N15: 60 | O15: 60 | P15: =SUM(D15:O15) -> 720
C16: Telefonía móvil | D16: 30 | E16: 30 | F16: 30 | G16: 30 | H16: 30 | I16: 30 | J16: 30 | K16: 30 | L16: 30 | M16: 30 | N16: 30 | O16: 30 | P16: =SUM(D16:O16) -> 360 | Q16: Una línea por técnico y por vendedor; escala con la dotación.
C17: Infraestructura cloud base | D17: 250 | E17: 250 | F17: 250 | G17: 250 | H17: 250 | I17: 250 | J17: 250 | K17: 250 | L17: 250 | M17: 250 | N17: 250 | O17: 250 | P17: =SUM(D17:O17) -> 3000 | Q17: Capacidad mínima para operar con independencia de la cantidad de comercios activos.
C18: Licencias de software | D18: 120 | E18: 120 | F18: 120 | G18: 120 | H18: 120 | I18: 120 | J18: 120 | K18: 120 | L18: 120 | M18: 120 | N18: 120 | O18: 120 | P18: =SUM(D18:O18) -> 1440 | Q18: Herramientas de desarrollo, monitoreo y productividad.
B19: Alquiler | C19: Oficina | D19: 600 | E19: 600 | F19: 600 | G19: 600 | H19: 600 | I19: 600 | J19: 600 | K19: 600 | L19: 600 | M19: 600 | N19: 600 | O19: 600 | P19: =SUM(D19:O19) -> 7200 | Q19: En 2028 se amplía el espacio por el crecimiento de la dotación.
C20: Auditoría y certificación ISO 27001 | D20: 0 | E20: 0 | F20: 0 | G20: 0 | H20: 0 | I20: 0 | J20: 0 | K20: 0 | L20: 0 | M20: 0 | N20: 0 | O20: 0 | P20: =SUM(D20:O20) -> 0 | Q20: Implementación durante 2027 y mantenimiento desde 2028.
B21: Honorarios | C21: Estudio Contable Externo | D21: 400 | E21: 400 | F21: 400 | G21: 400 | H21: 400 | I21: 400 | J21: 400 | K21: 400 | L21: 400 | M21: 400 | N21: 400 | O21: 400 | P21: =SUM(D21:O21) -> 4800 | Q21: Escala por tramos con la cantidad de empleados.
C22: Agencia de marketing | D22: 400 | E22: 400 | F22: 400 | G22: 400 | H22: 400 | I22: 400 | J22: 400 | K22: 400 | L22: 400 | M22: 400 | N22: 400 | O22: 400 | P22: =SUM(D22:O22) -> 4800 | Q22: Abono mensual; la pauta se imputa aparte.
B23: Publicidad online | C23: Campañas base en Meta y Google | D23: 150 | E23: 150 | F23: 150 | G23: 150 | H23: 150 | I23: 150 | J23: 150 | K23: 150 | L23: 150 | M23: 150 | N23: 150 | O23: 150 | P23: =SUM(D23:O23) -> 1800 | Q23: Pauta base permanente; las campañas de captación intensiva van en costos variables.
C24: Sitio web, SEO local y WhatsApp Business | D24: 50 | E24: 50 | F24: 50 | G24: 50 | H24: 50 | I24: 50 | J24: 50 | K24: 50 | L24: 50 | M24: 50 | N24: 50 | O24: 50 | P24: =SUM(D24:O24) -> 600
B25: TOTAL | D25: =SUM(D13:D24) -> 2120 | E25: =SUM(E13:E24) -> 2120 | F25: =SUM(F13:F24) -> 2120 | G25: =SUM(G13:G24) -> 2120 | H25: =SUM(H13:H24) -> 2120 | I25: =SUM(I13:I24) -> 2120 | J25: =SUM(J13:J24) -> 2120 | K25: =SUM(K13:K24) -> 2120 | ... O25: =SUM(O13:O24) -> 2120 | P25: =SUM(D25:O25) -> 25440
B28: Costos fijos - Año 2027
B29: Rubro | C29: Concepto | D29: Enero | E29: Febrero | F29: Marzo | G29: Abril | H29: Mayo | I29: Junio | J29: Julio | K29: Agosto | L29: Septiembre | M29: Octubre | N29: Noviembre | O29: Diciembre | P29: Total anual | Q29: Observaciones
B30: Servicios | C30: Luz | D30: 45 | E30: 45 | F30: 45 | G30: 45 | H30: 45 | I30: 45 | J30: 45 | K30: 45 | L30: 45 | M30: 45 | N30: 45 | O30: 45 | P30: =SUM(D30:O30) -> 540
C31: Agua | D31: 15 | E31: 15 | F31: 15 | G31: 15 | H31: 15 | I31: 15 | J31: 15 | K31: 15 | L31: 15 | M31: 15 | N31: 15 | O31: 15 | P31: =SUM(D31:O31) -> 180
C32: Internet y telefonía fija | D32: 60 | E32: 60 | F32: 60 | G32: 60 | H32: 60 | I32: 60 | J32: 60 | K32: 60 | L32: 60 | M32: 60 | N32: 60 | O32: 60 | P32: =SUM(D32:O32) -> 720
C33: Telefonía móvil | D33: 45 | E33: 45 | F33: 45 | G33: 45 | H33: 45 | I33: 45 | J33: 45 | K33: 45 | L33: 45 | M33: 45 | N33: 45 | O33: 45 | P33: =SUM(D33:O33) -> 540 | Q33: Una línea por técnico y por vendedor; escala con la dotación.
C34: Infraestructura cloud base | D34: 350 | E34: 350 | F34: 350 | G34: 350 | H34: 350 | I34: 350 | J34: 350 | K34: 350 | L34: 350 | M34: 350 | N34: 350 | O34: 350 | P34: =SUM(D34:O34) -> 4200 | Q34: Capacidad mínima para operar con independencia de la cantidad de comercios activos.
C35: Licencias de software | D35: 140 | E35: 140 | F35: 140 | G35: 140 | H35: 140 | I35: 140 | J35: 140 | K35: 140 | L35: 140 | M35: 140 | N35: 140 | O35: 140 | P35: =SUM(D35:O35) -> 1680 | Q35: Herramientas de desarrollo, monitoreo y productividad.
B36: Alquiler | C36: Oficina | D36: 600 | E36: 600 | F36: 600 | G36: 600 | H36: 600 | I36: 600 | J36: 600 | K36: 600 | L36: 600 | M36: 600 | N36: 600 | O36: 600 | P36: =SUM(D36:O36) -> 7200 | Q36: En 2028 se amplía el espacio por el crecimiento de la dotación.
C37: Auditoría y certificación ISO 27001 | D37: 400 | E37: 400 | F37: 400 | G37: 400 | H37: 400 | I37: 400 | J37: 400 | K37: 400 | L37: 400 | M37: 400 | N37: 400 | O37: 400 | P37: =SUM(D37:O37) -> 4800 | Q37: Implementación durante 2027 y mantenimiento desde 2028.
B38: Honorarios | C38: Estudio Contable Externo | D38: 450 | E38: 450 | F38: 450 | G38: 450 | H38: 450 | I38: 450 | J38: 450 | K38: 450 | L38: 450 | M38: 450 | N38: 450 | O38: 450 | P38: =SUM(D38:O38) -> 5400 | Q38: Escala por tramos con la cantidad de empleados.
C39: Agencia de marketing | D39: 400 | E39: 400 | F39: 400 | G39: 400 | H39: 400 | I39: 400 | J39: 400 | K39: 400 | L39: 400 | M39: 400 | N39: 400 | O39: 400 | P39: =SUM(D39:O39) -> 4800 | Q39: Abono mensual; la pauta se imputa aparte.
B40: Publicidad online | C40: Campañas base en Meta y Google | D40: 220 | E40: 220 | F40: 220 | G40: 220 | H40: 220 | I40: 220 | J40: 220 | K40: 220 | L40: 220 | M40: 220 | N40: 220 | O40: 220 | P40: =SUM(D40:O40) -> 2640 | Q40: Pauta base permanente; las campañas de captación intensiva van en costos variables.
C41: Sitio web, SEO local y WhatsApp Business | D41: 50 | E41: 50 | F41: 50 | G41: 50 | H41: 50 | I41: 50 | J41: 50 | K41: 50 | L41: 50 | M41: 50 | N41: 50 | O41: 50 | P41: =SUM(D41:O41) -> 600
B42: TOTAL | D42: =SUM(D30:D41) -> 2775 | E42: =SUM(E30:E41) -> 2775 | F42: =SUM(F30:F41) -> 2775 | G42: =SUM(G30:G41) -> 2775 | H42: =SUM(H30:H41) -> 2775 | I42: =SUM(I30:I41) -> 2775 | J42: =SUM(J30:J41) -> 2775 | K42: =SUM(K30:K41) -> 2775 | ... O42: =SUM(O30:O41) -> 2775 | P42: =SUM(D42:O42) -> 33300
B46: Costos fijos - Año 2028
B47: Rubro | C47: Concepto | D47: Enero | E47: Febrero | F47: Marzo | G47: Abril | H47: Mayo | I47: Junio | J47: Julio | K47: Agosto | L47: Septiembre | M47: Octubre | N47: Noviembre | O47: Diciembre | P47: Total anual | Q47: Observaciones
B48: Servicios | C48: Luz | D48: 50 | E48: 50 | F48: 50 | G48: 50 | H48: 50 | I48: 50 | J48: 50 | K48: 50 | L48: 50 | M48: 50 | N48: 50 | O48: 50 | P48: =SUM(D48:O48) -> 600
C49: Agua | D49: 15 | E49: 15 | F49: 15 | G49: 15 | H49: 15 | I49: 15 | J49: 15 | K49: 15 | L49: 15 | M49: 15 | N49: 15 | O49: 15 | P49: =SUM(D49:O49) -> 180
C50: Internet y telefonía fija | D50: 60 | E50: 60 | F50: 60 | G50: 60 | H50: 60 | I50: 60 | J50: 60 | K50: 60 | L50: 60 | M50: 60 | N50: 60 | O50: 60 | P50: =SUM(D50:O50) -> 720
C51: Telefonía móvil | D51: 60 | E51: 60 | F51: 60 | G51: 60 | H51: 60 | I51: 60 | J51: 60 | K51: 60 | L51: 60 | M51: 60 | N51: 60 | O51: 60 | P51: =SUM(D51:O51) -> 720 | Q51: Una línea por técnico y por vendedor; escala con la dotación.
C52: Infraestructura cloud base | D52: 500 | E52: 500 | F52: 500 | G52: 500 | H52: 500 | I52: 500 | J52: 500 | K52: 500 | L52: 500 | M52: 500 | N52: 500 | O52: 500 | P52: =SUM(D52:O52) -> 6000 | Q52: Capacidad mínima para operar con independencia de la cantidad de comercios activos.
C53: Licencias de software | D53: 160 | E53: 160 | F53: 160 | G53: 160 | H53: 160 | I53: 160 | J53: 160 | K53: 160 | L53: 160 | M53: 160 | N53: 160 | O53: 160 | P53: =SUM(D53:O53) -> 1920 | Q53: Herramientas de desarrollo, monitoreo y productividad.
B54: Alquiler | C54: Oficina | D54: 700 | E54: 700 | F54: 700 | G54: 700 | H54: 700 | I54: 700 | J54: 700 | K54: 700 | L54: 700 | M54: 700 | N54: 700 | O54: 700 | P54: =SUM(D54:O54) -> 8400 | Q54: En 2028 se amplía el espacio por el crecimiento de la dotación.
C55: Auditoría y certificación ISO 27001 | D55: 250 | E55: 250 | F55: 250 | G55: 250 | H55: 250 | I55: 250 | J55: 250 | K55: 250 | L55: 250 | M55: 250 | N55: 250 | O55: 250 | P55: =SUM(D55:O55) -> 3000 | Q55: Implementación durante 2027 y mantenimiento desde 2028.
B56: Honorarios | C56: Estudio Contable Externo | D56: 500 | E56: 500 | F56: 500 | G56: 500 | H56: 500 | I56: 500 | J56: 500 | K56: 500 | L56: 500 | M56: 500 | N56: 500 | O56: 500 | P56: =SUM(D56:O56) -> 6000 | Q56: Escala por tramos con la cantidad de empleados.
C57: Agencia de marketing | D57: 450 | E57: 450 | F57: 450 | G57: 450 | H57: 450 | I57: 450 | J57: 450 | K57: 450 | L57: 450 | M57: 450 | N57: 450 | O57: 450 | P57: =SUM(D57:O57) -> 5400 | Q57: Abono mensual; la pauta se imputa aparte.
B58: Publicidad online | C58: Campañas base en Meta y Google | D58: 300 | E58: 300 | F58: 300 | G58: 300 | H58: 300 | I58: 300 | J58: 300 | K58: 300 | L58: 300 | M58: 300 | N58: 300 | O58: 300 | P58: =SUM(D58:O58) -> 3600 | Q58: Pauta base permanente; las campañas de captación intensiva van en costos variables.
C59: Sitio web, SEO local y WhatsApp Business | D59: 60 | E59: 60 | F59: 60 | G59: 60 | H59: 60 | I59: 60 | J59: 60 | K59: 60 | L59: 60 | M59: 60 | N59: 60 | O59: 60 | P59: =SUM(D59:O59) -> 720
B60: TOTAL | D60: =SUM(D48:D59) -> 3105 | E60: =SUM(E48:E59) -> 3105 | F60: =SUM(F48:F59) -> 3105 | G60: =SUM(G48:G59) -> 3105 | H60: =SUM(H48:H59) -> 3105 | I60: =SUM(I48:I59) -> 3105 | J60: =SUM(J48:J59) -> 3105 | K60: =SUM(K48:K59) -> 3105 | ... O60: =SUM(O48:O59) -> 3105 | P60: =SUM(D60:O60) -> 37260

Sheet Costos variables
F1: Estructura de costos variables
B4: Evolución de la participación | H4: Costos variables - Totales
B5: 2026 | C5: 2027 | D5: 2028 | H5: 2026 | I5: 2027 | J5: 2028
B6: =Hipótesis!C24 -> 0.03 | C6: =Hipótesis!C25 -> 0.08 | D6: =Hipótesis!C26 -> 0.15 | H6: =AB32 -> 5402 | I6: =AB55 -> 11065.9 | J6: =AB78 -> 17774.3
B7: =Hipótesis!D24 -> 48960 | C7: =Hipótesis!D25 -> 130560 | D7: =Hipótesis!D26 -> 244800
H8: Costos de promoción variables - Totales
H9: 2026 | I9: 2027 | J9: 2028
H10: =SUM(AB21:AB24) -> 2401 | I10: =SUM(AB44:AB47) -> 4013.5 | J10: =SUM(AB67:AB70) -> 5616.5
B12: Costos variables - Año 2026
A13: Rubro | B13: Descripción | C13: Costo unitario | D13: Enero | F13: Febrero | H13: Marzo | J13: Abril | L13: Mayo | N13: Junio | P13: Julio | R13: Agosto | T13: Septiembre | V13: Octubre | X13: Noviembre | Z13: Diciembre | AB13: Total anual
D14: Cant. | E14: Costo | F14: Cant. | G14: Costo | H14: Cant. | I14: Costo | J14: Cant. | K14: Costo | L14: Cant. | M14: Costo | N14: Cant. | O14: Costo | P14: Cant. | Q14: Costo | R14: Cant. | S14: Costo | T14: Cant. | U14: Costo | V14: Cant. | W14: Costo | X14: Cant. | Y14: Costo | Z14: Cant. | AA14: Costo
A15: Operación | B15: Comisión del vendedor por alta concretada | C15: 15 | D15: ='Proy. ventas'!E19+'Proy. ventas'!E20+'Proy. ventas'!E21 -> 0 | E15: =D15*$C15 -> 0 | F15: ='Proy. ventas'!G19+'Proy. ventas'!G20+'Proy. ventas'!G21 -> 2 | G15: =F15*$C15 -> 30 | H15: ='Proy. ventas'!I19+'Proy. ventas'!I20+'Proy. ventas'!I21 -> 4 | I15: =H15*$C15 -> 60 | J15: ='Proy. ventas'!K19+'Proy. ventas'!K20+'Proy. ventas'!K21 -> 6 | K15: =J15*$C15 -> 90 | L15: ='Proy. ventas'!M19+'Proy. ventas'!M20+'Proy. ventas'!M21 -> 8 | M15: =L15*$C15 -> 120 | N15: ='Proy. ventas'!O19+'Proy. ventas'!O20+'Proy. ventas'!O21 -> 9 | O15: =N15*$C15 -> 135 | P15: ='Proy. ventas'!Q19+'Proy. ventas'!Q20+'Proy. ventas'!Q21 -> 10 | Q15: =P15*$C15 -> 150 | R15: ='Proy. ventas'!S19+'Proy. ventas'!S20+'Proy. ventas'!S21 -> 11 | S15: =R15*$C15 -> 165 | T15: ='Proy. ventas'!U19+'Proy. ventas'!U20+'Proy. ventas'!U21 -> 12 | U15: =T15*$C15 -> 180 | V15: ='Proy. ventas'!W19+'Proy. ventas'!W20+'Proy. ventas'!W21 -> 13 | W15: =V15*$C15 -> 195 | X15: ='Proy. ventas'!Y19+'Proy. ventas'!Y20+'Proy. ventas'!Y21 -> 13 | Y15: =X15*$C15 -> 195 | Z15: ='Proy. ventas'!AA19+'Proy. ventas'!AA20+'Proy. ventas'!AA21 -> 14 | AA15: =Z15*$C15 -> 210 | AB15: =E15+G15+I15+K15+M15+O15+Q15+S15+U15+W15+Y15+AA15 -> 1530
B16: Movilidad y viáticos de instalación | C16: 5 | D16: ='Proy. ventas'!E20+'Proy. ventas'!E21 -> 0 | E16: =D16*$C16 -> 0 | F16: ='Proy. ventas'!G20+'Proy. ventas'!G21 -> 1 | G16: =F16*$C16 -> 5 | H16: ='Proy. ventas'!I20+'Proy. ventas'!I21 -> 3 | I16: =H16*$C16 -> 15 | J16: ='Proy. ventas'!K20+'Proy. ventas'!K21 -> 4 | K16: =J16*$C16 -> 20 | L16: ='Proy. ventas'!M20+'Proy. ventas'!M21 -> 6 | M16: =L16*$C16 -> 30 | N16: ='Proy. ventas'!O20+'Proy. ventas'!O21 -> 6 | O16: =N16*$C16 -> 30 | P16: ='Proy. ventas'!Q20+'Proy. ventas'!Q21 -> 7 | Q16: =P16*$C16 -> 35 | R16: ='Proy. ventas'!S20+'Proy. ventas'!S21 -> 8 | S16: =R16*$C16 -> 40 | T16: ='Proy. ventas'!U20+'Proy. ventas'!U21 -> 8 | U16: =T16*$C16 -> 40 | V16: ='Proy. ventas'!W20+'Proy. ventas'!W21 -> 9 | W16: =V16*$C16 -> 45 | X16: ='Proy. ventas'!Y20+'Proy. ventas'!Y21 -> 9 | Y16: =X16*$C16 -> 45 | Z16: ='Proy. ventas'!AA20+'Proy. ventas'!AA21 -> 11 | AA16: =Z16*$C16 -> 55 | AB16: =E16+G16+I16+K16+M16+O16+Q16+S16+U16+W16+Y16+AA16 -> 360
B17: Consumo cloud por comercio activo | C17: 0.35 | D17: ='Proy. ventas'!E22+'Proy. ventas'!E23+'Proy. ventas'!E24 -> 0 | E17: =D17*$C17 -> 0 | F17: ='Proy. ventas'!G22+'Proy. ventas'!G23+'Proy. ventas'!G24 -> 2 | G17: =F17*$C17 -> 0.7 | H17: ='Proy. ventas'!I22+'Proy. ventas'!I23+'Proy. ventas'!I24 -> 6 | I17: =H17*$C17 -> 2.1 | J17: ='Proy. ventas'!K22+'Proy. ventas'!K23+'Proy. ventas'!K24 -> 12 | K17: =J17*$C17 -> 4.2 | L17: ='Proy. ventas'!M22+'Proy. ventas'!M23+'Proy. ventas'!M24 -> 20 | M17: =L17*$C17 -> 7 | N17: ='Proy. ventas'!O22+'Proy. ventas'!O23+'Proy. ventas'!O24 -> 29 | O17: =N17*$C17 -> 10.15 | P17: ='Proy. ventas'!Q22+'Proy. ventas'!Q23+'Proy. ventas'!Q24 -> 39 | Q17: =P17*$C17 -> 13.65 | R17: ='Proy. ventas'!S22+'Proy. ventas'!S23+'Proy. ventas'!S24 -> 50 | S17: =R17*$C17 -> 17.5 | T17: ='Proy. ventas'!U22+'Proy. ventas'!U23+'Proy. ventas'!U24 -> 62 | U17: =T17*$C17 -> 21.7 | V17: ='Proy. ventas'!W22+'Proy. ventas'!W23+'Proy. ventas'!W24 -> 75 | W17: =V17*$C17 -> 26.25 | X17: ='Proy. ventas'!Y22+'Proy. ventas'!Y23+'Proy. ventas'!Y24 -> 88 | Y17: =X17*$C17 -> 30.8 | Z17: ='Proy. ventas'!AA22+'Proy. ventas'!AA23+'Proy. ventas'!AA24 -> 102 | AA17: =Z17*$C17 -> 35.7 | AB17: =E17+G17+I17+K17+M17+O17+Q17+S17+U17+W17+Y17+AA17 -> 169.75
B18: Gateway de notificaciones | C18: 0.15 | D18: ='Proy. ventas'!E22+'Proy. ventas'!E23+'Proy. ventas'!E24 -> 0 | E18: =D18*$C18 -> 0 | F18: ='Proy. ventas'!G22+'Proy. ventas'!G23+'Proy. ventas'!G24 -> 2 | G18: =F18*$C18 -> 0.3 | H18: ='Proy. ventas'!I22+'Proy. ventas'!I23+'Proy. ventas'!I24 -> 6 | I18: =H18*$C18 -> 0.9 | J18: ='Proy. ventas'!K22+'Proy. ventas'!K23+'Proy. ventas'!K24 -> 12 | K18: =J18*$C18 -> 1.8 | L18: ='Proy. ventas'!M22+'Proy. ventas'!M23+'Proy. ventas'!M24 -> 20 | M18: =L18*$C18 -> 3 | N18: ='Proy. ventas'!O22+'Proy. ventas'!O23+'Proy. ventas'!O24 -> 29 | O18: =N18*$C18 -> 4.35 | P18: ='Proy. ventas'!Q22+'Proy. ventas'!Q23+'Proy. ventas'!Q24 -> 39 | Q18: =P18*$C18 -> 5.85 | R18: ='Proy. ventas'!S22+'Proy. ventas'!S23+'Proy. ventas'!S24 -> 50 | S18: =R18*$C18 -> 7.5 | T18: ='Proy. ventas'!U22+'Proy. ventas'!U23+'Proy. ventas'!U24 -> 62 | U18: =T18*$C18 -> 9.3 | V18: ='Proy. ventas'!W22+'Proy. ventas'!W23+'Proy. ventas'!W24 -> 75 | W18: =V18*$C18 -> 11.25 | X18: ='Proy. ventas'!Y22+'Proy. ventas'!Y23+'Proy. ventas'!Y24 -> 88 | Y18: =X18*$C18 -> 13.2 | Z18: ='Proy. ventas'!AA22+'Proy. ventas'!AA23+'Proy. ventas'!AA24 -> 102 | AA18: =Z18*$C18 -> 15.3 | AB18: =E18+G18+I18+K18+M18+O18+Q18+S18+U18+W18+Y18+AA18 -> 72.75
B19: Comisiones de medios de pago | C19: 0.9 | D19: ='Proy. ventas'!E22+'Proy. ventas'!E23+'Proy. ventas'!E24 -> 0 | E19: =D19*$C19 -> 0 | F19: ='Proy. ventas'!G22+'Proy. ventas'!G23+'Proy. ventas'!G24 -> 2 | G19: =F19*$C19 -> 1.8 | H19: ='Proy. ventas'!I22+'Proy. ventas'!I23+'Proy. ventas'!I24 -> 6 | I19: =H19*$C19 -> 5.4 | J19: ='Proy. ventas'!K22+'Proy. ventas'!K23+'Proy. ventas'!K24 -> 12 | K19: =J19*$C19 -> 10.8 | L19: ='Proy. ventas'!M22+'Proy. ventas'!M23+'Proy. ventas'!M24 -> 20 | M19: =L19*$C19 -> 18 | N19: ='Proy. ventas'!O22+'Proy. ventas'!O23+'Proy. ventas'!O24 -> 29 | O19: =N19*$C19 -> 26.1 | P19: ='Proy. ventas'!Q22+'Proy. ventas'!Q23+'Proy. ventas'!Q24 -> 39 | Q19: =P19*$C19 -> 35.1 | R19: ='Proy. ventas'!S22+'Proy. ventas'!S23+'Proy. ventas'!S24 -> 50 | S19: =R19*$C19 -> 45 | T19: ='Proy. ventas'!U22+'Proy. ventas'!U23+'Proy. ventas'!U24 -> 62 | U19: =T19*$C19 -> 55.8 | V19: ='Proy. ventas'!W22+'Proy. ventas'!W23+'Proy. ventas'!W24 -> 75 | W19: =V19*$C19 -> 67.5 | X19: ='Proy. ventas'!Y22+'Proy. ventas'!Y23+'Proy. ventas'!Y24 -> 88 | Y19: =X19*$C19 -> 79.2 | Z19: ='Proy. ventas'!AA22+'Proy. ventas'!AA23+'Proy. ventas'!AA24 -> 102 | AA19: =Z19*$C19 -> 91.8 | AB19: =E19+G19+I19+K19+M19+O19+Q19+S19+U19+W19+Y19+AA19 -> 436.5
B20: Reposición de equipamiento no recuperado | C20: 6 | D20: ='Proy. ventas'!E20+'Proy. ventas'!E21 -> 0 | E20: =D20*$C20 -> 0 | F20: ='Proy. ventas'!G20+'Proy. ventas'!G21 -> 1 | G20: =F20*$C20 -> 6 | H20: ='Proy. ventas'!I20+'Proy. ventas'!I21 -> 3 | I20: =H20*$C20 -> 18 | J20: ='Proy. ventas'!K20+'Proy. ventas'!K21 -> 4 | K20: =J20*$C20 -> 24 | L20: ='Proy. ventas'!M20+'Proy. ventas'!M21 -> 6 | M20: =L20*$C20 -> 36 | N20: ='Proy. ventas'!O20+'Proy. ventas'!O21 -> 6 | O20: =N20*$C20 -> 36 | P20: ='Proy. ventas'!Q20+'Proy. ventas'!Q21 -> 7 | Q20: =P20*$C20 -> 42 | R20: ='Proy. ventas'!S20+'Proy. ventas'!S21 -> 8 | S20: =R20*$C20 -> 48 | T20: ='Proy. ventas'!U20+'Proy. ventas'!U21 -> 8 | U20: =T20*$C20 -> 48 | V20: ='Proy. ventas'!W20+'Proy. ventas'!W21 -> 9 | W20: =V20*$C20 -> 54 | X20: ='Proy. ventas'!Y20+'Proy. ventas'!Y21 -> 9 | Y20: =X20*$C20 -> 54 | Z20: ='Proy. ventas'!AA20+'Proy. ventas'!AA21 -> 11 | AA20: =Z20*$C20 -> 66 | AB20: =E20+G20+I20+K20+M20+O20+Q20+S20+U20+W20+Y20+AA20 -> 432
A21: Promoción | B21: Bonificación del alta - Plan Básico | C21: =Hipótesis!$C$58*0.3 -> 7.5 | D21: ='Proy. ventas'!E19 -> 0 | E21: =D21*$C21 -> 0 | F21: ='Proy. ventas'!G19 -> 1 | G21: =F21*$C21 -> 7.5 | H21: ='Proy. ventas'!I19 -> 1 | I21: =H21*$C21 -> 7.5 | J21: ='Proy. ventas'!K19 -> 2 | K21: =J21*$C21 -> 15 | L21: ='Proy. ventas'!M19 -> 2 | M21: =L21*$C21 -> 15 | N21: ='Proy. ventas'!O19 -> 3 | O21: =N21*$C21 -> 22.5 | P21: ='Proy. ventas'!Q19 -> 3 | Q21: =P21*$C21 -> 22.5 | R21: ='Proy. ventas'!S19 -> 3 | S21: =R21*$C21 -> 22.5 | T21: ='Proy. ventas'!U19 -> 4 | U21: =T21*$C21 -> 30 | V21: ='Proy. ventas'!W19 -> 4 | W21: =V21*$C21 -> 30 | X21: ='Proy. ventas'!Y19 -> 4 | Y21: =X21*$C21 -> 30 | Z21: ='Proy. ventas'!AA19 -> 3 | AA21: =Z21*$C21 -> 22.5 | AB21: =E21+G21+I21+K21+M21+O21+Q21+S21+U21+W21+Y21+AA21 -> 225
B22: Bonificación del alta - Plan Vidriera | C22: =Hipótesis!$C$59*0.3 -> 18 | D22: ='Proy. ventas'!E20 -> 0 | E22: =D22*$C22 -> 0 | F22: ='Proy. ventas'!G20 -> 1 | G22: =F22*$C22 -> 18 | H22: ='Proy. ventas'!I20 -> 3 | I22: =H22*$C22 -> 54 | J22: ='Proy. ventas'!K20 -> 4 | K22: =J22*$C22 -> 72 | L22: ='Proy. ventas'!M20 -> 5 | M22: =L22*$C22 -> 90 | N22: ='Proy. ventas'!O20 -> 5 | O22: =N22*$C22 -> 90 | P22: ='Proy. ventas'!Q20 -> 6 | Q22: =P22*$C22 -> 108 | R22: ='Proy. ventas'!S20 -> 7 | S22: =R22*$C22 -> 126 | T22: ='Proy. ventas'!U20 -> 7 | U22: =T22*$C22 -> 126 | V22: ='Proy. ventas'!W20 -> 8 | W22: =V22*$C22 -> 144 | X22: ='Proy. ventas'!Y20 -> 8 | Y22: =X22*$C22 -> 144 | Z22: ='Proy. ventas'!AA20 -> 8 | AA22: =Z22*$C22 -> 144 | AB22: =E22+G22+I22+K22+M22+O22+Q22+S22+U22+W22+Y22+AA22 -> 1116
B23: Bonificación del alta - Plan Cadena | C23: =Hipótesis!$C$60*0.3 -> 75 | D23: ='Proy. ventas'!E21 -> 0 | E23: =D23*$C23 -> 0 | F23: ='Proy. ventas'!G21 -> 0 | G23: =F23*$C23 -> 0 | H23: ='Proy. ventas'!I21 -> 0 | I23: =H23*$C23 -> 0 | J23: ='Proy. ventas'!K21 -> 0 | K23: =J23*$C23 -> 0 | L23: ='Proy. ventas'!M21 -> 1 | M23: =L23*$C23 -> 75 | N23: ='Proy. ventas'!O21 -> 1 | O23: =N23*$C23 -> 75 | P23: ='Proy. ventas'!Q21 -> 1 | Q23: =P23*$C23 -> 75 | R23: ='Proy. ventas'!S21 -> 1 | S23: =R23*$C23 -> 75 | T23: ='Proy. ventas'!U21 -> 1 | U23: =T23*$C23 -> 75 | V23: ='Proy. ventas'!W21 -> 1 | W23: =V23*$C23 -> 75 | X23: ='Proy. ventas'!Y21 -> 1 | Y23: =X23*$C23 -> 75 | Z23: ='Proy. ventas'!AA21 -> 3 | AA23: =Z23*$C23 -> 225 | AB23: =E23+G23+I23+K23+M23+O23+Q23+S23+U23+W23+Y23+AA23 -> 750
B24: Incentivo del programa de referidos | C24: 10 | D24: =ROUND(('Proy. ventas'!E19+'Proy. ventas'!E20+'Proy. ventas'!E21)*0.3,0) -> 0 | E24: =D24*$C24 -> 0 | F24: =ROUND(('Proy. ventas'!G19+'Proy. ventas'!G20+'Proy. ventas'!G21)*0.3,0) -> 1 | G24: =F24*$C24 -> 10 | H24: =ROUND(('Proy. ventas'!I19+'Proy. ventas'!I20+'Proy. ventas'!I21)*0.3,0) -> 1 | I24: =H24*$C24 -> 10 | J24: =ROUND(('Proy. ventas'!K19+'Proy. ventas'!K20+'Proy. ventas'!K21)*0.3,0) -> 2 | K24: =J24*$C24 -> 20 | L24: =ROUND(('Proy. ventas'!M19+'Proy. ventas'!M20+'Proy. ventas'!M21)*0.3,0) -> 2 | M24: =L24*$C24 -> 20 | N24: =ROUND(('Proy. ventas'!O19+'Proy. ventas'!O20+'Proy. ventas'!O21)*0.3,0) -> 3 | O24: =N24*$C24 -> 30 | P24: =ROUND(('Proy. ventas'!Q19+'Proy. ventas'!Q20+'Proy. ventas'!Q21)*0.3,0) -> 3 | Q24: =P24*$C24 -> 30 | R24: =ROUND(('Proy. ventas'!S19+'Proy. ventas'!S20+'Proy. ventas'!S21)*0.3,0) -> 3 | S24: =R24*$C24 -> 30 | T24: =ROUND(('Proy. ventas'!U19+'Proy. ventas'!U20+'Proy. ventas'!U21)*0.3,0) -> 4 | U24: =T24*$C24 -> 40 | V24: =ROUND(('Proy. ventas'!W19+'Proy. ventas'!W20+'Proy. ventas'!W21)*0.3,0) -> 4 | W24: =V24*$C24 -> 40 | X24: =ROUND(('Proy. ventas'!Y19+'Proy. ventas'!Y20+'Proy. ventas'!Y21)*0.3,0) -> 4 | Y24: =X24*$C24 -> 40 | Z24: =ROUND(('Proy. ventas'!AA19+'Proy. ventas'!AA20+'Proy. ventas'!AA21)*0.3,0) -> 4 | AA24: =Z24*$C24 -> 40 | AB24: =E24+G24+I24+K24+M24+O24+Q24+S24+U24+W24+Y24+AA24 -> 310
B32: TOTAL | E32: =SUM(E15:E24) -> 0 | G32: =SUM(G15:G24) -> 79.3 | I32: =SUM(I15:I24) -> 172.9 | K32: =SUM(K15:K24) -> 257.8 | M32: =SUM(M15:M24) -> 414 | O32: =SUM(O15:O24) -> 459.1 | Q32: =SUM(Q15:Q24) -> 517.1 | S32: =SUM(S15:S24) -> 576.5 | U32: =SUM(U15:U24) -> 625.8 | W32: =SUM(W15:W24) -> 688 | Y32: =SUM(Y15:Y24) -> 706.2 | AA32: =SUM(AA15:AA24) -> 905.3 | AB32: =SUM(AB15:AB24) -> 5402
B35: Costos variables - Año 2027
A36: Rubro | B36: Descripción | C36: Costo unitario | D36: Enero | F36: Febrero | H36: Marzo | J36: Abril | L36: Mayo | N36: Junio | P36: Julio | R36: Agosto | T36: Septiembre | V36: Octubre | X36: Noviembre | Z36: Diciembre | AB36: Total anual
D37: Cant. | E37: Costo | F37: Cant. | G37: Costo | H37: Cant. | I37: Costo | J37: Cant. | K37: Costo | L37: Cant. | M37: Costo | N37: Cant. | O37: Costo | P37: Cant. | Q37: Costo | R37: Cant. | S37: Costo | T37: Cant. | U37: Costo | V37: Cant. | W37: Costo | X37: Cant. | Y37: Costo | Z37: Cant. | AA37: Costo
A38: Operación | B38: Comisión del vendedor por alta concretada | C38: 15 | D38: ='Proy. ventas'!E82+'Proy. ventas'!E83+'Proy. ventas'!E84 -> 13 | E38: =D38*$C38 -> 195 | F38: ='Proy. ventas'!G82+'Proy. ventas'!G83+'Proy. ventas'!G84 -> 13 | G38: =F38*$C38 -> 195 | H38: ='Proy. ventas'!I82+'Proy. ventas'!I83+'Proy. ventas'!I84 -> 13 | I38: =H38*$C38 -> 195 | J38: ='Proy. ventas'!K82+'Proy. ventas'!K83+'Proy. ventas'!K84 -> 13 | K38: =J38*$C38 -> 195 | L38: ='Proy. ventas'!M82+'Proy. ventas'!M83+'Proy. ventas'!M84 -> 13 | M38: =L38*$C38 -> 195 | N38: ='Proy. ventas'!O82+'Proy. ventas'!O83+'Proy. ventas'!O84 -> 14 | O38: =N38*$C38 -> 210 | P38: ='Proy. ventas'!Q82+'Proy. ventas'!Q83+'Proy. ventas'!Q84 -> 14 | Q38: =P38*$C38 -> 210 | R38: ='Proy. ventas'!S82+'Proy. ventas'!S83+'Proy. ventas'!S84 -> 15 | S38: =R38*$C38 -> 225 | T38: ='Proy. ventas'!U82+'Proy. ventas'!U83+'Proy. ventas'!U84 -> 14 | U38: =T38*$C38 -> 210 | V38: ='Proy. ventas'!W82+'Proy. ventas'!W83+'Proy. ventas'!W84 -> 15 | W38: =V38*$C38 -> 225 | X38: ='Proy. ventas'!Y82+'Proy. ventas'!Y83+'Proy. ventas'!Y84 -> 16 | Y38: =X38*$C38 -> 240 | Z38: ='Proy. ventas'!AA82+'Proy. ventas'!AA83+'Proy. ventas'!AA84 -> 17 | AA38: =Z38*$C38 -> 255 | AB38: =E38+G38+I38+K38+M38+O38+Q38+S38+U38+W38+Y38+AA38 -> 2550
B39: Movilidad y viáticos de instalación | C39: 5 | D39: ='Proy. ventas'!E83+'Proy. ventas'!E84 -> 9 | E39: =D39*$C39 -> 45 | F39: ='Proy. ventas'!G83+'Proy. ventas'!G84 -> 9 | G39: =F39*$C39 -> 45 | H39: ='Proy. ventas'!I83+'Proy. ventas'!I84 -> 9 | I39: =H39*$C39 -> 45 | J39: ='Proy. ventas'!K83+'Proy. ventas'!K84 -> 9 | K39: =J39*$C39 -> 45 | L39: ='Proy. ventas'!M83+'Proy. ventas'!M84 -> 9 | M39: =L39*$C39 -> 45 | N39: ='Proy. ventas'!O83+'Proy. ventas'!O84 -> 10 | O39: =N39*$C39 -> 50 | P39: ='Proy. ventas'!Q83+'Proy. ventas'!Q84 -> 10 | Q39: =P39*$C39 -> 50 | R39: ='Proy. ventas'!S83+'Proy. ventas'!S84 -> 11 | S39: =R39*$C39 -> 55 | T39: ='Proy. ventas'!U83+'Proy. ventas'!U84 -> 10 | U39: =T39*$C39 -> 50 | V39: ='Proy. ventas'!W83+'Proy. ventas'!W84 -> 11 | W39: =V39*$C39 -> 55 | X39: ='Proy. ventas'!Y83+'Proy. ventas'!Y84 -> 11 | Y39: =X39*$C39 -> 55 | Z39: ='Proy. ventas'!AA83+'Proy. ventas'!AA84 -> 11 | AA39: =Z39*$C39 -> 55 | AB39: =E39+G39+I39+K39+M39+O39+Q39+S39+U39+W39+Y39+AA39 -> 595
B40: Consumo cloud por comercio activo | C40: 0.35 | D40: ='Proy. ventas'!E85+'Proy. ventas'!E86+'Proy. ventas'!E87 -> 115 | E40: =D40*$C40 -> 40.25 | F40: ='Proy. ventas'!G85+'Proy. ventas'!G86+'Proy. ventas'!G87 -> 128 | G40: =F40*$C40 -> 44.8 | H40: ='Proy. ventas'!I85+'Proy. ventas'!I86+'Proy. ventas'!I87 -> 141 | I40: =H40*$C40 -> 49.35 | J40: ='Proy. ventas'!K85+'Proy. ventas'!K86+'Proy. ventas'!K87 -> 154 | K40: =J40*$C40 -> 53.9 | L40: ='Proy. ventas'!M85+'Proy. ventas'!M86+'Proy. ventas'!M87 -> 167 | M40: =L40*$C40 -> 58.45 | N40: ='Proy. ventas'!O85+'Proy. ventas'!O86+'Proy. ventas'!O87 -> 181 | O40: =N40*$C40 -> 63.35 | P40: ='Proy. ventas'!Q85+'Proy. ventas'!Q86+'Proy. ventas'!Q87 -> 195 | Q40: =P40*$C40 -> 68.25 | R40: ='Proy. ventas'!S85+'Proy. ventas'!S86+'Proy. ventas'!S87 -> 210 | S40: =R40*$C40 -> 73.5 | T40: ='Proy. ventas'!U85+'Proy. ventas'!U86+'Proy. ventas'!U87 -> 224 | U40: =T40*$C40 -> 78.4 | V40: ='Proy. ventas'!W85+'Proy. ventas'!W86+'Proy. ventas'!W87 -> 239 | W40: =V40*$C40 -> 83.65 | X40: ='Proy. ventas'!Y85+'Proy. ventas'!Y86+'Proy. ventas'!Y87 -> 255 | Y40: =X40*$C40 -> 89.25 | Z40: ='Proy. ventas'!AA85+'Proy. ventas'!AA86+'Proy. ventas'!AA87 -> 272 | AA40: =Z40*$C40 -> 95.2 | AB40: =E40+G40+I40+K40+M40+O40+Q40+S40+U40+W40+Y40+AA40 -> 798.35
B41: Gateway de notificaciones | C41: 0.15 | D41: ='Proy. ventas'!E85+'Proy. ventas'!E86+'Proy. ventas'!E87 -> 115 | E41: =D41*$C41 -> 17.25 | F41: ='Proy. ventas'!G85+'Proy. ventas'!G86+'Proy. ventas'!G87 -> 128 | G41: =F41*$C41 -> 19.2 | H41: ='Proy. ventas'!I85+'Proy. ventas'!I86+'Proy. ventas'!I87 -> 141 | I41: =H41*$C41 -> 21.15 | J41: ='Proy. ventas'!K85+'Proy. ventas'!K86+'Proy. ventas'!K87 -> 154 | K41: =J41*$C41 -> 23.1 | L41: ='Proy. ventas'!M85+'Proy. ventas'!M86+'Proy. ventas'!M87 -> 167 | M41: =L41*$C41 -> 25.05 | N41: ='Proy. ventas'!O85+'Proy. ventas'!O86+'Proy. ventas'!O87 -> 181 | O41: =N41*$C41 -> 27.15 | P41: ='Proy. ventas'!Q85+'Proy. ventas'!Q86+'Proy. ventas'!Q87 -> 195 | Q41: =P41*$C41 -> 29.25 | R41: ='Proy. ventas'!S85+'Proy. ventas'!S86+'Proy. ventas'!S87 -> 210 | S41: =R41*$C41 -> 31.5 | T41: ='Proy. ventas'!U85+'Proy. ventas'!U86+'Proy. ventas'!U87 -> 224 | U41: =T41*$C41 -> 33.6 | V41: ='Proy. ventas'!W85+'Proy. ventas'!W86+'Proy. ventas'!W87 -> 239 | W41: =V41*$C41 -> 35.85 | X41: ='Proy. ventas'!Y85+'Proy. ventas'!Y86+'Proy. ventas'!Y87 -> 255 | Y41: =X41*$C41 -> 38.25 | Z41: ='Proy. ventas'!AA85+'Proy. ventas'!AA86+'Proy. ventas'!AA87 -> 272 | AA41: =Z41*$C41 -> 40.8 | AB41: =E41+G41+I41+K41+M41+O41+Q41+S41+U41+W41+Y41+AA41 -> 342.15
B42: Comisiones de medios de pago | C42: 0.9 | D42: ='Proy. ventas'!E85+'Proy. ventas'!E86+'Proy. ventas'!E87 -> 115 | E42: =D42*$C42 -> 103.5 | F42: ='Proy. ventas'!G85+'Proy. ventas'!G86+'Proy. ventas'!G87 -> 128 | G42: =F42*$C42 -> 115.2 | H42: ='Proy. ventas'!I85+'Proy. ventas'!I86+'Proy. ventas'!I87 -> 141 | I42: =H42*$C42 -> 126.9 | J42: ='Proy. ventas'!K85+'Proy. ventas'!K86+'Proy. ventas'!K87 -> 154 | K42: =J42*$C42 -> 138.6 | L42: ='Proy. ventas'!M85+'Proy. ventas'!M86+'Proy. ventas'!M87 -> 167 | M42: =L42*$C42 -> 150.3 | N42: ='Proy. ventas'!O85+'Proy. ventas'!O86+'Proy. ventas'!O87 -> 181 | O42: =N42*$C42 -> 162.9 | P42: ='Proy. ventas'!Q85+'Proy. ventas'!Q86+'Proy. ventas'!Q87 -> 195 | Q42: =P42*$C42 -> 175.5 | R42: ='Proy. ventas'!S85+'Proy. ventas'!S86+'Proy. ventas'!S87 -> 210 | S42: =R42*$C42 -> 189 | T42: ='Proy. ventas'!U85+'Proy. ventas'!U86+'Proy. ventas'!U87 -> 224 | U42: =T42*$C42 -> 201.6 | V42: ='Proy. ventas'!W85+'Proy. ventas'!W86+'Proy. ventas'!W87 -> 239 | W42: =V42*$C42 -> 215.1 | X42: ='Proy. ventas'!Y85+'Proy. ventas'!Y86+'Proy. ventas'!Y87 -> 255 | Y42: =X42*$C42 -> 229.5 | Z42: ='Proy. ventas'!AA85+'Proy. ventas'!AA86+'Proy. ventas'!AA87 -> 272 | AA42: =Z42*$C42 -> 244.8 | AB42: =E42+G42+I42+K42+M42+O42+Q42+S42+U42+W42+Y42+AA42 -> 2052.9
B43: Reposición de equipamiento no recuperado | C43: 6 | D43: ='Proy. ventas'!E83+'Proy. ventas'!E84 -> 9 | E43: =D43*$C43 -> 54 | F43: ='Proy. ventas'!G83+'Proy. ventas'!G84 -> 9 | G43: =F43*$C43 -> 54 | H43: ='Proy. ventas'!I83+'Proy. ventas'!I84 -> 9 | I43: =H43*$C43 -> 54 | J43: ='Proy. ventas'!K83+'Proy. ventas'!K84 -> 9 | K43: =J43*$C43 -> 54 | L43: ='Proy. ventas'!M83+'Proy. ventas'!M84 -> 9 | M43: =L43*$C43 -> 54 | N43: ='Proy. ventas'!O83+'Proy. ventas'!O84 -> 10 | O43: =N43*$C43 -> 60 | P43: ='Proy. ventas'!Q83+'Proy. ventas'!Q84 -> 10 | Q43: =P43*$C43 -> 60 | R43: ='Proy. ventas'!S83+'Proy. ventas'!S84 -> 11 | S43: =R43*$C43 -> 66 | T43: ='Proy. ventas'!U83+'Proy. ventas'!U84 -> 10 | U43: =T43*$C43 -> 60 | V43: ='Proy. ventas'!W83+'Proy. ventas'!W84 -> 11 | W43: =V43*$C43 -> 66 | X43: ='Proy. ventas'!Y83+'Proy. ventas'!Y84 -> 11 | Y43: =X43*$C43 -> 66 | Z43: ='Proy. ventas'!AA83+'Proy. ventas'!AA84 -> 11 | AA43: =Z43*$C43 -> 66 | AB43: =E43+G43+I43+K43+M43+O43+Q43+S43+U43+W43+Y43+AA43 -> 714
A44: Promoción | B44: Bonificación del alta - Plan Básico | C44: =Hipótesis!$C$58*0.3 -> 7.5 | D44: ='Proy. ventas'!E82 -> 4 | E44: =D44*$C44 -> 30 | F44: ='Proy. ventas'!G82 -> 4 | G44: =F44*$C44 -> 30 | H44: ='Proy. ventas'!I82 -> 4 | I44: =H44*$C44 -> 30 | J44: ='Proy. ventas'!K82 -> 4 | K44: =J44*$C44 -> 30 | L44: ='Proy. ventas'!M82 -> 4 | M44: =L44*$C44 -> 30 | N44: ='Proy. ventas'!O82 -> 4 | O44: =N44*$C44 -> 30 | P44: ='Proy. ventas'!Q82 -> 4 | Q44: =P44*$C44 -> 30 | R44: ='Proy. ventas'!S82 -> 4 | S44: =R44*$C44 -> 30 | T44: ='Proy. ventas'!U82 -> 4 | U44: =T44*$C44 -> 30 | V44: ='Proy. ventas'!W82 -> 4 | W44: =V44*$C44 -> 30 | X44: ='Proy. ventas'!Y82 -> 5 | Y44: =X44*$C44 -> 37.5 | Z44: ='Proy. ventas'!AA82 -> 6 | AA44: =Z44*$C44 -> 45 | AB44: =E44+G44+I44+K44+M44+O44+Q44+S44+U44+W44+Y44+AA44 -> 382.5
B45: Bonificación del alta - Plan Vidriera | C45: =Hipótesis!$C$59*0.3 -> 18 | D45: ='Proy. ventas'!E83 -> 8 | E45: =D45*$C45 -> 144 | F45: ='Proy. ventas'!G83 -> 8 | G45: =F45*$C45 -> 144 | H45: ='Proy. ventas'!I83 -> 8 | I45: =H45*$C45 -> 144 | J45: ='Proy. ventas'!K83 -> 8 | K45: =J45*$C45 -> 144 | L45: ='Proy. ventas'!M83 -> 8 | M45: =L45*$C45 -> 144 | N45: ='Proy. ventas'!O83 -> 8 | O45: =N45*$C45 -> 144 | P45: ='Proy. ventas'!Q83 -> 9 | Q45: =P45*$C45 -> 162 | R45: ='Proy. ventas'!S83 -> 9 | S45: =R45*$C45 -> 162 | T45: ='Proy. ventas'!U83 -> 9 | U45: =T45*$C45 -> 162 | V45: ='Proy. ventas'!W83 -> 9 | W45: =V45*$C45 -> 162 | X45: ='Proy. ventas'!Y83 -> 9 | Y45: =X45*$C45 -> 162 | Z45: ='Proy. ventas'!AA83 -> 9 | AA45: =Z45*$C45 -> 162 | AB45: =E45+G45+I45+K45+M45+O45+Q45+S45+U45+W45+Y45+AA45 -> 1836
B46: Bonificación del alta - Plan Cadena | C46: =Hipótesis!$C$60*0.3 -> 75 | D46: ='Proy. ventas'!E84 -> 1 | E46: =D46*$C46 -> 75 | F46: ='Proy. ventas'!G84 -> 1 | G46: =F46*$C46 -> 75 | H46: ='Proy. ventas'!I84 -> 1 | I46: =H46*$C46 -> 75 | J46: ='Proy. ventas'!K84 -> 1 | K46: =J46*$C46 -> 75 | L46: ='Proy. ventas'!M84 -> 1 | M46: =L46*$C46 -> 75 | N46: ='Proy. ventas'!O84 -> 2 | O46: =N46*$C46 -> 150 | P46: ='Proy. ventas'!Q84 -> 1 | Q46: =P46*$C46 -> 75 | R46: ='Proy. ventas'!S84 -> 2 | S46: =R46*$C46 -> 150 | T46: ='Proy. ventas'!U84 -> 1 | U46: =T46*$C46 -> 75 | V46: ='Proy. ventas'!W84 -> 2 | W46: =V46*$C46 -> 150 | X46: ='Proy. ventas'!Y84 -> 2 | Y46: =X46*$C46 -> 150 | Z46: ='Proy. ventas'!AA84 -> 2 | AA46: =Z46*$C46 -> 150 | AB46: =E46+G46+I46+K46+M46+O46+Q46+S46+U46+W46+Y46+AA46 -> 1275
B47: Incentivo del programa de referidos | C47: 10 | D47: =ROUND(('Proy. ventas'!E82+'Proy. ventas'!E83+'Proy. ventas'!E84)*0.3,0) -> 4 | E47: =D47*$C47 -> 40 | F47: =ROUND(('Proy. ventas'!G82+'Proy. ventas'!G83+'Proy. ventas'!G84)*0.3,0) -> 4 | G47: =F47*$C47 -> 40 | H47: =ROUND(('Proy. ventas'!I82+'Proy. ventas'!I83+'Proy. ventas'!I84)*0.3,0) -> 4 | I47: =H47*$C47 -> 40 | J47: =ROUND(('Proy. ventas'!K82+'Proy. ventas'!K83+'Proy. ventas'!K84)*0.3,0) -> 4 | K47: =J47*$C47 -> 40 | L47: =ROUND(('Proy. ventas'!M82+'Proy. ventas'!M83+'Proy. ventas'!M84)*0.3,0) -> 4 | M47: =L47*$C47 -> 40 | N47: =ROUND(('Proy. ventas'!O82+'Proy. ventas'!O83+'Proy. ventas'!O84)*0.3,0) -> 4 | O47: =N47*$C47 -> 40 | P47: =ROUND(('Proy. ventas'!Q82+'Proy. ventas'!Q83+'Proy. ventas'!Q84)*0.3,0) -> 4 | Q47: =P47*$C47 -> 40 | R47: =ROUND(('Proy. ventas'!S82+'Proy. ventas'!S83+'Proy. ventas'!S84)*0.3,0) -> 5 | S47: =R47*$C47 -> 50 | T47: =ROUND(('Proy. ventas'!U82+'Proy. ventas'!U83+'Proy. ventas'!U84)*0.3,0) -> 4 | U47: =T47*$C47 -> 40 | V47: =ROUND(('Proy. ventas'!W82+'Proy. ventas'!W83+'Proy. ventas'!W84)*0.3,0) -> 5 | W47: =V47*$C47 -> 50 | X47: =ROUND(('Proy. ventas'!Y82+'Proy. ventas'!Y83+'Proy. ventas'!Y84)*0.3,0) -> 5 | Y47: =X47*$C47 -> 50 | Z47: =ROUND(('Proy. ventas'!AA82+'Proy. ventas'!AA83+'Proy. ventas'!AA84)*0.3,0) -> 5 | AA47: =Z47*$C47 -> 50 | AB47: =E47+G47+I47+K47+M47+O47+Q47+S47+U47+W47+Y47+AA47 -> 520
B55: TOTAL | E55: =SUM(E38:E47) -> 744 | G55: =SUM(G38:G47) -> 762.2 | I55: =SUM(I38:I47) -> 780.4 | K55: =SUM(K38:K47) -> 798.6 | M55: =SUM(M38:M47) -> 816.8 | O55: =SUM(O38:O47) -> 937.4 | Q55: =SUM(Q38:Q47) -> 900 | S55: =SUM(S38:S47) -> 1032 | U55: =SUM(U38:U47) -> 940.6 | W55: =SUM(W38:W47) -> 1072.6 | Y55: =SUM(Y38:Y47) -> 1117.5 | AA55: =SUM(AA38:AA47) -> 1163.8 | AB55: =SUM(AB38:AB47) -> 11065.9
B58: Costos variables - Año 2028
A59: Rubro | B59: Descripción | C59: Costo unitario | D59: Enero | F59: Febrero | H59: Marzo | J59: Abril | L59: Mayo | N59: Junio | P59: Julio | R59: Agosto | T59: Septiembre | V59: Octubre | X59: Noviembre | Z59: Diciembre | AB59: Total anual
D60: Cant. | E60: Costo | F60: Cant. | G60: Costo | H60: Cant. | I60: Costo | J60: Cant. | K60: Costo | L60: Cant. | M60: Costo | N60: Cant. | O60: Costo | P60: Cant. | Q60: Costo | R60: Cant. | S60: Costo | T60: Cant. | U60: Costo | V60: Cant. | W60: Costo | X60: Cant. | Y60: Costo | Z60: Cant. | AA60: Costo
A61: Operación | B61: Comisión del vendedor por alta concretada | C61: 15 | D61: ='Proy. ventas'!E144+'Proy. ventas'!E145+'Proy. ventas'!E146 -> 20 | E61: =D61*$C61 -> 300 | F61: ='Proy. ventas'!G144+'Proy. ventas'!G145+'Proy. ventas'!G146 -> 20 | G61: =F61*$C61 -> 300 | H61: ='Proy. ventas'!I144+'Proy. ventas'!I145+'Proy. ventas'!I146 -> 20 | I61: =H61*$C61 -> 300 | J61: ='Proy. ventas'!K144+'Proy. ventas'!K145+'Proy. ventas'!K146 -> 20 | K61: =J61*$C61 -> 300 | L61: ='Proy. ventas'!M144+'Proy. ventas'!M145+'Proy. ventas'!M146 -> 20 | M61: =L61*$C61 -> 300 | N61: ='Proy. ventas'!O144+'Proy. ventas'!O145+'Proy. ventas'!O146 -> 20 | O61: =N61*$C61 -> 300 | P61: ='Proy. ventas'!Q144+'Proy. ventas'!Q145+'Proy. ventas'!Q146 -> 20 | Q61: =P61*$C61 -> 300 | R61: ='Proy. ventas'!S144+'Proy. ventas'!S145+'Proy. ventas'!S146 -> 20 | S61: =R61*$C61 -> 300 | T61: ='Proy. ventas'!U144+'Proy. ventas'!U145+'Proy. ventas'!U146 -> 20 | U61: =T61*$C61 -> 300 | V61: ='Proy. ventas'!W144+'Proy. ventas'!W145+'Proy. ventas'!W146 -> 20 | W61: =V61*$C61 -> 300 | X61: ='Proy. ventas'!Y144+'Proy. ventas'!Y145+'Proy. ventas'!Y146 -> 20 | Y61: =X61*$C61 -> 300 | Z61: ='Proy. ventas'!AA144+'Proy. ventas'!AA145+'Proy. ventas'!AA146 -> 18 | AA61: =Z61*$C61 -> 270 | AB61: =E61+G61+I61+K61+M61+O61+Q61+S61+U61+W61+Y61+AA61 -> 3570
B62: Movilidad y viáticos de instalación | C62: 5 | D62: ='Proy. ventas'!E145+'Proy. ventas'!E146 -> 14 | E62: =D62*$C62 -> 70 | F62: ='Proy. ventas'!G145+'Proy. ventas'!G146 -> 14 | G62: =F62*$C62 -> 70 | H62: ='Proy. ventas'!I145+'Proy. ventas'!I146 -> 14 | I62: =H62*$C62 -> 70 | J62: ='Proy. ventas'!K145+'Proy. ventas'!K146 -> 14 | K62: =J62*$C62 -> 70 | L62: ='Proy. ventas'!M145+'Proy. ventas'!M146 -> 14 | M62: =L62*$C62 -> 70 | N62: ='Proy. ventas'!O145+'Proy. ventas'!O146 -> 14 | O62: =N62*$C62 -> 70 | P62: ='Proy. ventas'!Q145+'Proy. ventas'!Q146 -> 14 | Q62: =P62*$C62 -> 70 | R62: ='Proy. ventas'!S145+'Proy. ventas'!S146 -> 14 | S62: =R62*$C62 -> 70 | T62: ='Proy. ventas'!U145+'Proy. ventas'!U146 -> 14 | U62: =T62*$C62 -> 70 | V62: ='Proy. ventas'!W145+'Proy. ventas'!W146 -> 14 | W62: =V62*$C62 -> 70 | X62: ='Proy. ventas'!Y145+'Proy. ventas'!Y146 -> 14 | Y62: =X62*$C62 -> 70 | Z62: ='Proy. ventas'!AA145+'Proy. ventas'!AA146 -> 13 | AA62: =Z62*$C62 -> 65 | AB62: =E62+G62+I62+K62+M62+O62+Q62+S62+U62+W62+Y62+AA62 -> 835
B63: Consumo cloud por comercio activo | C63: 0.35 | D63: ='Proy. ventas'!E147+'Proy. ventas'!E148+'Proy. ventas'!E149 -> 292 | E63: =D63*$C63 -> 102.2 | F63: ='Proy. ventas'!G147+'Proy. ventas'!G148+'Proy. ventas'!G149 -> 312 | G63: =F63*$C63 -> 109.2 | H63: ='Proy. ventas'!I147+'Proy. ventas'!I148+'Proy. ventas'!I149 -> 332 | I63: =H63*$C63 -> 116.2 | J63: ='Proy. ventas'!K147+'Proy. ventas'!K148+'Proy. ventas'!K149 -> 352 | K63: =J63*$C63 -> 123.2 | L63: ='Proy. ventas'!M147+'Proy. ventas'!M148+'Proy. ventas'!M149 -> 372 | M63: =L63*$C63 -> 130.2 | N63: ='Proy. ventas'!O147+'Proy. ventas'!O148+'Proy. ventas'!O149 -> 392 | O63: =N63*$C63 -> 137.2 | P63: ='Proy. ventas'!Q147+'Proy. ventas'!Q148+'Proy. ventas'!Q149 -> 412 | Q63: =P63*$C63 -> 144.2 | R63: ='Proy. ventas'!S147+'Proy. ventas'!S148+'Proy. ventas'!S149 -> 432 | S63: =R63*$C63 -> 151.2 | T63: ='Proy. ventas'!U147+'Proy. ventas'!U148+'Proy. ventas'!U149 -> 452 | U63: =T63*$C63 -> 158.2 | V63: ='Proy. ventas'!W147+'Proy. ventas'!W148+'Proy. ventas'!W149 -> 472 | W63: =V63*$C63 -> 165.2 | X63: ='Proy. ventas'!Y147+'Proy. ventas'!Y148+'Proy. ventas'!Y149 -> 492 | Y63: =X63*$C63 -> 172.2 | Z63: ='Proy. ventas'!AA147+'Proy. ventas'!AA148+'Proy. ventas'!AA149 -> 510 | AA63: =Z63*$C63 -> 178.5 | AB63: =E63+G63+I63+K63+M63+O63+Q63+S63+U63+W63+Y63+AA63 -> 1687.7
B64: Gateway de notificaciones | C64: 0.15 | D64: ='Proy. ventas'!E147+'Proy. ventas'!E148+'Proy. ventas'!E149 -> 292 | E64: =D64*$C64 -> 43.8 | F64: ='Proy. ventas'!G147+'Proy. ventas'!G148+'Proy. ventas'!G149 -> 312 | G64: =F64*$C64 -> 46.8 | H64: ='Proy. ventas'!I147+'Proy. ventas'!I148+'Proy. ventas'!I149 -> 332 | I64: =H64*$C64 -> 49.8 | J64: ='Proy. ventas'!K147+'Proy. ventas'!K148+'Proy. ventas'!K149 -> 352 | K64: =J64*$C64 -> 52.8 | L64: ='Proy. ventas'!M147+'Proy. ventas'!M148+'Proy. ventas'!M149 -> 372 | M64: =L64*$C64 -> 55.8 | N64: ='Proy. ventas'!O147+'Proy. ventas'!O148+'Proy. ventas'!O149 -> 392 | O64: =N64*$C64 -> 58.8 | P64: ='Proy. ventas'!Q147+'Proy. ventas'!Q148+'Proy. ventas'!Q149 -> 412 | Q64: =P64*$C64 -> 61.8 | R64: ='Proy. ventas'!S147+'Proy. ventas'!S148+'Proy. ventas'!S149 -> 432 | S64: =R64*$C64 -> 64.8 | T64: ='Proy. ventas'!U147+'Proy. ventas'!U148+'Proy. ventas'!U149 -> 452 | U64: =T64*$C64 -> 67.8 | V64: ='Proy. ventas'!W147+'Proy. ventas'!W148+'Proy. ventas'!W149 -> 472 | W64: =V64*$C64 -> 70.8 | X64: ='Proy. ventas'!Y147+'Proy. ventas'!Y148+'Proy. ventas'!Y149 -> 492 | Y64: =X64*$C64 -> 73.8 | Z64: ='Proy. ventas'!AA147+'Proy. ventas'!AA148+'Proy. ventas'!AA149 -> 510 | AA64: =Z64*$C64 -> 76.5 | AB64: =E64+G64+I64+K64+M64+O64+Q64+S64+U64+W64+Y64+AA64 -> 723.3
B65: Comisiones de medios de pago | C65: 0.9 | D65: ='Proy. ventas'!E147+'Proy. ventas'!E148+'Proy. ventas'!E149 -> 292 | E65: =D65*$C65 -> 262.8 | F65: ='Proy. ventas'!G147+'Proy. ventas'!G148+'Proy. ventas'!G149 -> 312 | G65: =F65*$C65 -> 280.8 | H65: ='Proy. ventas'!I147+'Proy. ventas'!I148+'Proy. ventas'!I149 -> 332 | I65: =H65*$C65 -> 298.8 | J65: ='Proy. ventas'!K147+'Proy. ventas'!K148+'Proy. ventas'!K149 -> 352 | K65: =J65*$C65 -> 316.8 | L65: ='Proy. ventas'!M147+'Proy. ventas'!M148+'Proy. ventas'!M149 -> 372 | M65: =L65*$C65 -> 334.8 | N65: ='Proy. ventas'!O147+'Proy. ventas'!O148+'Proy. ventas'!O149 -> 392 | O65: =N65*$C65 -> 352.8 | P65: ='Proy. ventas'!Q147+'Proy. ventas'!Q148+'Proy. ventas'!Q149 -> 412 | Q65: =P65*$C65 -> 370.8 | R65: ='Proy. ventas'!S147+'Proy. ventas'!S148+'Proy. ventas'!S149 -> 432 | S65: =R65*$C65 -> 388.8 | T65: ='Proy. ventas'!U147+'Proy. ventas'!U148+'Proy. ventas'!U149 -> 452 | U65: =T65*$C65 -> 406.8 | V65: ='Proy. ventas'!W147+'Proy. ventas'!W148+'Proy. ventas'!W149 -> 472 | W65: =V65*$C65 -> 424.8 | X65: ='Proy. ventas'!Y147+'Proy. ventas'!Y148+'Proy. ventas'!Y149 -> 492 | Y65: =X65*$C65 -> 442.8 | Z65: ='Proy. ventas'!AA147+'Proy. ventas'!AA148+'Proy. ventas'!AA149 -> 510 | AA65: =Z65*$C65 -> 459 | AB65: =E65+G65+I65+K65+M65+O65+Q65+S65+U65+W65+Y65+AA65 -> 4339.8
B66: Reposición de equipamiento no recuperado | C66: 6 | D66: ='Proy. ventas'!E145+'Proy. ventas'!E146 -> 14 | E66: =D66*$C66 -> 84 | F66: ='Proy. ventas'!G145+'Proy. ventas'!G146 -> 14 | G66: =F66*$C66 -> 84 | H66: ='Proy. ventas'!I145+'Proy. ventas'!I146 -> 14 | I66: =H66*$C66 -> 84 | J66: ='Proy. ventas'!K145+'Proy. ventas'!K146 -> 14 | K66: =J66*$C66 -> 84 | L66: ='Proy. ventas'!M145+'Proy. ventas'!M146 -> 14 | M66: =L66*$C66 -> 84 | N66: ='Proy. ventas'!O145+'Proy. ventas'!O146 -> 14 | O66: =N66*$C66 -> 84 | P66: ='Proy. ventas'!Q145+'Proy. ventas'!Q146 -> 14 | Q66: =P66*$C66 -> 84 | R66: ='Proy. ventas'!S145+'Proy. ventas'!S146 -> 14 | S66: =R66*$C66 -> 84 | T66: ='Proy. ventas'!U145+'Proy. ventas'!U146 -> 14 | U66: =T66*$C66 -> 84 | V66: ='Proy. ventas'!W145+'Proy. ventas'!W146 -> 14 | W66: =V66*$C66 -> 84 | X66: ='Proy. ventas'!Y145+'Proy. ventas'!Y146 -> 14 | Y66: =X66*$C66 -> 84 | Z66: ='Proy. ventas'!AA145+'Proy. ventas'!AA146 -> 13 | AA66: =Z66*$C66 -> 78 | AB66: =E66+G66+I66+K66+M66+O66+Q66+S66+U66+W66+Y66+AA66 -> 1002
A67: Promoción | B67: Bonificación del alta - Plan Básico | C67: =Hipótesis!$C$58*0.3 -> 7.5 | D67: ='Proy. ventas'!E144 -> 6 | E67: =D67*$C67 -> 45 | F67: ='Proy. ventas'!G144 -> 6 | G67: =F67*$C67 -> 45 | H67: ='Proy. ventas'!I144 -> 6 | I67: =H67*$C67 -> 45 | J67: ='Proy. ventas'!K144 -> 6 | K67: =J67*$C67 -> 45 | L67: ='Proy. ventas'!M144 -> 6 | M67: =L67*$C67 -> 45 | N67: ='Proy. ventas'!O144 -> 6 | O67: =N67*$C67 -> 45 | P67: ='Proy. ventas'!Q144 -> 6 | Q67: =P67*$C67 -> 45 | R67: ='Proy. ventas'!S144 -> 6 | S67: =R67*$C67 -> 45 | T67: ='Proy. ventas'!U144 -> 6 | U67: =T67*$C67 -> 45 | V67: ='Proy. ventas'!W144 -> 6 | W67: =V67*$C67 -> 45 | X67: ='Proy. ventas'!Y144 -> 6 | Y67: =X67*$C67 -> 45 | Z67: ='Proy. ventas'!AA144 -> 5 | AA67: =Z67*$C67 -> 37.5 | AB67: =E67+G67+I67+K67+M67+O67+Q67+S67+U67+W67+Y67+AA67 -> 532.5
B68: Bonificación del alta - Plan Vidriera | C68: =Hipótesis!$C$59*0.3 -> 18 | D68: ='Proy. ventas'!E145 -> 12 | E68: =D68*$C68 -> 216 | F68: ='Proy. ventas'!G145 -> 12 | G68: =F68*$C68 -> 216 | H68: ='Proy. ventas'!I145 -> 12 | I68: =H68*$C68 -> 216 | J68: ='Proy. ventas'!K145 -> 12 | K68: =J68*$C68 -> 216 | L68: ='Proy. ventas'!M145 -> 12 | M68: =L68*$C68 -> 216 | N68: ='Proy. ventas'!O145 -> 12 | O68: =N68*$C68 -> 216 | P68: ='Proy. ventas'!Q145 -> 12 | Q68: =P68*$C68 -> 216 | R68: ='Proy. ventas'!S145 -> 12 | S68: =R68*$C68 -> 216 | T68: ='Proy. ventas'!U145 -> 12 | U68: =T68*$C68 -> 216 | V68: ='Proy. ventas'!W145 -> 12 | W68: =V68*$C68 -> 216 | X68: ='Proy. ventas'!Y145 -> 12 | Y68: =X68*$C68 -> 216 | Z68: ='Proy. ventas'!AA145 -> 11 | AA68: =Z68*$C68 -> 198 | AB68: =E68+G68+I68+K68+M68+O68+Q68+S68+U68+W68+Y68+AA68 -> 2574
B69: Bonificación del alta - Plan Cadena | C69: =Hipótesis!$C$60*0.3 -> 75 | D69: ='Proy. ventas'!E146 -> 2 | E69: =D69*$C69 -> 150 | F69: ='Proy. ventas'!G146 -> 2 | G69: =F69*$C69 -> 150 | H69: ='Proy. ventas'!I146 -> 2 | I69: =H69*$C69 -> 150 | J69: ='Proy. ventas'!K146 -> 2 | K69: =J69*$C69 -> 150 | L69: ='Proy. ventas'!M146 -> 2 | M69: =L69*$C69 -> 150 | N69: ='Proy. ventas'!O146 -> 2 | O69: =N69*$C69 -> 150 | P69: ='Proy. ventas'!Q146 -> 2 | Q69: =P69*$C69 -> 150 | R69: ='Proy. ventas'!S146 -> 2 | S69: =R69*$C69 -> 150 | T69: ='Proy. ventas'!U146 -> 2 | U69: =T69*$C69 -> 150 | V69: ='Proy. ventas'!W146 -> 2 | W69: =V69*$C69 -> 150 | X69: ='Proy. ventas'!Y146 -> 2 | Y69: =X69*$C69 -> 150 | Z69: ='Proy. ventas'!AA146 -> 2 | AA69: =Z69*$C69 -> 150 | AB69: =E69+G69+I69+K69+M69+O69+Q69+S69+U69+W69+Y69+AA69 -> 1800
B70: Incentivo del programa de referidos | C70: 10 | D70: =ROUND(('Proy. ventas'!E144+'Proy. ventas'!E145+'Proy. ventas'!E146)*0.3,0) -> 6 | E70: =D70*$C70 -> 60 | F70: =ROUND(('Proy. ventas'!G144+'Proy. ventas'!G145+'Proy. ventas'!G146)*0.3,0) -> 6 | G70: =F70*$C70 -> 60 | H70: =ROUND(('Proy. ventas'!I144+'Proy. ventas'!I145+'Proy. ventas'!I146)*0.3,0) -> 6 | I70: =H70*$C70 -> 60 | J70: =ROUND(('Proy. ventas'!K144+'Proy. ventas'!K145+'Proy. ventas'!K146)*0.3,0) -> 6 | K70: =J70*$C70 -> 60 | L70: =ROUND(('Proy. ventas'!M144+'Proy. ventas'!M145+'Proy. ventas'!M146)*0.3,0) -> 6 | M70: =L70*$C70 -> 60 | N70: =ROUND(('Proy. ventas'!O144+'Proy. ventas'!O145+'Proy. ventas'!O146)*0.3,0) -> 6 | O70: =N70*$C70 -> 60 | P70: =ROUND(('Proy. ventas'!Q144+'Proy. ventas'!Q145+'Proy. ventas'!Q146)*0.3,0) -> 6 | Q70: =P70*$C70 -> 60 | R70: =ROUND(('Proy. ventas'!S144+'Proy. ventas'!S145+'Proy. ventas'!S146)*0.3,0) -> 6 | S70: =R70*$C70 -> 60 | T70: =ROUND(('Proy. ventas'!U144+'Proy. ventas'!U145+'Proy. ventas'!U146)*0.3,0) -> 6 | U70: =T70*$C70 -> 60 | V70: =ROUND(('Proy. ventas'!W144+'Proy. ventas'!W145+'Proy. ventas'!W146)*0.3,0) -> 6 | W70: =V70*$C70 -> 60 | X70: =ROUND(('Proy. ventas'!Y144+'Proy. ventas'!Y145+'Proy. ventas'!Y146)*0.3,0) -> 6 | Y70: =X70*$C70 -> 60 | Z70: =ROUND(('Proy. ventas'!AA144+'Proy. ventas'!AA145+'Proy. ventas'!AA146)*0.3,0) -> 5 | AA70: =Z70*$C70 -> 50 | AB70: =E70+G70+I70+K70+M70+O70+Q70+S70+U70+W70+Y70+AA70 -> 710
B78: TOTAL | E78: =SUM(E61:E70) -> 1333.8 | G78: =SUM(G61:G70) -> 1361.8 | I78: =SUM(I61:I70) -> 1389.8 | K78: =SUM(K61:K70) -> 1417.8 | M78: =SUM(M61:M70) -> 1445.8 | O78: =SUM(O61:O70) -> 1473.8 | Q78: =SUM(Q61:Q70) -> 1501.8 | S78: =SUM(S61:S70) -> 1529.8 | U78: =SUM(U61:U70) -> 1557.8 | W78: =SUM(W61:W70) -> 1585.8 | Y78: =SUM(Y61:Y70) -> 1613.8 | AA78: =SUM(AA61:AA70) -> 1562.5 | AB78: =SUM(AB61:AB70) -> 17774.3

Sheet Costos RRHH
E1: Estructura de costos de RRHH
B4: Evolución de la participación | H4: Costos de RRHH - Totales
B5: 2026 | C5: 2027 | D5: 2028 | H5: 2026 | I5: 2027 | J5: 2028
B6: =Hipótesis!C24 -> 0.03 | C6: =Hipótesis!C25 -> 0.08 | D6: =Hipótesis!C26 -> 0.15 | H6: =O39 -> 122984.64 | I6: =O57 -> 150323.36 | J6: =O75 -> 183152.53
B7: =Hipótesis!D24 -> 48960 | C7: =Hipótesis!D25 -> 130560 | D7: =Hipótesis!D26 -> 244800
B13: Costo mensual por puesto (USD)
B14: Área | C14: Puesto | D14: Sueldo bruto | E14: Jubilación | F14: Ley 19.032 | G14: Obra social | H14: F. Nac. Empleo | I14: Seg. de Vida | J14: ART | K14: Total aportes | L14: Costo mensual para la empresa
B15: Alícuotas patronales | E15: 0.1047 | F15: 0.0154 | G15: 0.06 | H15: 0.0092 | I15: 1.2 | J15: 0.03
B16: Gerencia | C16: Gerente General (Fundador / CEO) | D16: 2000 | E16: =$D16*$E$15 -> 209.4 | F16: =$D16*$F$15 -> 30.8 | G16: =$D16*$G$15 -> 120 | H16: =$D16*$H$15 -> 18.4 | I16: =$I$15 -> 1.2 | J16: =$D16*$J$15 -> 60 | K16: =SUM(E16:J16) -> 439.8 | L16: =D16+K16 -> 2439.8
C17: Gerente de Sistemas (Fundador / CTO) | D17: 2000 | E17: =$D17*$E$15 -> 209.4 | F17: =$D17*$F$15 -> 30.8 | G17: =$D17*$G$15 -> 120 | H17: =$D17*$H$15 -> 18.4 | I17: =$I$15 -> 1.2 | J17: =$D17*$J$15 -> 60 | K17: =SUM(E17:J17) -> 439.8 | L17: =D17+K17 -> 2439.8
B18: Sistemas | C18: Desarrollador | D18: 1800 | E18: =$D18*$E$15 -> 188.46 | F18: =$D18*$F$15 -> 27.72 | G18: =$D18*$G$15 -> 108 | H18: =$D18*$H$15 -> 16.56 | I18: =$I$15 -> 1.2 | J18: =$D18*$J$15 -> 54 | K18: =SUM(E18:J18) -> 395.94 | L18: =D18+K18 -> 2195.94
C19: Técnico de instalación y soporte | D19: 1100 | E19: =$D19*$E$15 -> 115.17 | F19: =$D19*$F$15 -> 16.94 | G19: =$D19*$G$15 -> 66 | H19: =$D19*$H$15 -> 10.12 | I19: =$I$15 -> 1.2 | J19: =$D19*$J$15 -> 33 | K19: =SUM(E19:J19) -> 242.43 | L19: =D19+K19 -> 1342.43
B20: Comercial | C20: Vendedor | D20: 1000 | E20: =$D20*$E$15 -> 104.7 | F20: =$D20*$F$15 -> 15.4 | G20: =$D20*$G$15 -> 60 | H20: =$D20*$H$15 -> 9.2 | I20: =$I$15 -> 1.2 | J20: =$D20*$J$15 -> 30 | K20: =SUM(E20:J20) -> 220.5 | L20: =D20+K20 -> 1220.5
B24: Dotación por mes - Año 2026
B25: Puesto | C25: Enero | D25: Febrero | E25: Marzo | F25: Abril | G25: Mayo | H25: Junio | I25: Julio | J25: Agosto | K25: Septiembre | L25: Octubre | M25: Noviembre | N25: Diciembre | O25: Dotación al cierre
B26: Gerente General (Fundador / CEO) | C26: 1 | D26: 1 | E26: 1 | F26: 1 | G26: 1 | H26: 1 | I26: 1 | J26: 1 | K26: 1 | L26: 1 | M26: 1 | N26: 1 | O26: =N26 -> 1
B27: Gerente de Sistemas (Fundador / CTO) | C27: 1 | D27: 1 | E27: 1 | F27: 1 | G27: 1 | H27: 1 | I27: 1 | J27: 1 | K27: 1 | L27: 1 | M27: 1 | N27: 1 | O27: =N27 -> 1
B28: Desarrollador | C28: 1 | D28: 1 | E28: 1 | F28: 1 | G28: 1 | H28: 1 | I28: 1 | J28: 1 | K28: 1 | L28: 1 | M28: 1 | N28: 1 | O28: =N28 -> 1
B29: Técnico de instalación y soporte | C29: 1 | D29: 1 | E29: 1 | F29: 1 | G29: 1 | H29: 1 | I29: 1 | J29: 1 | K29: 1 | L29: 1 | M29: 1 | N29: 1 | O29: =N29 -> 1
B30: Vendedor | C30: 1 | D30: 1 | E30: 1 | F30: 1 | G30: 1 | H30: 1 | I30: 2 | J30: 2 | K30: 2 | L30: 2 | M30: 2 | N30: 2 | O30: =N30 -> 2
B31: Total dotación | C31: =SUM(C26:C30) -> 5 | D31: =SUM(D26:D30) -> 5 | E31: =SUM(E26:E30) -> 5 | F31: =SUM(F26:F30) -> 5 | G31: =SUM(G26:G30) -> 5 | H31: =SUM(H26:H30) -> 5 | I31: =SUM(I26:I30) -> 6 | J31: =SUM(J26:J30) -> 6 | ... N31: =SUM(N26:N30) -> 6 | O31: =N31 -> 6
B32: Costo de RRHH por mes (USD) - Año 2026
B33: Puesto | C33: Enero | D33: Febrero | E33: Marzo | F33: Abril | G33: Mayo | H33: Junio | I33: Julio | J33: Agosto | K33: Septiembre | L33: Octubre | M33: Noviembre | N33: Diciembre | O33: Total anual
B34: Gerente General (Fundador / CEO) | C34: =C26*$L$16 -> 2439.8 | D34: =D26*$L$16 -> 2439.8 | E34: =E26*$L$16 -> 2439.8 | F34: =F26*$L$16 -> 2439.8 | G34: =G26*$L$16 -> 2439.8 | H34: =H26*$L$16 -> 2439.8 | I34: =I26*$L$16 -> 2439.8 | J34: =J26*$L$16 -> 2439.8 | ... N34: =N26*$L$16 -> 2439.8 | O34: =SUM(C34:N34) -> 29277.6
B35: Gerente de Sistemas (Fundador / CTO) | C35: =C27*$L$17 -> 2439.8 | D35: =D27*$L$17 -> 2439.8 | E35: =E27*$L$17 -> 2439.8 | F35: =F27*$L$17 -> 2439.8 | G35: =G27*$L$17 -> 2439.8 | H35: =H27*$L$17 -> 2439.8 | I35: =I27*$L$17 -> 2439.8 | J35: =J27*$L$17 -> 2439.8 | ... N35: =N27*$L$17 -> 2439.8 | O35: =SUM(C35:N35) -> 29277.6
B36: Desarrollador | C36: =C28*$L$18 -> 2195.94 | D36: =D28*$L$18 -> 2195.94 | E36: =E28*$L$18 -> 2195.94 | F36: =F28*$L$18 -> 2195.94 | G36: =G28*$L$18 -> 2195.94 | H36: =H28*$L$18 -> 2195.94 | I36: =I28*$L$18 -> 2195.94 | J36: =J28*$L$18 -> 2195.94 | ... N36: =N28*$L$18 -> 2195.94 | O36: =SUM(C36:N36) -> 26351.28
B37: Técnico de instalación y soporte | C37: =C29*$L$19 -> 1342.43 | D37: =D29*$L$19 -> 1342.43 | E37: =E29*$L$19 -> 1342.43 | F37: =F29*$L$19 -> 1342.43 | G37: =G29*$L$19 -> 1342.43 | H37: =H29*$L$19 -> 1342.43 | I37: =I29*$L$19 -> 1342.43 | J37: =J29*$L$19 -> 1342.43 | ... N37: =N29*$L$19 -> 1342.43 | O37: =SUM(C37:N37) -> 16109.16
B38: Vendedor | C38: =C30*$L$20 -> 1220.5 | D38: =D30*$L$20 -> 1220.5 | E38: =E30*$L$20 -> 1220.5 | F38: =F30*$L$20 -> 1220.5 | G38: =G30*$L$20 -> 1220.5 | H38: =H30*$L$20 -> 1220.5 | I38: =I30*$L$20 -> 2441 | J38: =J30*$L$20 -> 2441 | ... N38: =N30*$L$20 -> 2441 | O38: =SUM(C38:N38) -> 21969
B39: TOTAL | C39: =SUM(C34:C38) -> 9638.47 | D39: =SUM(D34:D38) -> 9638.47 | E39: =SUM(E34:E38) -> 9638.47 | F39: =SUM(F34:F38) -> 9638.47 | G39: =SUM(G34:G38) -> 9638.47 | H39: =SUM(H34:H38) -> 9638.47 | I39: =SUM(I34:I38) -> 10858.97 | J39: =SUM(J34:J38) -> 10858.97 | ... N39: =SUM(N34:N38) -> 10858.97 | O39: =SUM(C39:N39) -> 122984.64
B42: Dotación por mes - Año 2027
B43: Puesto | C43: Enero | D43: Febrero | E43: Marzo | F43: Abril | G43: Mayo | H43: Junio | I43: Julio | J43: Agosto | K43: Septiembre | L43: Octubre | M43: Noviembre | N43: Diciembre | O43: Dotación al cierre
B44: Gerente General (Fundador / CEO) | C44: 1 | D44: 1 | E44: 1 | F44: 1 | G44: 1 | H44: 1 | I44: 1 | J44: 1 | K44: 1 | L44: 1 | M44: 1 | N44: 1 | O44: =N44 -> 1
B45: Gerente de Sistemas (Fundador / CTO) | C45: 1 | D45: 1 | E45: 1 | F45: 1 | G45: 1 | H45: 1 | I45: 1 | J45: 1 | K45: 1 | L45: 1 | M45: 1 | N45: 1 | O45: =N45 -> 1
B46: Desarrollador | C46: 1 | D46: 1 | E46: 1 | F46: 1 | G46: 1 | H46: 1 | I46: 1 | J46: 1 | K46: 1 | L46: 1 | M46: 1 | N46: 1 | O46: =N46 -> 1
B47: Técnico de instalación y soporte | C47: 1 | D47: 1 | E47: 1 | F47: 1 | G47: 1 | H47: 1 | I47: 1 | J47: 1 | K47: 2 | L47: 2 | M47: 2 | N47: 2 | O47: =N47 -> 2
B48: Vendedor | C48: 3 | D48: 3 | E48: 3 | F48: 3 | G48: 3 | H48: 3 | I48: 3 | J48: 3 | K48: 3 | L48: 3 | M48: 3 | N48: 3 | O48: =N48 -> 3
B49: Total dotación | C49: =SUM(C44:C48) -> 7 | D49: =SUM(D44:D48) -> 7 | E49: =SUM(E44:E48) -> 7 | F49: =SUM(F44:F48) -> 7 | G49: =SUM(G44:G48) -> 7 | H49: =SUM(H44:H48) -> 7 | I49: =SUM(I44:I48) -> 7 | J49: =SUM(J44:J48) -> 7 | ... N49: =SUM(N44:N48) -> 8 | O49: =N49 -> 8
B50: Costo de RRHH por mes (USD) - Año 2027
B51: Puesto | C51: Enero | D51: Febrero | E51: Marzo | F51: Abril | G51: Mayo | H51: Junio | I51: Julio | J51: Agosto | K51: Septiembre | L51: Octubre | M51: Noviembre | N51: Diciembre | O51: Total anual
B52: Gerente General (Fundador / CEO) | C52: =C44*$L$16 -> 2439.8 | D52: =D44*$L$16 -> 2439.8 | E52: =E44*$L$16 -> 2439.8 | F52: =F44*$L$16 -> 2439.8 | G52: =G44*$L$16 -> 2439.8 | H52: =H44*$L$16 -> 2439.8 | I52: =I44*$L$16 -> 2439.8 | J52: =J44*$L$16 -> 2439.8 | ... N52: =N44*$L$16 -> 2439.8 | O52: =SUM(C52:N52) -> 29277.6
B53: Gerente de Sistemas (Fundador / CTO) | C53: =C45*$L$17 -> 2439.8 | D53: =D45*$L$17 -> 2439.8 | E53: =E45*$L$17 -> 2439.8 | F53: =F45*$L$17 -> 2439.8 | G53: =G45*$L$17 -> 2439.8 | H53: =H45*$L$17 -> 2439.8 | I53: =I45*$L$17 -> 2439.8 | J53: =J45*$L$17 -> 2439.8 | ... N53: =N45*$L$17 -> 2439.8 | O53: =SUM(C53:N53) -> 29277.6
B54: Desarrollador | C54: =C46*$L$18 -> 2195.94 | D54: =D46*$L$18 -> 2195.94 | E54: =E46*$L$18 -> 2195.94 | F54: =F46*$L$18 -> 2195.94 | G54: =G46*$L$18 -> 2195.94 | H54: =H46*$L$18 -> 2195.94 | I54: =I46*$L$18 -> 2195.94 | J54: =J46*$L$18 -> 2195.94 | ... N54: =N46*$L$18 -> 2195.94 | O54: =SUM(C54:N54) -> 26351.28
B55: Técnico de instalación y soporte | C55: =C47*$L$19 -> 1342.43 | D55: =D47*$L$19 -> 1342.43 | E55: =E47*$L$19 -> 1342.43 | F55: =F47*$L$19 -> 1342.43 | G55: =G47*$L$19 -> 1342.43 | H55: =H47*$L$19 -> 1342.43 | I55: =I47*$L$19 -> 1342.43 | J55: =J47*$L$19 -> 1342.43 | ... N55: =N47*$L$19 -> 2684.86 | O55: =SUM(C55:N55) -> 21478.88
B56: Vendedor | C56: =C48*$L$20 -> 3661.5 | D56: =D48*$L$20 -> 3661.5 | E56: =E48*$L$20 -> 3661.5 | F56: =F48*$L$20 -> 3661.5 | G56: =G48*$L$20 -> 3661.5 | H56: =H48*$L$20 -> 3661.5 | I56: =I48*$L$20 -> 3661.5 | J56: =J48*$L$20 -> 3661.5 | ... N56: =N48*$L$20 -> 3661.5 | O56: =SUM(C56:N56) -> 43938
B57: TOTAL | C57: =SUM(C52:C56) -> 12079.47 | D57: =SUM(D52:D56) -> 12079.47 | E57: =SUM(E52:E56) -> 12079.47 | F57: =SUM(F52:F56) -> 12079.47 | G57: =SUM(G52:G56) -> 12079.47 | H57: =SUM(H52:H56) -> 12079.47 | I57: =SUM(I52:I56) -> 12079.47 | J57: =SUM(J52:J56) -> 12079.47 | ... N57: =SUM(N52:N56) -> 13421.9 | O57: =SUM(C57:N57) -> 150323.36
B60: Dotación por mes - Año 2028
B61: Puesto | C61: Enero | D61: Febrero | E61: Marzo | F61: Abril | G61: Mayo | H61: Junio | I61: Julio | J61: Agosto | K61: Septiembre | L61: Octubre | M61: Noviembre | N61: Diciembre | O61: Dotación al cierre
B62: Gerente General (Fundador / CEO) | C62: 1 | D62: 1 | E62: 1 | F62: 1 | G62: 1 | H62: 1 | I62: 1 | J62: 1 | K62: 1 | L62: 1 | M62: 1 | N62: 1 | O62: =N62 -> 1
B63: Gerente de Sistemas (Fundador / CTO) | C63: 1 | D63: 1 | E63: 1 | F63: 1 | G63: 1 | H63: 1 | I63: 1 | J63: 1 | K63: 1 | L63: 1 | M63: 1 | N63: 1 | O63: =N63 -> 1
B64: Desarrollador | C64: 1 | D64: 1 | E64: 1 | F64: 1 | G64: 1 | H64: 1 | I64: 1 | J64: 1 | K64: 1 | L64: 1 | M64: 1 | N64: 1 | O64: =N64 -> 1
B65: Técnico de instalación y soporte | C65: 2 | D65: 3 | E65: 3 | F65: 3 | G65: 3 | H65: 3 | I65: 3 | J65: 3 | K65: 3 | L65: 3 | M65: 3 | N65: 3 | O65: =N65 -> 3
B66: Vendedor | C66: 3 | D66: 3 | E66: 3 | F66: 3 | G66: 3 | H66: 3 | I66: 4 | J66: 4 | K66: 4 | L66: 4 | M66: 4 | N66: 4 | O66: =N66 -> 4
B67: Total dotación | C67: =SUM(C62:C66) -> 8 | D67: =SUM(D62:D66) -> 9 | E67: =SUM(E62:E66) -> 9 | F67: =SUM(F62:F66) -> 9 | G67: =SUM(G62:G66) -> 9 | H67: =SUM(H62:H66) -> 9 | I67: =SUM(I62:I66) -> 10 | J67: =SUM(J62:J66) -> 10 | ... N67: =SUM(N62:N66) -> 10 | O67: =N67 -> 10
B68: Costo de RRHH por mes (USD) - Año 2028
B69: Puesto | C69: Enero | D69: Febrero | E69: Marzo | F69: Abril | G69: Mayo | H69: Junio | I69: Julio | J69: Agosto | K69: Septiembre | L69: Octubre | M69: Noviembre | N69: Diciembre | O69: Total anual
B70: Gerente General (Fundador / CEO) | C70: =C62*$L$16 -> 2439.8 | D70: =D62*$L$16 -> 2439.8 | E70: =E62*$L$16 -> 2439.8 | F70: =F62*$L$16 -> 2439.8 | G70: =G62*$L$16 -> 2439.8 | H70: =H62*$L$16 -> 2439.8 | I70: =I62*$L$16 -> 2439.8 | J70: =J62*$L$16 -> 2439.8 | ... N70: =N62*$L$16 -> 2439.8 | O70: =SUM(C70:N70) -> 29277.6
B71: Gerente de Sistemas (Fundador / CTO) | C71: =C63*$L$17 -> 2439.8 | D71: =D63*$L$17 -> 2439.8 | E71: =E63*$L$17 -> 2439.8 | F71: =F63*$L$17 -> 2439.8 | G71: =G63*$L$17 -> 2439.8 | H71: =H63*$L$17 -> 2439.8 | I71: =I63*$L$17 -> 2439.8 | J71: =J63*$L$17 -> 2439.8 | ... N71: =N63*$L$17 -> 2439.8 | O71: =SUM(C71:N71) -> 29277.6
B72: Desarrollador | C72: =C64*$L$18 -> 2195.94 | D72: =D64*$L$18 -> 2195.94 | E72: =E64*$L$18 -> 2195.94 | F72: =F64*$L$18 -> 2195.94 | G72: =G64*$L$18 -> 2195.94 | H72: =H64*$L$18 -> 2195.94 | I72: =I64*$L$18 -> 2195.94 | J72: =J64*$L$18 -> 2195.94 | ... N72: =N64*$L$18 -> 2195.94 | O72: =SUM(C72:N72) -> 26351.28
B73: Técnico de instalación y soporte | C73: =C65*$L$19 -> 2684.86 | D73: =D65*$L$19 -> 4027.29 | E73: =E65*$L$19 -> 4027.29 | F73: =F65*$L$19 -> 4027.29 | G73: =G65*$L$19 -> 4027.29 | H73: =H65*$L$19 -> 4027.29 | I73: =I65*$L$19 -> 4027.29 | J73: =J65*$L$19 -> 4027.29 | ... N73: =N65*$L$19 -> 4027.29 | O73: =SUM(C73:N73) -> 46985.05
B74: Vendedor | C74: =C66*$L$20 -> 3661.5 | D74: =D66*$L$20 -> 3661.5 | E74: =E66*$L$20 -> 3661.5 | F74: =F66*$L$20 -> 3661.5 | G74: =G66*$L$20 -> 3661.5 | H74: =H66*$L$20 -> 3661.5 | I74: =I66*$L$20 -> 4882 | J74: =J66*$L$20 -> 4882 | ... N74: =N66*$L$20 -> 4882 | O74: =SUM(C74:N74) -> 51261
B75: TOTAL | C75: =SUM(C70:C74) -> 13421.9 | D75: =SUM(D70:D74) -> 14764.33 | E75: =SUM(E70:E74) -> 14764.33 | F75: =SUM(F70:F74) -> 14764.33 | G75: =SUM(G70:G74) -> 14764.33 | H75: =SUM(H70:H74) -> 14764.33 | I75: =SUM(I70:I74) -> 15984.83 | J75: =SUM(J70:J74) -> 15984.83 | ... N75: =SUM(N70:N74) -> 15984.83 | O75: =SUM(C75:N75) -> 183152.53

Sheet Mod. egresos
F1: Modelo de egresos
B3: Evolución de la participación
B4: 2026 | C4: 2027 | D4: 2028
B5: =Hipótesis!C24 -> 0.03 | C5: =Hipótesis!C25 -> 0.08 | D5: =Hipótesis!C26 -> 0.15
B6: =Hipótesis!D24 -> 48960 | C6: =Hipótesis!D25 -> 130560 | D6: =Hipótesis!D26 -> 244800
B8: Costos totales (USD)
A9: Concepto | B9: 2026 | C9: 2027 | D9: 2028
A10: Costos fijos | B10: ='Costos fijos'!$G$5 -> 25440 | C10: ='Costos fijos'!$H$5 -> 33300 | D10: ='Costos fijos'!$I$5 -> 37260
A11: Costos variables | B11: ='Costos variables'!$H$6 -> 5402 | C11: ='Costos variables'!$I$6 -> 11065.9 | D11: ='Costos variables'!$J$6 -> 17774.3
A12: Costos de RRHH | B12: ='Costos RRHH'!$H$6 -> 122984.64 | C12: ='Costos RRHH'!$I$6 -> 150323.36 | D12: ='Costos RRHH'!$J$6 -> 183152.53
A13: Egresos totales | B13: =SUM(B10:B12) -> 153826.64 | C13: =SUM(C10:C12) -> 194689.26 | D13: =SUM(D10:D12) -> 238186.83
A14: Ingresos proyectados | B14: =+'Mod. ingresos'!C30 -> 20863 | C14: =+'Mod. ingresos'!D30 -> 79130 | D14: =+'Mod. ingresos'!E30 -> 160047
A15: Resultado operativo (antes de inversión, amortizaciones e impuestos) | B15: =B14-B13 -> -132963.64 | C15: =C14-C13 -> -115559.26 | D15: =D14-D13 -> -78139.83
A16: Egresos sobre ingresos | B16: =IFERROR(B13/B14,"") -> 7.3731793 | C16: =IFERROR(C13/C14,"") -> 2.4603723 | D16: =IFERROR(D13/D14,"") -> 1.4882305
B18: Composición de los egresos
A19: Concepto | B19: 2026 | C19: 2027 | D19: 2028
A20: Costos fijos | B20: =IFERROR(B10/B$13,"") -> 0.16538098 | C20: =IFERROR(C10/C$13,"") -> 0.17104179 | D20: =IFERROR(D10/D$13,"") -> 0.15643182
A21: Costos variables | B21: =IFERROR(B11/B$13,"") -> 0.035117454 | C21: =IFERROR(C11/C$13,"") -> 0.05683878 | D21: =IFERROR(D11/D$13,"") -> 0.074623353
A22: Costos de RRHH | B22: =IFERROR(B12/B$13,"") -> 0.79950157 | C22: =IFERROR(C12/C$13,"") -> 0.77211943 | D22: =IFERROR(D12/D$13,"") -> 0.76894482

Sheet Mod. inversión

Sheet Amortizaciones

Sheet Presupuesto financiero

Sheet Estructura

Sheet Riesgos
B1: Riesgos
B3: Posibles riesgos
B5: R1: No alcanzar el volumen mínimo de comercios
B6: R2: Rotación de comercios antes de amortizar el alta
B7: R3: Ruptura de un conector con un sistema de punto de venta
B8: R4: Sostenibilidad financiera de los primeros 18 a 24 meses
B9: R5: Restricción a la importación de sensores y gateways
B10: R6: Salto cambiario o inflación por encima de lo proyectado
B11: R7: Incidente de privacidad o pérdida de datos del comercio
B12: R8: Pérdida, robo o rotura del equipamiento en comodato
B13: R9: Dependencia de los dos socios fundadores
B14: R10: Entrada de un competidor local con precio agresivo

Sheet Matriz de riesgos
B2: Riesgo | C2: Descripción | D2: Causas | E2: Efectos cuantitativos (USD) | F2: Efectos cualitativos | G2: Probabilidad (1-5) | H2: Impacto (1-5) | I2: Nivel de riesgo (P x I) | L2: Escalas de valoración
B3: R1 | C3: No alcanzar el volumen mínimo de comercios. La captación queda por debajo de las 102, 272 y 510 altas acumuladas que proyecta el plan, de modo que el ingreso recurrente no llega a cubrir la estructura fija. | D3: - Tasa de conversión por visita menor a la prevista | E3: Cada 10% de desvío sobre las 510 altas del año 3 equivale a unos USD 16.000 de ingreso anual no realizado. Un desvío del 30% deja el ingreso 2028 en torno de USD 112.000, por debajo del costo de la dotación prevista. | F3: Estructura sobredimensionada frente al ingreso, necesidad de reducir dotación y pérdida de la masa crítica de pares que da valor al benchmarking. | G3: 4 | H3: 5 | I3: =G3*H3 -> 20 | L3: Probabilidad (1 a 5) | M3: Impacto (1 a 5) | N3: Impacto \ Probabilidad | O3: Muy improbable (1) | P3: No es probable (2) | Q3: Posible (3) | R3: Probable (4) | S3: Muy probable (5)
D4: - Resistencia del comerciante a instalar equipos en su local | L4: 1: Muy improbable | M4: 1: Insignificante | N4: Catastrófico (5) | P4: R7 | R4: R1 - R4
D5: - Densidad efectiva del eje menor a la relevada | L5: 2: No es probable | M5: 2: Menor | N5: Importante (4) | P5: R10 | Q5: R5 - R6 - R9 | R5: R2 - R3
B6: R2 | C6: Rotación de comercios antes de amortizar el alta. El comercio se da de baja antes de que el abono acumulado recupere el costo del alta y del equipamiento instalado en su local. | D6: - Alta rotación propia del comercio minorista | E6: Una baja del Plan Vidriera antes del mes doce deja sin recuperar los USD 60 del alta más las tres horas de técnico y el reacondicionamiento del equipo retirado. | F6: Erosión de la base instalada, mayor esfuerzo comercial para sostener el mismo stock de clientes y deterioro de la comparación sectorial. | G6: 4 | H6: 4 | I6: =G6*H6 -> 16 | L6: 3: Posible | M6: 3: Moderado | N6: Moderado (3) | Q6: R8
D7: - Bajo uso de la plataforma tras las primeras semanas | L7: 4: Probable | M7: 4: Importante | N7: Menor (2)
D8: - Estacionalidad del rubro indumentaria | L8: 5: Muy probable | M8: 5: Catastrófico | N8: Insignificante (1)
B9: R3 | C9: Ruptura de un conector con un sistema de punto de venta. Uno de los siete sistemas de punto de venta integrados cambia o deprecia su API y el conector deja de funcionar. | D9: - Deprecación de la API por el proveedor del punto de venta | E9: Horas del Desarrollador destinadas a rehacer el conector en lugar de al roadmap, más el ingreso en riesgo de los comercios que operan con ese sistema. | F9: Incumplimiento del acuerdo de nivel de servicio y pérdida de confianza en un diferencial que es la principal barrera de entrada de la empresa. | G9: 4 | H9: 4 | I9: =G9*H9 -> 16 | O9: Bajo (1-6): Riesgos que probablemente no sucederán o que, si lo hacen, no tendrán consecuencias significativas.
D10: - Cambio de versión sin aviso previo | O10: Moderado (7-12): Riesgos que pueden causar contratiempos, pero son manejables con medidas adecuadas.
D11: - Consolidación o discontinuidad de un proveedor | O11: Alto (13-20): Riesgos que requieren atención inmediata y estrategias de mitigación rigurosas.
B12: R4 | C12: Sostenibilidad financiera de los primeros 18 a 24 meses. El déficit acumulado hasta alcanzar el punto de equilibrio supera la capacidad de aporte de los socios y la inversión inicial prevista. | D12: - Ingresos de USD 20.863 en 2026 contra una estructura fija muy superior | E12: El resultado operativo se mantiene negativo durante los dos primeros ejercicios; el déficit acumulado debe cubrirse con capital propio o financiamiento. | F12: Dependencia del aporte de los socios, pérdida de autonomía en la toma de decisiones y presión para acelerar la captación por encima de lo que soporta la capacidad operativa. | G12: 4 | H12: 5 | I12: =G12*H12 -> 20 | O12: Crítico (21-25): Riesgos que pueden poner en peligro la viabilidad del proyecto y requieren acciones urgentes.
D13: - Incorporaciones de dotación anteriores al ingreso que las financia
D14: - Demora en la cobranza y morosidad de los primeros clientes
B15: R5 | C15: Restricción a la importación de sensores y gateways. El equipamiento de conteo, de origen importado, no puede reponerse en tiempo o su costo se incrementa de manera significativa. | D15: - Cambios en el régimen de importaciones y licencias no automáticas | E15: Mayor costo del capital de trabajo por lote de reposición y altas del Plan Vidriera postergadas por falta de stock, con el ingreso recurrente diferido. | F15: Incumplimiento de las fechas de instalación comprometidas por el vendedor y deterioro de la experiencia inicial del cliente. | G15: 3 | H15: 4 | I15: =G15*H15 -> 12
D16: - Demoras aduaneras en la nacionalización
D17: - Aumento del costo en origen o del flete
B18: R6 | C18: Salto cambiario o inflación por encima de lo proyectado. La lista de precios está denominada en dólares pero se cobra en pesos con ajuste por índice, mientras los sueldos se pagan en pesos. | D18: - Volatilidad cambiaria y ampliación de la brecha | E18: Erosión del valor real del abono cobrado entre la facturación y la cobranza, y aumento de la masa salarial por encima del ingreso ajustado. | F18: Necesidad de renegociar precios con la base instalada, con riesgo de bajas, y pérdida de previsibilidad en la planificación. | G18: 3 | H18: 4 | I18: =G18*H18 -> 12
D19: - Inflación superior a la proyección del REM
D20: - Rezago del índice de ajuste frente a la suba de costos
B21: R7 | C21: Incidente de privacidad o pérdida de datos del comercio. Acceso indebido, filtración o pérdida de los datos de ventas y de conteo que los comercios confían a la plataforma. | D21: - Vulnerabilidad en la plataforma o en un conector | E21: Costos de recuperación, notificación y eventual sanción bajo la Ley 25.326, más el ingreso perdido por las bajas que el incidente provoque. | F21: Daño reputacional severo en un negocio cuya propuesta de valor se apoya en la privacidad por diseño; pérdida de la principal respuesta a la objeción del comerciante. | G21: 2 | H21: 5 | I21: =G21*H21 -> 10
D22: - Error humano en la gestión de credenciales
D23: - Falla en la política de respaldos
B24: R8 | C24: Pérdida, robo o rotura del equipamiento en comodato. Los sensores, contadores y gateways entregados en comodato no se recuperan o se recuperan sin posibilidad de reacondicionamiento. | D24: - Cierre abrupto del local sin devolución del equipo | E24: Reposición del equipamiento no recuperado, que se suma al capital de trabajo del período sin generar una nueva alta. | F24: Deterioro de la rotación del capital de trabajo, que es una de las condiciones que vuelven viable el modelo de abono bajo. | G24: 3 | H24: 3 | I24: =G24*H24 -> 9
D25: - Robo o daño en el punto de instalación
D26: - Desgaste por encima de la vida útil estimada
B27: R9 | C27: Dependencia de los dos socios fundadores. La conducción estratégica, técnica y comercial se concentra en dos personas que además ejecutan tareas operativas. | D27: - Ausencia prolongada o desvinculación de un socio | E27: Detención del desarrollo o de la conducción comercial, con impacto directo sobre el ritmo de altas y sobre el mantenimiento de los conectores. | F27: Vulnerabilidad estructural de la organización y dificultad para incorporar inversores que evalúan la continuidad del equipo. | G27: 3 | H27: 4 | I27: =G27*H27 -> 12
D28: - Concentración del conocimiento técnico sin documentar
D29: - Sobrecarga por acumulación de funciones
B30: R10 | C30: Entrada de un competidor local con precio agresivo. Un competidor local replica la propuesta con un abono menor, apoyado en los mismos dispositivos de conteo disponibles en el mercado. | D30: - Baja barrera de entrada en la capa de hardware | E30: Presión a la baja sobre el abono y aumento del costo de adquisición por comercio en los ejes disputados. | F30: Pérdida de la ventaja de ser el primero en el corredor y erosión del margen que sostiene la estructura. | G30: 2 | H30: 4 | I30: =G30*H30 -> 8
D31: - Imitación del modelo comercial una vez validado
D32: - Estrategia de precio por debajo del costo para ganar participación

Sheet Cuadro de evaluación de riesgos
C1: Cuadro de evaluación de riesgos
C3: Impacto \ Probabilidad | D3: Muy improbable (1) | E3: No es probable (2) | F3: Posible (3) | G3: Probable (4) | H3: Muy probable (5)
C4: Catastrófico (5) | E4: R7 | G4: R1 - R4 | K4: Bajo (1-6): Riesgos que probablemente no sucederán o que, si lo hacen, no tendrán consecuencias significativas.
C5: Importante (4) | E5: R10 | F5: R5 - R6 - R9 | G5: R2 - R3 | K5: Moderado (7-12): Riesgos que pueden causar contratiempos, pero son manejables con medidas adecuadas.
C6: Moderado (3) | F6: R8 | K6: Alto (13-20): Riesgos que requieren atención inmediata y estrategias de mitigación rigurosas.
C7: Menor (2) | K7: Crítico (21-25): Riesgos que pueden poner en peligro la viabilidad del proyecto y requieren acciones urgentes.
C8: Insignificante (1)

Sheet Escenario 1

Sheet Escenario 2

Sheet Escenario 3

Sheet Plan de Contingencia
